HW/01GRUPO1/02verilog/Liss/FIFO1/FIFO/fifo.v
module fifo # (parameter abits = 4, dbits = 3)(
    input clock,
    input reset,
    input wr,
    input rd,
  input [dbits-1:0] din,
    output empty,
    output full,
  output [dbits-1:0] dout
    );
 
wire db_wr, db_rd;
reg dffw1, dffw2, dffr1, dffr2;
reg [dbits-1:0] out;
 
always @ (posedge clock) dffw1 <= wr; 
always @ (posedge clock) dffw2 <= dffw1;
 
assign db_wr = ~dffw1 & dffw2; //monostable multivibrator to detect only one pulse of the button
 
always @ (posedge clock) dffr1 <= rd;
always @ (posedge clock) dffr2 <= dffr1;
 
assign db_rd = ~dffr1 & dffr2; //monostable multivibrator to detect only one pulse of the button
 
 
reg [dbits-1:0] regarray[2**abits-1:0]; //number of words in fifo = 2^(number of address bits)
reg [abits-1:0] wr_reg, wr_next, wr_succ; //points to the register that needs to be written to
reg [abits-1:0] rd_reg, rd_next, rd_succ; //points to the register that needs to be read from
reg full_reg, empty_reg, full_next, empty_next;
 
assign wr_en = db_wr & ~full; //only write if write signal is high and fifo is not full
 
//always block for write operation
always @ (posedge clock)
 begin
  if(wr_en)
   regarray[wr_reg] <= din;  //at wr_reg location of regarray store what is given at din
 
 end
  
//always block for read operation
always @ (posedge clock)
 begin
  if(db_rd)
   out <= regarray[rd_reg];
 end
  
 
always @ (posedge clock or posedge reset)
 begin
  if (reset)
   begin
   wr_reg <= 0;
   rd_reg <= 0;
   full_reg <= 1'b0;
   empty_reg <= 1'b1;
   end
   
  else
   begin
   wr_reg <= wr_next; //created the next registers to avoid the error of mixing blocking and non blocking assignment to the same signal
   rd_reg <= rd_next;
   full_reg <= full_next;
   empty_reg <= empty_next;
   end
 end
  
always @(*)
 begin
  wr_succ = wr_reg + 1; //assigned to new value as wr_next cannot be tested for in same always block
  rd_succ = rd_reg + 1; //assigned to new value as rd_next cannot be tested for in same always block
  wr_next = wr_reg;  //defaults state stays the same
  rd_next = rd_reg;  //defaults state stays the same
  full_next = full_reg;  //defaults state stays the same
  empty_next = empty_reg;  //defaults state stays the same
   
   case({db_wr,db_rd})
    //2'b00: do nothing LOL..
     
    2'b01: //read
     begin
      if(~empty) //if fifo is not empty continue
       begin
        rd_next = rd_succ;
        full_next = 1'b0;
       if(rd_succ == wr_reg) //all data has been read
         empty_next = 1'b1;  //its empty again
       end
     end
     
    2'b10: //write
     begin
       
      if(~full) //if fifo is not full continue
       begin
        wr_next = wr_succ;
        empty_next = 1'b0;
        if(wr_succ == (2**abits-1)) //all registers have been written to
         full_next = 1'b1;   //its full now
       end
     end
      
    2'b11: //read and write
     begin
      wr_next = wr_succ;
      rd_next = rd_succ;
     end
     //no empty or full flag will be checked for or asserted in this state since data is being written to and read from together it can  not get full in this state.
    endcase
    
 
 end
 
assign full = full_reg;
assign empty = empty_reg;
assign dout = out;
endmodule

HW/01GRUPO1/02verilog/Liss/FIFO/fifo_TB.v
//----------------------------------------------------------------------------
`timescale 1 ns / 100 ps

module fifo_TB;

parameter tck              = 2;       // clock period in ns
//----------------------------------------------------------------------------
//----------------------------------------------------------------------------

reg clk;
reg rst;

reg rd,wr;
reg [7:0] data_in;

//----------------------------------------------------------------------------
// Device Under Test 
//------------------------------------------------------------------

fifo  uut(.reset(rst),.clock(clk),.rd(rd),.wr(wr),.din(data_in));


/* Clocking device */
initial begin
	clk <= 0;
	rst <=1;
	#(2*tck) rst=0;
	rd <=0;
	wr<=0;
end

always #(tck/2) clk <= ~clk;


initial begin
#4;
data_in="h"; #1 wr=1; #2 wr=0;
data_in="o"; #1 wr=1; #2 wr=0;
data_in="l"; #1 wr=1; #2 wr=0;
data_in="a"; #1 wr=1; #2 wr=0;
data_in=" "; #1 wr=1; #2 wr=0;
data_in="m"; #1 wr=1; #2 wr=0;
data_in="u"; #1 wr=1; #2 wr=0;
data_in="n"; #1 wr=1; #2 wr=0;
data_in="d"; #1 wr=1; #2 wr=0;
data_in="o"; #1 wr=1; #2 wr=0;
data_in="."; #1 wr=1; #2 wr=0;
data_in="1"; #1 wr=1; #2 wr=0;
data_in="2"; #1 wr=1; #2 wr=0;
data_in="3"; #1 wr=1; #2 wr=0;
data_in="4"; #1 wr=1; #2 wr=0;
data_in="5"; #1 wr=1; #2 wr=0;
data_in="6"; #1 wr=1; #2 wr=0;
data_in="7"; #1 wr=1; #2 wr=0;
data_in="8"; #1 wr=1; #2 wr=0;
data_in="9"; #1 wr=1; #2 wr=0;
data_in="0"; #1 wr=1; #2 wr=0;

#1 rd=1; #2 rd=0;
#1 rd=1; #2 rd=0;
#1 rd=1; #2 rd=0;

data_in="a"; #1 wr=1; rd=0;#2 wr=0;rd=1;
data_in="b"; #1 wr=1; #2 wr=0;
data_in="c"; #1 wr=1; #2 wr=0;
data_in="d"; #1 wr=1; #2 wr=0;

#1 rd=1; #2 rd=0;
#1 rd=1; #2 rd=0;
#1 rd=1; #2 rd=0;
#1 rd=1; #2 rd=0;
#1 rd=1; #2 rd=0;
#1 rd=1; #2 rd=0;
#1 rd=1; #2 rd=0;
#1 rd=1; #2 rd=0;
#1 rd=1; #2 rd=0;
#1 rd=1; #2 rd=0;
#1 rd=1; #2 rd=0;
#1 rd=1; #2 rd=0;
#1 rd=1; #2 rd=0;
#1 rd=1; #2 rd=0;
#1 rd=1; #2 rd=0;
#1 rd=1; #2 rd=0;
#1 rd=1; #2 rd=0;
#1 rd=1; #2 rd=0;


end
initial begin: TEST_CASE
     $dumpfile("fifo_TB.vcd");
     $dumpvars(-1, uut);
     #(200) $finish;
   end

endmodule //

HW/01GRUPO1/02verilog/Liss/FIFO/simulation/fifo_TB.vcd
$date
	Fri Mar  9 12:27:42 2018
$end
$version
	Icarus Verilog
$end
$timescale
	100ps
$end
$scope module fifo_TB $end
$scope module uut $end
$var wire 1 ! clock $end
$var wire 1 " db_rd $end
$var wire 1 # db_wr $end
$var wire 3 $ din [2:0] $end
$var wire 3 % dout [2:0] $end
$var wire 1 & empty $end
$var wire 1 ' full $end
$var wire 1 ( rd $end
$var wire 1 ) reset $end
$var wire 1 * wr $end
$var wire 1 + wr_en $end
$var reg 1 , dffr1 $end
$var reg 1 - dffr2 $end
$var reg 1 . dffw1 $end
$var reg 1 / dffw2 $end
$var reg 1 0 empty_next $end
$var reg 1 1 empty_reg $end
$var reg 1 2 full_next $end
$var reg 1 3 full_reg $end
$var reg 3 4 out [2:0] $end
$var reg 4 5 rd_next [3:0] $end
$var reg 4 6 rd_reg [3:0] $end
$var reg 4 7 rd_succ [3:0] $end
$var reg 4 8 wr_next [3:0] $end
$var reg 4 9 wr_reg [3:0] $end
$var reg 4 : wr_succ [3:0] $end
$upscope $end
$upscope $end
$enddefinitions $end
#0
$dumpvars
b1 :
b0 9
b0 8
b1 7
b0 6
b0 5
bx 4
03
02
11
10
x/
x.
x-
x,
x+
x*
1)
x(
0'
1&
bx %
bx $
x#
x"
0!
$end
#10
1!
#20
0!
#30
1!
#40
0!
0*
0(
b0 $
0)
#50
0+
0#
1.
0,
1!
1*
#60
0!
#70
1+
00
b1 8
0"
1#
0-
1/
0.
1!
b111 $
0*
#80
0!
1*
#90
0+
b10 :
0#
01
0&
b1 9
1.
0/
1!
#100
0!
b100 $
0*
#110
1/
1!
1*
#120
0!
#130
1+
b10 8
1#
0.
1!
b1 $
0*
#140
0!
1*
#150
0+
b11 :
0#
b10 9
0/
1.
1!
#160
0!
b0 $
0*
#170
1/
1!
1*
#180
0!
#190
1+
b11 8
1#
0.
1!
b101 $
0*
#200
0!
1*
#210
0+
b100 :
0#
b11 9
1.
0/
1!
#220
0!
0*
#230
1/
1!
1*
#240
0!
#250
1+
b100 8
1#
0.
1!
b110 $
0*
#260
0!
1*
#270
0+
b101 :
0#
b100 9
0/
1.
1!
#280
0!
b100 $
0*
#290
1/
1!
1*
#300
0!
#310
1+
b101 8
1#
0.
1!
b111 $
0*
#320
0!
1*
#330
0+
b110 :
0#
b101 9
1.
0/
1!
#340
0!
b110 $
0*
#350
1/
1!
1*
#360
0!
#370
1+
b110 8
1#
0.
1!
b1 $
0*
#380
0!
1*
#390
0+
b111 :
0#
b110 9
0/
1.
1!
#400
0!
b10 $
0*
#410
1/
1!
1*
#420
0!
#430
1+
b111 8
1#
0.
1!
b11 $
0*
#440
0!
1*
#450
0+
b1000 :
0#
b111 9
1.
0/
1!
#460
0!
b100 $
0*
#470
1/
1!
1*
#480
0!
#490
1+
b1000 8
1#
0.
1!
b101 $
0*
#500
0!
1*
#510
0+
b1001 :
0#
b1000 9
0/
1.
1!
#520
0!
b110 $
0*
#530
1/
1!
1*
#540
0!
#550
1+
b1001 8
1#
0.
1!
b111 $
0*
#560
0!
1*
#570
0+
b1010 :
0#
b1001 9
1.
0/
1!
#580
0!
b0 $
0*
#590
1/
1!
1*
#600
0!
#610
1+
b1010 8
1#
0.
1!
b1 $
0*
#620
0!
1*
#630
0+
b1011 :
0#
b1010 9
0/
1.
1!
#640
0!
b0 $
0*
#650
1/
1!
1*
#660
0!
#670
1+
b1011 8
1#
0.
1!
0*
#680
0!
1(
#690
0+
b1100 :
0#
b1011 9
0/
1,
1!
#700
0!
0(
#710
1-
1!
1(
#720
0!
#730
b1 5
1"
0,
1!
0(
#740
0!
1(
#750
b10 7
0"
b1 6
b111 4
b111 %
0-
1,
1!
#760
0!
b1 $
0(
#770
b10 5
1"
1.
0,
1-
1!
1*
#780
0!
#790
1+
b1100 8
b11 7
0"
1#
b10 6
b1 4
b1 %
0-
1,
1/
0.
1!
b10 $
1(
0*
#800
0!
1*
#810
0+
b1101 :
0#
b1100 9
1.
0/
1-
1!
#820
0!
b11 $
0*
#830
1/
1!
1*
#840
0!
#850
1+
b1101 8
1#
0.
1!
b100 $
0*
#860
0!
1*
#870
0+
b1110 :
0#
b1101 9
0/
1.
1!
#880
0!
0*
#890
1+
b1110 8
1#
0.
1/
1!
#900
0!
#910
b11 5
1"
0+
b1111 :
0#
b1110 9
0,
0/
1!
0(
#920
0!
1(
#930
b100 7
0"
b11 6
1,
0-
b101 4
b101 %
1!
#940
0!
0(
#950
1-
1!
1(
#960
0!
#970
b100 5
1"
0,
1!
0(
#980
0!
1(
#990
b101 7
0"
b100 6
b110 4
b110 %
0-
1,
1!
#1000
0!
0(
#1010
1-
1!
1(
#1020
0!
#1030
b101 5
1"
0,
1!
0(
#1040
0!
1(
#1050
b110 7
0"
b101 6
1,
0-
b111 4
b111 %
1!
#1060
0!
0(
#1070
1-
1!
1(
#1080
0!
#1090
b110 5
1"
0,
1!
0(
#1100
0!
1(
#1110
b111 7
0"
b110 6
b1 4
b1 %
0-
1,
1!
#1120
0!
0(
#1130
1-
1!
1(
#1140
0!
#1150
b111 5
1"
0,
1!
0(
#1160
0!
1(
#1170
b1000 7
0"
b111 6
1,
0-
b11 4
b11 %
1!
#1180
0!
0(
#1190
1-
1!
1(
#1200
0!
#1210
b1000 5
1"
0,
1!
0(
#1220
0!
1(
#1230
b1001 7
0"
b1000 6
b101 4
b101 %
0-
1,
1!
#1240
0!
0(
#1250
1-
1!
1(
#1260
0!
#1270
b1001 5
1"
0,
1!
0(
#1280
0!
1(
#1290
b1010 7
0"
b1001 6
1,
0-
b111 4
b111 %
1!
#1300
0!
0(
#1310
1-
1!
1(
#1320
0!
#1330
b1010 5
1"
0,
1!
0(
#1340
0!
1(
#1350
b1011 7
0"
b1010 6
b1 4
b1 %
0-
1,
1!
#1360
0!
0(
#1370
1-
1!
1(
#1380
0!
#1390
b1011 5
1"
0,
1!
0(
#1400
0!
1(
#1410
b1100 7
0"
b1011 6
1,
0-
b0 4
b0 %
1!
#1420
0!
0(
#1430
b1100 5
1"
1-
0,
1!
#1440
0!
#1450
b1101 7
0"
b1100 6
0-
b10 4
b10 %
1!
