HW/03GRUPO3/02verilog/FIFO/FIFO.v
module FIFO
  (input  rst, Pclk, 
    input  rd, wr,
    input  [9:0] data_in,
    output reg [9:0] data_out, 
    output reg empty, 
    output reg full);
 
    parameter depth = (1 << adr_width);  //preguntar....................................
    parameter adr_width = 16; 

  reg [9:0] array_reg [depth-1:0]; 
  reg [adr_width-1:0] w_ptr;
  reg [adr_width-1:0] r_ptr;


    always @(posedge Pclk) begin
       if (rst) begin
            full <= 0;
            empty <= 1;
            w_ptr <= 0;
            r_ptr <= 0;
       end
       else begin
    	   case ({wr, rd})
    		 2'b01: // read
    		    if (~empty) begin //not empty
                   data_out<= array_reg[r_ptr];
    		       r_ptr <= r_ptr + 1;
    		       full <= 1'b0;
    		       if (r_ptr==w_ptr)
    		           empty <= 1'b1; //-------------- ESTE SI FUNCIONA
    		    end
    		 2'b10: // write
    		    if (~full) begin // not full
                   array_reg[w_ptr] <= data_in;
    		       w_ptr <= w_ptr + 1;
    		       empty <= 1'b0;
    		       if (w_ptr==r_ptr)
    		          full <= 1'b0; //-----------------NO ESTA FUNCIONANA EL FULL SE ASIGANA EN 1 AUN SI LA POSICION DE LECTURA NO ES LA MISMA QUE LA DE ESCRITURA
    		    end
    		 2'b11: // write and read
    		    begin
    		       w_ptr <= w_ptr + 1;
    		       r_ptr <= r_ptr + 1;
    		    end
    	   endcase
        end
    end
endmodule

HW/03GRUPO3/02verilog/FIFO/FIFO_TB.v
//----------------------------------------------------------------------------

module FIFO_TB;

// (input  rst, Pclk, input  rd, wr, input  [dat_width-1:0] data_in, output [dat_width-1:0] data_out, output empty, output full);

//
//----------------------------------------------------------------------------
reg Pclk=0;
reg rst;
reg rd=0;
reg wr=0;
reg [9:0] data_in;
//----------------------------------------------------------------------------
// Device Under Test 
//------------------------------------------------------------------

FIFO  uut(.rst(rst),.Pclk(Pclk),.data_in(data_in),.wr(wr),.rd(rd), . data_out(data_out), .empty(empty), .full(full));

always #1 Pclk <= ~Pclk;

/* Clocking device */
initial begin
rst <=1;
#50;
rst<=0;
data_in=1111111111;  #50;
wr <= ~wr;#5; 
wr <= ~wr;#5;  
data_in=1010101010;  #50; 
wr <= ~wr;#5; 
wr <= ~wr;#5; 
data_in=1111100000;  #50;  
wr <= ~wr;#5; 
wr <= ~wr;#5; 
rd <= ~rd;#10;
end

initial begin: TEST_CASE
     $dumpfile("FIFO_TB.vcd");
     $dumpvars(-1, uut);
     #(20000) $finish;
   end

endmodule //

HW/03GRUPO3/02verilog/FIFO/simulation/FIFO_TB.vcd
$date
	Wed May 16 12:03:17 2018
$end
$version
	Icarus Verilog
$end
$timescale
	1s
$end
$scope module FIFO_TB $end
$scope module uut $end
$var wire 1 ! Pclk $end
$var wire 10 " data_in [9:0] $end
$var wire 1 # rd $end
$var wire 1 $ rst $end
$var wire 1 % wr $end
$var reg 10 & data_out [9:0] $end
$var reg 1 ' empty $end
$var reg 1 ( full $end
$var reg 16 ) r_ptr [15:0] $end
$var reg 16 * w_ptr [15:0] $end
$upscope $end
$upscope $end
$enddefinitions $end
#0
$dumpvars
bx *
bx )
x(
x'
bx &
0%
1$
0#
bx "
0!
$end
#1
b0 )
b0 *
1'
0(
1!
#2
0!
#3
1!
#4
0!
#5
1!
#6
0!
#7
1!
#8
0!
#9
1!
#10
0!
#11
1!
#12
0!
#13
1!
#14
0!
#15
1!
#16
0!
#17
1!
#18
0!
#19
1!
#20
0!
#21
1!
#22
0!
#23
1!
#24
0!
#25
1!
#26
0!
#27
1!
#28
0!
#29
1!
#30
0!
#31
1!
#32
0!
#33
1!
#34
0!
#35
1!
#36
0!
#37
1!
#38
0!
#39
1!
#40
0!
#41
1!
#42
0!
#43
1!
#44
0!
#45
1!
#46
0!
#47
1!
#48
0!
#49
1!
#50
0!
0$
b111000111 "
#51
1!
#52
0!
#53
1!
#54
0!
#55
1!
#56
0!
#57
1!
#58
0!
#59
1!
#60
0!
#61
1!
#62
0!
#63
1!
#64
0!
#65
1!
#66
0!
#67
1!
#68
0!
#69
1!
#70
0!
#71
1!
#72
0!
#73
1!
#74
0!
#75
1!
#76
0!
#77
1!
#78
0!
#79
1!
#80
0!
#81
1!
#82
0!
#83
1!
#84
0!
#85
1!
#86
0!
#87
1!
#88
0!
#89
1!
#90
0!
#91
1!
#92
0!
#93
1!
#94
0!
#95
1!
#96
0!
#97
1!
#98
0!
#99
1!
#100
0!
1%
#101
0'
b1 *
1!
#102
0!
#103
b10 *
1!
#104
0!
#105
1!
0%
#106
0!
#107
1!
#108
0!
#109
1!
#110
0!
b1100010010 "
