HW/03GRUPO3/02verilog/CAMARA/FIFO.v
module FIFO
  (input  rst, Pclk, 
    input  rd, wr,
    input  [9:0] data_in,
    output reg [9:0] data_out, 
    output reg empty, 
    output reg full);
 
    parameter depth = (1 << adr_width);  //preguntar....................................
    parameter adr_width = 16; 

  reg [9:0] array_reg [depth-1:0]; 
  reg [adr_width-1:0] w_ptr;
  reg [adr_width-1:0] r_ptr;


    always @(posedge Pclk) begin
       if (rst) begin
            full <= 0;
            empty <= 1;
            w_ptr <= 0;
            r_ptr <= 0;
       end
       else begin
    	   case ({wr, rd})
    		 2'b01: // read
    		    if (~empty) begin //not empty
                   data_out<= array_reg[r_ptr];
    		       r_ptr <= r_ptr + 1;
    		       full <= 1'b0;
    		       if (r_ptr==w_ptr)
    		           empty <= 1'b1; //-------------- ESTE SI FUNCIONA
    		    end
    		 2'b10: // write
    		    if (~full) begin // not full
                   array_reg[w_ptr] <= data_in;
    		       w_ptr <= w_ptr + 1;
    		       empty <= 1'b0;
    		       if (w_ptr==r_ptr)
    		          full <= 1'b0; //-----------------NO ESTA FUNCIONANA EL FULL SE ASIGANA EN 1 AUN SI LA POSICION DE LECTURA NO ES LA MISMA QUE LA DE ESCRITURA
    		    end
    		 2'b11: // write and read
    		    begin
    		       w_ptr <= w_ptr + 1;
    		       r_ptr <= r_ptr + 1;
              data_out<= array_reg[r_ptr];
              array_reg[w_ptr] <= data_in;
    		       w_ptr <= w_ptr + 1;
              
    		    end
    	   endcase
        end
    end
endmodule

HW/03GRUPO3/02verilog/CAMARA/div_frec.v
module div_frec(input clk, input en_div, output reg Xclk);

reg [31:0] count;


initial begin
Xclk=0;
end

always @(posedge  clk)
begin
    if (~en_div)
    begin
        count<=1;
        Xclk<=0;
    end
    else
    begin
		if (count==2)
        begin
			Xclk <=~Xclk;
			count <= 1;
	    end	
        else begin
            count <= count +1;
        end
    end
end
endmodule

HW/03GRUPO3/02verilog/CAMARA/camara.v
module camara (input capture, //.........
               input clk, 
               input Href, 
               input Vsyn, 
               input Pclk,
               input [7:0]data,
               input rst,         //---------
               input en_div,    //..........
               input rd,
               output reset,    
               output Xclk, 
               output PWDN,     
               output [9:0]data_out);
 
reg wr;
reg [9:0]data_in;
reg [20:0]counter;
wire empty;
wire full;
wire [9:0]data_out;


assign PWDN = ~capture;
assign Pclk = Xclk; /// para gtk wave
assign reset = rst;  

div_frec div( .Xclk(Xclk), .en_div(en_div), .clk(clk)); 

FIFO fif(.data_in(data_in), .Pclk(Pclk), .empty(empty), .full(full), .rd(rd), .wr(wr), .data_out(data_out), .rst(rst));

always @(posedge Pclk) begin
    if (rst)begin
         wr<=0;
        counter<=0;       
    end
    if (~PWDN )begin
         data_in <= {data[7:0],Href,Vsyn}; 
        if (Vsyn==0 && Href==1)
            wr<=1;
        else
            wr<=0;
    end
end      
endmodule

HW/03GRUPO3/02verilog/CAMARA/camara_TB.v
//`timescale 1 ns / 100 ps

module camara_TB;

reg clk=0;
reg capture;
reg Href; 
reg Vsyn;
wire Pclk; 
reg [7:0]data;
reg rst;
reg rd;
reg en_div;
wire reset;
wire Xclk;
wire PWDN;
wire data_out;


camara uut(.rd(rd), .capture(capture), .clk(clk), .Href(Href), .Vsyn(Vsyn), .data(data), .Pclk(Pclk), .rst(rst), .reset(reset), .Xclk(Xclk), .PWDN(PWDN), .en_div(en_div));

always #1 clk = ~clk;

initial begin
en_div=0; rd=0; #5;
en_div=1; rst=0; #5;
rst=1; #10;
rst=0; capture=1; Href=0; Vsyn=1; data= 8'b0;#10;
Vsyn=0; Href=1; data=8'b00000001; #10;
Href=0; data=8'b00000010; #10;
Href=1; data=8'b00000100; #10;
Href=0; data=8'b00001000; #10;
Href=1; data=8'b00010000; #10;
Href=0; data=8'b00100000; #10;
Href=1; data=8'b01000000; #10;
Href=0; Vsyn=1; data =8'b0; #10;
Vsyn=0; capture=0; 
end


initial begin: TEST_CASE
     $dumpfile("camara_TB.vcd");
     $dumpvars(-1, uut);
     #(200) $finish;
end

endmodule

HW/03GRUPO3/02verilog/CAMARA/simulation/camara_TB.vcd
$date
	Tue Jun  5 17:52:40 2018
$end
$version
	Icarus Verilog
$end
$timescale
	1s
$end
$scope module camara_TB $end
$scope module uut $end
$var wire 1 ! Href $end
$var wire 1 " PWDN $end
$var wire 1 # Pclk $end
$var wire 1 $ Vsyn $end
$var wire 1 % Xclk $end
$var wire 1 & capture $end
$var wire 1 ' clk $end
$var wire 8 ( data [7:0] $end
$var wire 10 ) data_out [9:0] $end
$var wire 1 * empty $end
$var wire 1 + en_div $end
$var wire 1 , full $end
$var wire 1 - rd $end
$var wire 1 . reset $end
$var wire 1 / rst $end
$var reg 21 0 counter [20:0] $end
$var reg 10 1 data_in [9:0] $end
$var reg 1 2 wr $end
$scope module div $end
$var wire 1 ' clk $end
$var wire 1 + en_div $end
$var reg 1 3 Xclk $end
$var reg 32 4 count [31:0] $end
$upscope $end
$scope module fif $end
$var wire 1 # Pclk $end
$var wire 10 5 data_in [9:0] $end
$var wire 1 - rd $end
$var wire 1 / rst $end
$var wire 1 6 wr $end
$var reg 10 7 data_out [9:0] $end
$var reg 1 8 empty $end
$var reg 1 9 full $end
$var reg 16 : r_ptr [15:0] $end
$var reg 16 ; w_ptr [15:0] $end
$upscope $end
$upscope $end
$upscope $end
$enddefinitions $end
#0
$dumpvars
bx ;
bx :
x9
x8
bx 7
x6
bx 5
bx 4
03
x2
bx 1
bx 0
x/
x.
0-
x,
0+
x*
bx )
bx (
0'
x&
0%
x$
0#
x"
x!
$end
#1
b1 4
1'
#2
0'
#3
1'
#4
0'
#5
b10 4
1'
0.
0/
1+
#6
0'
#7
b1 4
13
1#
1%
1'
#8
0'
#9
b10 4
1'
#10
0'
1.
1/
#11
b1 4
03
0#
0%
1'
#12
0'
#13
b10 4
1'
#14
0'
#15
b0 0
02
06
b0 :
b0 ;
18
1*
09
0,
b1 4
13
1#
1%
1'
#16
0'
#17
b10 4
1'
#18
0'
#19
b1 4
03
0#
0%
1'
#20
0"
0'
b0 (
1$
0!
1&
0.
0/
#21
b10 4
1'
#22
0'
#23
b1 1
b1 5
b1 4
13
1#
1%
1'
#24
0'
#25
b10 4
1'
#26
0'
#27
b1 4
03
0#
0%
1'
#28
0'
#29
b10 4
1'
#30
0'
b1 (
1!
0$
#31
12
16
b110 1
b110 5
b1 4
13
1#
1%
1'
#32
0'
#33
b10 4
1'
#34
0'
#35
b1 4
03
0#
0%
1'
#36
0'
#37
b10 4
1'
#38
0'
#39
08
0*
b1 ;
b1 4
13
1#
1%
1'
#40
0'
b10 (
0!
#41
b10 4
1'
#42
0'
#43
b1 4
03
0#
0%
1'
#44
0'
#45
b10 4
1'
#46
0'
#47
02
06
b1000 1
b1000 5
b10 ;
b1 4
13
1#
1%
1'
#48
0'
#49
b10 4
1'
#50
0'
b100 (
1!
#51
b1 4
03
0#
0%
1'
#52
0'
#53
b10 4
1'
#54
0'
#55
12
16
b10010 1
b10010 5
b1 4
13
1#
1%
1'
#56
0'
#57
b10 4
1'
#58
0'
#59
b1 4
03
0#
0%
1'
#60
0'
b1000 (
0!
#61
b10 4
1'
#62
0'
#63
02
06
b100000 1
b100000 5
b11 ;
b1 4
13
1#
1%
1'
#64
0'
#65
b10 4
1'
#66
0'
#67
b1 4
03
0#
0%
1'
#68
0'
#69
b10 4
1'
#70
0'
b10000 (
1!
#71
12
16
b1000010 1
b1000010 5
b1 4
13
1#
1%
1'
#72
0'
#73
b10 4
1'
#74
0'
#75
b1 4
03
0#
0%
1'
#76
0'
#77
b10 4
1'
#78
0'
#79
b100 ;
b1 4
13
1#
1%
1'
#80
0'
b100000 (
0!
#81
b10 4
1'
#82
0'
#83
b1 4
03
0#
0%
1'
#84
0'
#85
b10 4
1'
#86
0'
#87
b101 ;
02
06
b10000000 1
b10000000 5
b1 4
13
1#
1%
1'
#88
0'
#89
b10 4
1'
#90
0'
b1000000 (
1!
#91
b1 4
03
0#
0%
1'
#92
0'
#93
b10 4
1'
#94
0'
#95
12
16
b100000010 1
b100000010 5
b1 4
13
1#
1%
1'
#96
0'
#97
b10 4
1'
#98
0'
#99
b1 4
03
0#
0%
1'
#100
0'
b0 (
1$
0!
#101
b10 4
1'
#102
0'
#103
b110 ;
02
06
b1 1
b1 5
b1 4
13
1#
1%
1'
#104
0'
#105
b10 4
1'
#106
0'
#107
b1 4
03
0#
0%
1'
#108
0'
#109
b10 4
1'
#110
1"
0'
0&
0$
#111
b1 4
13
1#
1%
1'
#112
0'
#113
b10 4
1'
#114
0'
#115
b1 4
03
0#
0%
1'
#116
0'
#117
b10 4
1'
#118
0'
#119
b1 4
13
1#
1%
1'
#120
0'
#121
b10 4
1'
#122
0'
#123
b1 4
03
0#
0%
1'
#124
0'
#125
b10 4
1'
#126
0'
#127
b1 4
13
1#
1%
1'
#128
0'
#129
b10 4
1'
#130
0'
#131
b1 4
03
0#
0%
1'
#132
0'
#133
b10 4
1'
#134
0'
#135
b1 4
13
1#
1%
1'
#136
0'
#137
b10 4
1'
#138
0'
#139
b1 4
03
0#
0%
1'
#140
0'
#141
b10 4
1'
#142
0'
#143
b1 4
13
1#
1%
1'
#144
0'
#145
b10 4
1'
#146
0'
#147
b1 4
03
0#
0%
1'
#148
0'
#149
b10 4
1'
#150
0'
#151
b1 4
13
1#
1%
1'
#152
0'
#153
b10 4
1'
#154
0'
#155
b1 4
03
0#
0%
1'
#156
0'
#157
b10 4
1'
#158
0'
#159
b1 4
13
1#
1%
1'
#160
0'
#161
b10 4
1'
#162
0'
#163
b1 4
03
0#
0%
1'
#164
0'
#165
b10 4
1'
#166
0'
#167
b1 4
13
1#
1%
1'
#168
0'
#169
b10 4
1'
#170
0'
#171
b1 4
03
0#
0%
1'
#172
0'
#173
b10 4
1'
#174
0'
#175
b1 4
13
1#
1%
1'
#176
0'
#177
b10 4
1'
#178
0'
#179
b1 4
03
0#
0%
1'
#180
0'
#181
b10 4
1'
#182
0'
#183
b1 4
13
1#
1%
1'
#184
0'
#185
b10 4
1'
#186
0'
#187
b1 4
03
0#
0%
1'
#188
0'
#189
b10 4
1'
#190
0'
#191
b1 4
13
1#
1%
1'
#192
0'
#193
b10 4
1'
#194
0'
#195
b1 4
03
0#
0%
1'
#196
0'
#197
b10 4
1'
#198
0'
#199
b1 4
13
1#
1%
1'
