HW/03GRUPO3/02verilog/Camara/FIFO.v
module FIFO
  (input  rst, Pclk, 
    input  rd, wr,
    input  [9:0] data_in,
    output [9:0] data_out, 
    output empty, 
    output full);
 
    parameter depth = (1 << adr_width);
    parameter adr_width = 16; 

  reg [9:0] array_reg [depth-1:0]; 
  reg [adr_width-1:0] w_ptr_reg, w_ptr_next;
  reg [adr_width-1:0] r_ptr_reg, r_ptr_next;
  reg full_reg, empty_reg, full_next, empty_next;

   assign data_out = array_reg[r_ptr_reg];

   assign full = full_reg;
   assign empty = empty_reg;

    always @(posedge Pclk) begin
       if (rst) begin
            w_ptr_reg <= 0;
            r_ptr_reg <= 0;
            full_reg <= 1'b0;
            empty_reg <= 1'b1;
       end
       else begin
            w_ptr_reg <= w_ptr_next;
            r_ptr_reg <= r_ptr_next;
            full_reg <= full_next;
            empty_reg <= empty_next;
       end
      full_next = full_reg;
	  empty_next = empty_reg;
	   case ({wr, rd})
		 2'b01: // read
		    if (~empty_reg) begin //not empty
		       r_ptr_next = r_ptr_reg + 1;
		       full_next = 1'b0;
		       if (r_ptr_next==w_ptr_reg)
		           empty_next = 1'b1;
		    end
		 2'b10: // write
		    if (~full_reg) begin // not full
               array_reg[w_ptr_reg] = data_in;
		       w_ptr_next = w_ptr_reg + 1;
		       empty_next = 1'b0;
		       if (w_ptr_next==r_ptr_reg)
		          full_next = 1'b1;
		    end
		 2'b11: // write and read
		    begin
		       w_ptr_next =  w_ptr_reg + 1;
		       r_ptr_next = r_ptr_reg + 1;
		    end
	   endcase
    end
endmodule

HW/03GRUPO3/02verilog/Camara/div_frec.v
module div_frec(input clk, input en_div, output reg Xclk);

reg [31:0] count;
wire rst;

assign rst = ~en_div;

initial begin
Xclk=0;
end

always @(posedge  clk)
begin
    if (rst)
    begin
        count<=1;
        Xclk<=0;
    end
    else
    begin
		if (count==5)
        begin
			Xclk <=~Xclk;
			count <= 1;
	    end	
        else begin
            count <= count +1;
        end
    end
end
endmodule

HW/03GRUPO3/02verilog/Camara/camara.v
module camara (input capture, //buttom
               input clk, 
               input Href, 
               input Vsyn, 
               input Pclk,
               input [7:0]data,
               input rst,     //buttom rst    
               input en_div,    
               output reset,
               output Xclk, 
               output PWDN, 
               //output [9:0]data_out,
               output frame_done);

reg rd;
reg wr;
reg [9:0]data_in;
reg frame_done=0;
reg [20:0]counter;
wire empty;
wire full;
wire [9:0]data_out;


assign PWDN = ~capture;

assign reset = rst;  // _________________________lo cmabie a negado 
//assign Pclk = Xclk;---------------- para gtk wave

div_frec div( .Xclk(Xclk), .en_div(en_div), .clk(clk)); 

FIFO fif(.data_in(data_in), .Pclk(Pclk), .empty(empty), .full(full), .rd(rd), .wr(wr), .data_out(data_out), .rst(rst));



always @(posedge Pclk) begin
    if (rst)begin    
         frame_done=0;
         rd<=0;
         wr<=0; 
        counter<=0;       
    end
    else if (~PWDN)begin
         data_in <= {data,Href,Vsyn}; //---------------------------si esta asiganado data_in 
         wr<=1; //---------------------------no esta asignando 1 en escritura
         counter<=counter+1; //-----------------------------si esta contando
         if (counter<799681)begin             
            frame_done=1;
            wr<=0;
         end
    end     
    else if (~empty)begin
        rd<=1;
    end
end      
endmodule

HW/03GRUPO3/02verilog/Camara/camara_TB.v
//`timescale 1 ns / 100 ps

module camara_TB;

reg clk=0;
reg capture;
//reg data[7:0];
reg Href; 
reg Vsyn;
wire Pclk; //////////////////////////////////lo cambie 
reg [7:0]data;
reg rst;
reg en_div;
wire reset;
wire Xclk;
wire PWDN;
wire frame_done;
wire data_out;

parameter tck=6;

camara uut(.capture(capture), .clk(clk), .Href(Href), .Vsyn(Vsyn), .data(data), .Pclk(Pclk), .rst(rst), .reset(reset), .Xclk(Xclk), .PWDN(PWDN), .frame_done(frame_done), .en_div(en_div));

always #1 clk = ~clk;

initial begin
en_div=0;
#200;
en_div=1;
rst=0; 
#1000;
rst=1;
#2000;
rst=0;
capture=1;
Href=1;
Vsyn=1;
data= 8'b0;
#3000;
Href=0;
Vsyn=0;
data=8'b1;
#3000;
capture=0;
#3000;
end


initial begin: TEST_CASE
     $dumpfile("camara_TB.vcd");
     $dumpvars(-1, uut);
     #(20000) $finish;
   end

endmodule

HW/03GRUPO3/02verilog/Camara/simulation/camara_TB.vcd
$date
	Tue May  8 06:55:56 2018
$end
$version
	Icarus Verilog
$end
$timescale
	1s
$end
$scope module camara_TB $end
$scope module uut $end
$var wire 1 ! Href $end
$var wire 1 " PWDN $end
$var wire 1 # Pclk $end
$var wire 1 $ Vsyn $end
$var wire 1 % Xclk $end
$var wire 1 & capture $end
$var wire 1 ' clk $end
$var wire 8 ( data [7:0] $end
$var wire 10 ) data_out [9:0] $end
$var wire 1 * empty $end
$var wire 1 + en_div $end
$var wire 1 , full $end
$var wire 1 - reset $end
$var wire 1 . rst $end
$var reg 21 / counter [20:0] $end
$var reg 10 0 data_in [9:0] $end
$var reg 1 1 frame_done $end
$var reg 1 2 rd $end
$var reg 1 3 wr $end
$scope module div $end
$var wire 1 ' clk $end
$var wire 1 + en_div $end
$var wire 1 4 rst $end
$var reg 1 5 Xclk $end
$var reg 32 6 count [31:0] $end
$upscope $end
$scope module fif $end
$var wire 1 # Pclk $end
$var wire 10 7 data_in [9:0] $end
$var wire 10 8 data_out [9:0] $end
$var wire 1 * empty $end
$var wire 1 , full $end
$var wire 1 9 rd $end
$var wire 1 . rst $end
$var wire 1 : wr $end
$var reg 1 ; empty_next $end
$var reg 1 < empty_reg $end
$var reg 1 = full_next $end
$var reg 1 > full_reg $end
$var reg 16 ? r_ptr_next [15:0] $end
$var reg 16 @ r_ptr_reg [15:0] $end
$var reg 16 A w_ptr_next [15:0] $end
$var reg 16 B w_ptr_reg [15:0] $end
$upscope $end
$upscope $end
$upscope $end
$enddefinitions $end
#0
$dumpvars
bx B
bx A
bx @
bx ?
x>
x=
x<
x;
x:
x9
bx 8
bx 7
bx 6
05
14
x3
x2
01
bx 0
bx /
x.
x-
x,
0+
x*
bx )
bx (
0'
x&
0%
x$
0#
x"
x!
$end
#1
b1 6
1'
#2
0'
#3
1'
#4
0'
#5
1'
#6
0'
#7
1'
#8
0'
#9
1'
#10
0'
#11
1'
#12
0'
#13
1'
#14
0'
#15
1'
#16
0'
#17
1'
#18
0'
#19
1'
#20
0'
#21
1'
#22
0'
#23
1'
#24
0'
#25
1'
#26
0'
#27
1'
#28
0'
#29
1'
#30
0'
#31
1'
#32
0'
#33
1'
#34
0'
#35
1'
#36
0'
#37
1'
#38
0'
#39
1'
#40
0'
#41
1'
#42
0'
#43
1'
#44
0'
#45
1'
#46
0'
#47
1'
#48
0'
#49
1'
#50
0'
#51
1'
#52
0'
#53
1'
#54
0'
#55
1'
#56
0'
#57
1'
#58
0'
#59
1'
#60
0'
#61
1'
#62
0'
#63
1'
#64
0'
#65
1'
#66
0'
#67
1'
#68
0'
#69
1'
#70
0'
#71
1'
#72
0'
#73
1'
#74
0'
#75
1'
#76
0'
#77
1'
#78
0'
#79
1'
#80
0'
#81
1'
#82
0'
#83
1'
#84
0'
#85
1'
#86
0'
#87
1'
#88
0'
#89
1'
#90
0'
#91
1'
#92
0'
#93
1'
#94
0'
#95
1'
#96
0'
#97
1'
#98
0'
#99
1'
#100
0'
#101
1'
#102
0'
#103
1'
#104
0'
#105
1'
#106
0'
#107
1'
#108
0'
#109
1'
#110
0'
#111
1'
#112
0'
#113
1'
#114
0'
#115
1'
#116
0'
#117
1'
#118
0'
#119
1'
#120
0'
#121
1'
#122
0'
#123
1'
#124
0'
#125
1'
#126
0'
#127
1'
#128
0'
#129
1'
#130
0'
#131
1'
#132
0'
#133
1'
#134
0'
#135
1'
#136
0'
#137
1'
#138
0'
#139
1'
#140
0'
#141
1'
#142
0'
#143
1'
#144
0'
#145
1'
#146
0'
#147
1'
#148
0'
#149
1'
#150
0'
#151
1'
#152
0'
#153
1'
#154
0'
#155
1'
#156
0'
#157
1'
#158
0'
#159
1'
#160
0'
#161
1'
#162
0'
#163
1'
#164
0'
#165
1'
#166
0'
#167
1'
#168
0'
#169
1'
#170
0'
#171
1'
#172
0'
#173
1'
#174
0'
#175
1'
#176
0'
#177
1'
#178
0'
#179
1'
#180
0'
#181
1'
#182
0'
#183
1'
#184
0'
#185
1'
#186
0'
#187
1'
#188
0'
#189
1'
#190
0'
#191
1'
#192
0'
#193
1'
#194
0'
#195
1'
#196
0'
#197
1'
#198
0'
#199
1'
#200
04
0'
0-
0.
1+
#201
b10 6
1'
#202
0'
#203
b11 6
1'
#204
0'
#205
b100 6
1'
#206
0'
#207
b101 6
1'
#208
0'
#209
b1 6
15
1#
1%
1'
#210
0'
#211
b10 6
1'
#212
0'
#213
b11 6
1'
#214
0'
#215
b100 6
1'
#216
0'
#217
b101 6
1'
#218
0'
#219
b1 6
05
0#
0%
1'
#220
0'
#221
b10 6
1'
#222
0'
#223
b11 6
1'
#224
0'
#225
b100 6
1'
#226
0'
#227
b101 6
1'
#228
0'
#229
b1 6
15
1#
1%
1'
#230
0'
#231
b10 6
1'
#232
0'
#233
b11 6
1'
#234
0'
#235
b100 6
1'
#236
0'
#237
b101 6
1'
#238
0'
#239
b1 6
05
0#
0%
1'
#240
0'
#241
b10 6
1'
#242
0'
#243
b11 6
1'
#244
0'
#245
b100 6
1'
#246
0'
#247
b101 6
1'
#248
0'
#249
b1 6
15
1#
1%
1'
#250
0'
#251
b10 6
1'
#252
0'
#253
b11 6
1'
#254
0'
#255
b100 6
1'
#256
0'
#257
b101 6
1'
#258
0'
#259
b1 6
05
0#
0%
1'
#260
0'
#261
b10 6
1'
#262
0'
#263
b11 6
1'
#264
0'
#265
b100 6
1'
#266
0'
#267
b101 6
1'
#268
0'
#269
b1 6
15
1#
1%
1'
#270
0'
#271
b10 6
1'
#272
0'
#273
b11 6
1'
#274
0'
#275
b100 6
1'
#276
0'
#277
b101 6
1'
#278
0'
#279
b1 6
05
0#
0%
1'
#280
0'
#281
b10 6
1'
#282
0'
#283
b11 6
1'
#284
0'
#285
b100 6
1'
#286
0'
#287
b101 6
1'
#288
0'
#289
b1 6
15
1#
1%
1'
#290
0'
#291
b10 6
1'
#292
0'
#293
b11 6
1'
#294
0'
#295
b100 6
1'
#296
0'
#297
b101 6
1'
#298
0'
#299
b1 6
05
0#
0%
1'
#300
0'
#301
b10 6
1'
#302
0'
#303
b11 6
1'
#304
0'
#305
b100 6
1'
#306
0'
#307
b101 6
1'
#308
0'
#309
b1 6
15
1#
1%
1'
#310
0'
#311
b10 6
1'
#312
0'
#313
b11 6
1'
#314
0'
#315
b100 6
1'
#316
0'
#317
b101 6
1'
#318
0'
#319
b1 6
05
0#
0%
1'
#320
0'
#321
b10 6
1'
#322
0'
#323
b11 6
1'
#324
0'
#325
b100 6
1'
#326
0'
#327
b101 6
1'
#328
0'
#329
b1 6
15
1#
1%
1'
#330
0'
#331
b10 6
1'
#332
0'
#333
b11 6
1'
#334
0'
#335
b100 6
1'
#336
0'
#337
b101 6
1'
#338
0'
#339
b1 6
05
0#
0%
1'
#340
0'
#341
b10 6
1'
#342
0'
#343
b11 6
1'
#344
0'
#345
b100 6
1'
#346
0'
#347
b101 6
1'
#348
0'
#349
b1 6
15
1#
1%
1'
#350
0'
#351
b10 6
1'
#352
0'
#353
b11 6
1'
#354
0'
#355
b100 6
1'
#356
0'
#357
b101 6
1'
#358
0'
#359
b1 6
05
0#
0%
1'
#360
0'
#361
b10 6
1'
#362
0'
#363
b11 6
1'
#364
0'
#365
b100 6
1'
#366
0'
#367
b101 6
1'
#368
0'
#369
b1 6
15
1#
1%
1'
#370
0'
#371
b10 6
1'
#372
0'
#373
b11 6
1'
#374
0'
#375
b100 6
1'
#376
0'
#377
b101 6
1'
#378
0'
#379
b1 6
05
0#
0%
1'
#380
0'
#381
b10 6
1'
#382
0'
#383
b11 6
1'
#384
0'
#385
b100 6
1'
#386
0'
#387
b101 6
1'
#388
0'
#389
b1 6
15
1#
1%
1'
#390
0'
#391
b10 6
1'
#392
0'
#393
b11 6
1'
#394
0'
#395
b100 6
1'
#396
0'
#397
b101 6
1'
#398
0'
#399
b1 6
05
0#
0%
1'
#400
0'
#401
b10 6
1'
#402
0'
#403
b11 6
1'
#404
0'
#405
b100 6
1'
#406
0'
#407
b101 6
1'
#408
0'
#409
b1 6
15
1#
1%
1'
#410
0'
#411
b10 6
1'
#412
0'
#413
b11 6
1'
#414
0'
#415
b100 6
1'
#416
0'
#417
b101 6
1'
#418
0'
#419
b1 6
05
0#
0%
1'
#420
0'
#421
b10 6
1'
#422
0'
#423
b11 6
1'
#424
0'
#425
b100 6
1'
#426
0'
#427
b101 6
1'
#428
0'
#429
b1 6
15
1#
1%
1'
#430
0'
#431
b10 6
1'
#432
0'
#433
b11 6
1'
#434
0'
#435
b100 6
1'
#436
0'
#437
b101 6
1'
#438
0'
#439
b1 6
05
0#
0%
1'
#440
0'
#441
b10 6
1'
#442
0'
#443
b11 6
1'
#444
0'
#445
b100 6
1'
#446
0'
#447
b101 6
1'
#448
0'
#449
b1 6
15
1#
1%
1'
#450
0'
#451
b10 6
1'
#452
0'
#453
b11 6
1'
#454
0'
#455
b100 6
1'
#456
0'
#457
b101 6
1'
#458
0'
#459
b1 6
05
0#
0%
1'
#460
0'
#461
b10 6
1'
#462
0'
#463
b11 6
1'
#464
0'
#465
b100 6
1'
#466
0'
#467
b101 6
1'
#468
0'
#469
b1 6
15
1#
1%
1'
#470
0'
#471
b10 6
1'
#472
0'
#473
b11 6
1'
#474
0'
#475
b100 6
1'
#476
0'
#477
b101 6
1'
#478
0'
#479
b1 6
05
0#
0%
1'
#480
0'
#481
b10 6
1'
#482
0'
#483
b11 6
1'
#484
0'
#485
b100 6
1'
#486
0'
#487
b101 6
1'
#488
0'
#489
b1 6
15
1#
1%
1'
#490
0'
#491
b10 6
1'
#492
0'
#493
b11 6
1'
#494
0'
#495
b100 6
1'
#496
0'
#497
b101 6
1'
#498
0'
#499
b1 6
05
0#
0%
1'
#500
0'
#501
b10 6
1'
#502
0'
#503
b11 6
1'
#504
0'
#505
b100 6
1'
#506
0'
#507
b101 6
1'
#508
0'
#509
b1 6
15
1#
1%
1'
#510
0'
#511
b10 6
1'
#512
0'
#513
b11 6
1'
#514
0'
#515
b100 6
1'
#516
0'
#517
b101 6
1'
#518
0'
#519
b1 6
05
0#
0%
1'
#520
0'
#521
b10 6
1'
#522
0'
#523
b11 6
1'
#524
0'
#525
b100 6
1'
#526
0'
#527
b101 6
1'
#528
0'
#529
b1 6
15
1#
1%
1'
#530
0'
#531
b10 6
1'
#532
0'
#533
b11 6
1'
#534
0'
#535
b100 6
1'
#536
0'
#537
b101 6
1'
#538
0'
#539
b1 6
05
0#
0%
1'
#540
0'
#541
b10 6
1'
#542
0'
#543
b11 6
1'
#544
0'
#545
b100 6
1'
#546
0'
#547
b101 6
1'
#548
0'
#549
b1 6
15
1#
1%
1'
#550
0'
#551
b10 6
1'
#552
0'
#553
b11 6
1'
#554
0'
#555
b100 6
1'
#556
0'
#557
b101 6
1'
#558
0'
#559
b1 6
05
0#
0%
1'
#560
0'
#561
b10 6
1'
#562
0'
#563
b11 6
1'
#564
0'
#565
b100 6
1'
#566
0'
#567
b101 6
1'
#568
0'
#569
b1 6
15
1#
1%
1'
#570
0'
#571
b10 6
1'
#572
0'
#573
b11 6
1'
#574
0'
#575
b100 6
1'
#576
0'
#577
b101 6
1'
#578
0'
#579
b1 6
05
0#
0%
1'
#580
0'
#581
b10 6
1'
#582
0'
#583
b11 6
1'
#584
0'
#585
b100 6
1'
#586
0'
#587
b101 6
1'
#588
0'
#589
b1 6
15
1#
1%
1'
#590
0'
#591
b10 6
1'
#592
0'
#593
b11 6
1'
#594
0'
#595
b100 6
1'
#596
0'
#597
b101 6
1'
#598
0'
#599
b1 6
05
0#
0%
1'
#600
0'
#601
b10 6
1'
#602
0'
#603
b11 6
1'
#604
0'
#605
b100 6
1'
#606
0'
#607
b101 6
1'
#608
0'
#609
b1 6
15
1#
1%
1'
#610
0'
#611
b10 6
1'
#612
0'
#613
b11 6
1'
#614
0'
#615
b100 6
1'
#616
0'
#617
b101 6
1'
#618
0'
#619
b1 6
05
0#
0%
1'
#620
0'
#621
b10 6
1'
#622
0'
#623
b11 6
1'
#624
0'
#625
b100 6
1'
#626
0'
#627
b101 6
1'
#628
0'
#629
b1 6
15
1#
1%
1'
#630
0'
#631
b10 6
1'
#632
0'
#633
b11 6
1'
#634
0'
#635
b100 6
1'
#636
0'
#637
b101 6
1'
#638
0'
#639
b1 6
05
0#
0%
1'
#640
0'
#641
b10 6
1'
#642
0'
#643
b11 6
1'
#644
0'
#645
b100 6
1'
#646
0'
#647
b101 6
1'
#648
0'
#649
b1 6
15
1#
1%
1'
#650
0'
#651
b10 6
1'
#652
0'
#653
b11 6
1'
#654
0'
#655
b100 6
1'
#656
0'
#657
b101 6
1'
#658
0'
#659
b1 6
05
0#
0%
1'
#660
0'
#661
b10 6
1'
#662
0'
#663
b11 6
1'
#664
0'
#665
b100 6
1'
#666
0'
#667
b101 6
1'
#668
0'
#669
b1 6
15
1#
1%
1'
#670
0'
#671
b10 6
1'
#672
0'
#673
b11 6
1'
#674
0'
#675
b100 6
1'
#676
0'
#677
b101 6
1'
#678
0'
#679
b1 6
05
0#
0%
1'
#680
0'
#681
b10 6
1'
#682
0'
#683
b11 6
1'
#684
0'
#685
b100 6
1'
#686
0'
#687
b101 6
1'
#688
0'
#689
b1 6
15
1#
1%
1'
#690
0'
#691
b10 6
1'
#692
0'
#693
b11 6
1'
#694
0'
#695
b100 6
1'
#696
0'
#697
b101 6
1'
#698
0'
#699
b1 6
05
0#
0%
1'
#700
0'
#701
b10 6
1'
#702
0'
#703
b11 6
1'
#704
0'
#705
b100 6
1'
#706
0'
#707
b101 6
1'
#708
0'
#709
b1 6
15
1#
1%
1'
#710
0'
#711
b10 6
1'
#712
0'
#713
b11 6
1'
#714
0'
#715
b100 6
1'
#716
0'
#717
b101 6
1'
#718
0'
#719
b1 6
05
0#
0%
1'
#720
0'
#721
b10 6
1'
#722
0'
#723
b11 6
1'
#724
0'
#725
b100 6
1'
#726
0'
#727
b101 6
1'
#728
0'
#729
b1 6
15
1#
1%
1'
#730
0'
#731
b10 6
1'
#732
0'
#733
b11 6
1'
#734
0'
#735
b100 6
1'
#736
0'
#737
b101 6
1'
#738
0'
#739
b1 6
05
0#
0%
1'
#740
0'
#741
b10 6
1'
#742
0'
#743
b11 6
1'
#744
0'
#745
b100 6
1'
#746
0'
#747
b101 6
1'
#748
0'
#749
b1 6
15
1#
1%
1'
#750
0'
#751
b10 6
1'
#752
0'
#753
b11 6
1'
#754
0'
#755
b100 6
1'
#756
0'
#757
b101 6
1'
#758
0'
#759
b1 6
05
0#
0%
1'
#760
0'
#761
b10 6
1'
#762
0'
#763
b11 6
1'
#764
0'
#765
b100 6
1'
#766
0'
#767
b101 6
1'
#768
0'
#769
b1 6
15
1#
1%
1'
#770
0'
#771
b10 6
1'
#772
0'
#773
b11 6
1'
#774
0'
#775
b100 6
1'
#776
0'
#777
b101 6
1'
#778
0'
#779
b1 6
05
0#
0%
1'
#780
0'
#781
b10 6
1'
#782
0'
#783
b11 6
1'
#784
0'
#785
b100 6
1'
#786
0'
#787
b101 6
1'
#788
0'
#789
b1 6
15
1#
1%
1'
#790
0'
#791
b10 6
1'
#792
0'
#793
b11 6
1'
#794
0'
#795
b100 6
1'
#796
0'
#797
b101 6
1'
#798
0'
#799
b1 6
05
0#
0%
1'
#800
0'
#801
b10 6
1'
#802
0'
#803
b11 6
1'
#804
0'
#805
b100 6
1'
#806
0'
#807
b101 6
1'
#808
0'
#809
b1 6
15
1#
1%
1'
#810
0'
#811
b10 6
1'
#812
0'
#813
b11 6
1'
#814
0'
#815
b100 6
1'
#816
0'
#817
b101 6
1'
#818
0'
#819
b1 6
05
0#
0%
1'
#820
0'
#821
b10 6
1'
#822
0'
#823
b11 6
1'
#824
0'
#825
b100 6
1'
#826
0'
#827
b101 6
1'
#828
0'
#829
b1 6
15
1#
1%
1'
#830
0'
#831
b10 6
1'
#832
0'
#833
b11 6
1'
#834
0'
#835
b100 6
1'
#836
0'
#837
b101 6
1'
#838
0'
#839
b1 6
05
0#
0%
1'
#840
0'
#841
b10 6
1'
#842
0'
#843
b11 6
1'
#844
0'
#845
b100 6
1'
#846
0'
#847
b101 6
1'
#848
0'
#849
b1 6
15
1#
1%
1'
#850
0'
#851
b10 6
1'
#852
0'
#853
b11 6
1'
#854
0'
#855
b100 6
1'
#856
0'
#857
b101 6
1'
#858
0'
#859
b1 6
05
0#
0%
1'
#860
0'
#861
b10 6
1'
#862
0'
#863
b11 6
1'
#864
0'
#865
b100 6
1'
#866
0'
#867
b101 6
1'
#868
0'
#869
b1 6
15
1#
1%
1'
#870
0'
#871
b10 6
1'
#872
0'
#873
b11 6
1'
#874
0'
#875
b100 6
1'
#876
0'
#877
b101 6
1'
#878
0'
#879
b1 6
05
0#
0%
1'
#880
0'
#881
b10 6
1'
#882
0'
#883
b11 6
1'
#884
0'
#885
b100 6
1'
#886
0'
#887
b101 6
1'
#888
0'
#889
b1 6
15
1#
1%
1'
#890
0'
#891
b10 6
1'
#892
0'
#893
b11 6
1'
#894
0'
#895
b100 6
1'
#896
0'
#897
b101 6
1'
#898
0'
#899
b1 6
05
0#
0%
1'
#900
0'
#901
b10 6
1'
#902
0'
#903
b11 6
1'
#904
0'
#905
b100 6
1'
#906
0'
#907
b101 6
1'
#908
0'
#909
b1 6
15
1#
1%
1'
#910
0'
#911
b10 6
1'
#912
0'
#913
b11 6
1'
#914
0'
#915
b100 6
1'
#916
0'
#917
b101 6
1'
#918
0'
#919
b1 6
05
0#
0%
1'
#920
0'
#921
b10 6
1'
#922
0'
#923
b11 6
1'
#924
0'
#925
b100 6
1'
#926
0'
#927
b101 6
1'
#928
0'
#929
b1 6
15
1#
1%
1'
#930
0'
#931
b10 6
1'
#932
0'
#933
b11 6
1'
#934
0'
#935
b100 6
1'
#936
0'
#937
b101 6
1'
#938
0'
#939
b1 6
05
0#
0%
1'
#940
0'
#941
b10 6
1'
#942
0'
#943
b11 6
1'
#944
0'
#945
b100 6
1'
#946
0'
#947
b101 6
1'
#948
0'
#949
b1 6
15
1#
1%
1'
#950
0'
#951
b10 6
1'
#952
0'
#953
b11 6
1'
#954
0'
#955
b100 6
1'
#956
0'
#957
b101 6
1'
#958
0'
#959
b1 6
05
0#
0%
1'
#960
0'
#961
b10 6
1'
#962
0'
#963
b11 6
1'
#964
0'
#965
b100 6
1'
#966
0'
#967
b101 6
1'
#968
0'
#969
b1 6
15
1#
1%
1'
#970
0'
#971
b10 6
1'
#972
0'
#973
b11 6
1'
#974
0'
#975
b100 6
1'
#976
0'
#977
b101 6
1'
#978
0'
#979
b1 6
05
0#
0%
1'
#980
0'
#981
b10 6
1'
#982
0'
#983
b11 6
1'
#984
0'
#985
b100 6
1'
#986
0'
#987
b101 6
1'
#988
0'
#989
b1 6
15
1#
1%
1'
#990
0'
#991
b10 6
1'
#992
0'
#993
b11 6
1'
#994
0'
#995
b100 6
1'
#996
0'
#997
b101 6
1'
#998
0'
#999
b1 6
05
0#
0%
1'
#1000
0'
#1001
b10 6
1'
#1002
0'
#1003
b11 6
1'
#1004
0'
#1005
b100 6
1'
#1006
0'
#1007
b101 6
1'
#1008
0'
#1009
b1 6
15
1#
1%
1'
#1010
0'
#1011
b10 6
1'
#1012
0'
#1013
b11 6
1'
#1014
0'
#1015
b100 6
1'
#1016
0'
#1017
b101 6
1'
#1018
0'
#1019
b1 6
05
0#
0%
1'
#1020
0'
#1021
b10 6
1'
#1022
0'
#1023
b11 6
1'
#1024
0'
#1025
b100 6
1'
#1026
0'
#1027
b101 6
1'
#1028
0'
#1029
b1 6
15
1#
1%
1'
#1030
0'
#1031
b10 6
1'
#1032
0'
#1033
b11 6
1'
#1034
0'
#1035
b100 6
1'
#1036
0'
#1037
b101 6
1'
#1038
0'
#1039
b1 6
05
0#
0%
1'
#1040
0'
#1041
b10 6
1'
#1042
0'
#1043
b11 6
1'
#1044
0'
#1045
b100 6
1'
#1046
0'
#1047
b101 6
1'
#1048
0'
#1049
b1 6
15
1#
1%
1'
#1050
0'
#1051
b10 6
1'
#1052
0'
#1053
b11 6
1'
#1054
0'
#1055
b100 6
1'
#1056
0'
#1057
b101 6
1'
#1058
0'
#1059
b1 6
05
0#
0%
1'
#1060
0'
#1061
b10 6
1'
#1062
0'
#1063
b11 6
1'
#1064
0'
#1065
b100 6
1'
#1066
0'
#1067
b101 6
1'
#1068
0'
#1069
b1 6
15
1#
1%
1'
#1070
0'
#1071
b10 6
1'
#1072
0'
#1073
b11 6
1'
#1074
0'
#1075
b100 6
1'
#1076
0'
#1077
b101 6
1'
#1078
0'
#1079
b1 6
05
0#
0%
1'
#1080
0'
#1081
b10 6
1'
#1082
0'
#1083
b11 6
1'
#1084
0'
#1085
b100 6
1'
#1086
0'
#1087
b101 6
1'
#1088
0'
#1089
b1 6
15
1#
1%
1'
#1090
0'
#1091
b10 6
1'
#1092
0'
#1093
b11 6
1'
#1094
0'
#1095
b100 6
1'
#1096
0'
#1097
b101 6
1'
#1098
0'
#1099
b1 6
05
0#
0%
1'
#1100
0'
#1101
b10 6
1'
#1102
0'
#1103
b11 6
1'
#1104
0'
#1105
b100 6
1'
#1106
0'
#1107
b101 6
1'
#1108
0'
#1109
b1 6
15
1#
1%
1'
#1110
0'
#1111
b10 6
1'
#1112
0'
#1113
b11 6
1'
#1114
0'
#1115
b100 6
1'
#1116
0'
#1117
b101 6
1'
#1118
0'
#1119
b1 6
05
0#
0%
1'
#1120
0'
#1121
b10 6
1'
#1122
0'
#1123
b11 6
1'
#1124
0'
#1125
b100 6
1'
#1126
0'
#1127
b101 6
1'
#1128
0'
#1129
b1 6
15
1#
1%
1'
#1130
0'
#1131
b10 6
1'
#1132
0'
#1133
b11 6
1'
#1134
0'
#1135
b100 6
1'
#1136
0'
#1137
b101 6
1'
#1138
0'
#1139
b1 6
05
0#
0%
1'
#1140
0'
#1141
b10 6
1'
#1142
0'
#1143
b11 6
1'
#1144
0'
#1145
b100 6
1'
#1146
0'
#1147
b101 6
1'
#1148
0'
#1149
b1 6
15
1#
1%
1'
#1150
0'
#1151
b10 6
1'
#1152
0'
#1153
b11 6
1'
#1154
0'
#1155
b100 6
1'
#1156
0'
#1157
b101 6
1'
#1158
0'
#1159
b1 6
05
0#
0%
1'
#1160
0'
#1161
b10 6
1'
#1162
0'
#1163
b11 6
1'
#1164
0'
#1165
b100 6
1'
#1166
0'
#1167
b101 6
1'
#1168
0'
#1169
b1 6
15
1#
1%
1'
#1170
0'
#1171
b10 6
1'
#1172
0'
#1173
b11 6
1'
#1174
0'
#1175
b100 6
1'
#1176
0'
#1177
b101 6
1'
#1178
0'
#1179
b1 6
05
0#
0%
1'
#1180
0'
#1181
b10 6
1'
#1182
0'
#1183
b11 6
1'
#1184
0'
#1185
b100 6
1'
#1186
0'
#1187
b101 6
1'
#1188
0'
#1189
b1 6
15
1#
1%
1'
#1190
0'
#1191
b10 6
1'
#1192
0'
#1193
b11 6
1'
#1194
0'
#1195
b100 6
1'
#1196
0'
#1197
b101 6
1'
#1198
0'
#1199
b1 6
05
0#
0%
1'
#1200
0'
1-
1.
#1201
b10 6
1'
#1202
0'
#1203
b11 6
1'
#1204
0'
#1205
b100 6
1'
#1206
0'
#1207
b101 6
1'
#1208
0'
#1209
1<
1*
0>
0,
b0 @
b0 B
b0 /
03
0:
02
09
b1 6
15
1#
1%
1'
#1210
0'
#1211
b10 6
1'
#1212
0'
#1213
b11 6
1'
#1214
0'
#1215
b100 6
1'
#1216
0'
#1217
b101 6
1'
#1218
0'
#1219
b1 6
05
0#
0%
1'
#1220
0'
#1221
b10 6
1'
#1222
0'
#1223
b11 6
1'
#1224
0'
#1225
b100 6
1'
#1226
0'
#1227
b101 6
1'
#1228
0'
#1229
1;
0=
b1 6
15
1#
1%
1'
#1230
0'
#1231
b10 6
1'
#1232
0'
#1233
b11 6
1'
#1234
0'
#1235
b100 6
1'
#1236
0'
#1237
b101 6
1'
#1238
0'
#1239
b1 6
05
0#
0%
1'
#1240
0'
#1241
b10 6
1'
#1242
0'
#1243
b11 6
1'
#1244
0'
#1245
b100 6
1'
#1246
0'
#1247
b101 6
1'
#1248
0'
#1249
b1 6
15
1#
1%
1'
#1250
0'
#1251
b10 6
1'
#1252
0'
#1253
b11 6
1'
#1254
0'
#1255
b100 6
1'
#1256
0'
#1257
b101 6
1'
#1258
0'
#1259
b1 6
05
0#
0%
1'
#1260
0'
#1261
b10 6
1'
#1262
0'
#1263
b11 6
1'
#1264
0'
#1265
b100 6
1'
#1266
0'
#1267
b101 6
1'
#1268
0'
#1269
b1 6
15
1#
1%
1'
#1270
0'
#1271
b10 6
1'
#1272
0'
#1273
b11 6
1'
#1274
0'
#1275
b100 6
1'
#1276
0'
#1277
b101 6
1'
#1278
0'
#1279
b1 6
05
0#
0%
1'
#1280
0'
#1281
b10 6
1'
#1282
0'
#1283
b11 6
1'
#1284
0'
#1285
b100 6
1'
#1286
0'
#1287
b101 6
1'
#1288
0'
#1289
b1 6
15
1#
1%
1'
#1290
0'
#1291
b10 6
1'
#1292
0'
#1293
b11 6
1'
#1294
0'
#1295
b100 6
1'
#1296
0'
#1297
b101 6
1'
#1298
0'
#1299
b1 6
05
0#
0%
1'
#1300
0'
#1301
b10 6
1'
#1302
0'
#1303
b11 6
1'
#1304
0'
#1305
b100 6
1'
#1306
0'
#1307
b101 6
1'
#1308
0'
#1309
b1 6
15
1#
1%
1'
#1310
0'
#1311
b10 6
1'
#1312
0'
#1313
b11 6
1'
#1314
0'
#1315
b100 6
1'
