HW/01GRUPO1/02verilog/Liss/FIFO/fifo.v
module fifo # (parameter abits = 14, dbits = 8)(
    input clock,
    input reset,
    input href,
    input vsync,
    input [dbits-1:0] din,
    output empty,
    output full,
    output [dbits-1:0] dout,
    input rd );

wire wr;
reg [dbits-1:0] out;
assign wr = href & ~vsync;

reg [dbits-1:0] regarray[2**abits-1:0]; //number of words in fifo = 2^(number of address bits)
reg [abits-1:0] wr_reg, wr_next, wr_succ; //points to the register that needs to be written to
reg [abits-1:0] rd_reg, rd_next, rd_succ; //points to the register that needs to be read from
reg full_reg, empty_reg, full_next, empty_next;
 
assign wr_en = wr & ~full; //only write if write signal is high and fifo is not full
 
//always block for write operation
always @ (posedge clock)
 begin
  if(wr_en)
   regarray[wr_reg] <= din;  //at wr_reg location of regarray store what is given at din
 
 end
  
//always block for read operation
always @ (posedge clock)
 begin
  if(rd)
   out <= regarray[rd_reg];
 end
  
 
always @ (posedge clock or posedge reset)
 begin
  if (reset)
   begin
   wr_reg <= 0;
   rd_reg <= 0;
   full_reg <= 1'b0;
   empty_reg <= 1'b1;
   end
   
  else
   begin
   wr_reg <= wr_next; //created the next registers to avoid the error of mixing blocking and non blocking assignment to the same signal
   rd_reg <= rd_next;
   full_reg <= full_next;
   empty_reg <= empty_next;
   end
 end
  
always @(*)
 begin
  wr_succ = wr_reg + 1; //assigned to new value as wr_next cannot be tested for in same always block
  rd_succ = rd_reg + 1; //assigned to new value as rd_next cannot be tested for in same always block
  wr_next = wr_reg;  //defaults state stays the same
  rd_next = rd_reg;  //defaults state stays the same
  full_next = full_reg;  //defaults state stays the same
  empty_next = empty_reg;  //defaults state stays the same
   
   case({wr,rd})
    //2'b00: do nothing LOL..
     
    2'b01: //read
     begin
      if(~empty) //if fifo is not empty continue
       begin
        rd_next = rd_succ;
        full_next = 1'b0;
       if(rd_succ == wr_reg) //all data has been read
         empty_next = 1'b1;  //its empty again
       end
     end
     
    2'b10: //write
     begin
       
      if(~full) //if fifo is not full continue
       begin
        wr_next = wr_succ;
        empty_next = 1'b0;
        if(wr_succ == (2**abits-1)) //all registers have been written to
         full_next = 1'b1;   //its full now
       end
     end
      
    2'b11: //read and write
     begin
      wr_next = wr_succ;
      rd_next = rd_succ;
     end
     //no empty or full flag will be checked for or asserted in this state since data is being written to and read from together it can  not get full in this state.
    endcase
    
 
 end
 
assign full = full_reg;
assign empty = empty_reg;
assign dout = out;
endmodule

HW/01GRUPO1/02verilog/Liss/FIFO1/fifo_TB.v
//----------------------------------------------------------------------------
`timescale 1 ns / 100 ps

module fifo_TB;

parameter tck              = 2;       // clock period in ns
//----------------------------------------------------------------------------
//----------------------------------------------------------------------------

reg clk;
reg rst;

reg rd,wr;
reg [7:0] data_in;

//----------------------------------------------------------------------------
// Device Under Test 
//------------------------------------------------------------------

fifo  uut(.reset(rst),.clock(clk),.rd(rd),.wr(wr),.din(data_in));


/* Clocking device */
initial begin
	clk <= 0;
	rst <=1;
	#(2*tck) rst=0;
	rd <=0;
	wr<=0;
end

always #(tck/2) clk <= ~clk;


initial begin
#4;
data_in="h"; #1 wr=1; #2 wr=0;
data_in="o"; #1 wr=1; #2 wr=0;
data_in="l"; #1 rd=1; wr=1; #2 rd=0; wr=0;
data_in="a"; #1 wr=1; #2 wr=0;
data_in=" "; #1 wr=1; #2 wr=0;
data_in="m"; #1 wr=1; #2 wr=0;
data_in="u"; #1 wr=1; #2 wr=0;
data_in="n"; #1 wr=1; #2 wr=0;
data_in="d"; #1 wr=1; #2 wr=0;
data_in="o"; #1 wr=1; #2 wr=0;
data_in="."; #1 wr=1; #2 wr=0;
data_in="1"; #1 wr=1; #2 wr=0;
data_in="2"; #1 wr=1; #2 wr=0;
data_in="3"; #1 wr=1; #2 wr=0;
data_in="4"; #1 wr=1; #2 wr=0;
data_in="5"; #1 wr=1; #2 wr=0;
data_in="6"; #1 wr=1; #2 wr=0;
data_in="7"; #1 wr=1; #2 wr=0;
data_in="8"; #1 wr=1; #2 wr=0;
data_in="9"; #1 wr=1; #2 wr=0;
data_in="0"; #1 wr=1; #2 wr=0;

#1 rd=1; #2 rd=0;
#1 rd=1; #2 rd=0;
#1 rd=1; #2 rd=0;

data_in="a"; #1 wr=1; rd=0;#2 wr=0;rd=1;
data_in="b"; #1 wr=1; #2 wr=0;
data_in="c"; #1 wr=1; #2 wr=0;
data_in="d"; #1 wr=1; #2 wr=0;

#1 rd=1; #2 rd=0;
#1 rd=1; #2 rd=0;
#1 rd=1; #2 rd=0;
#1 rd=1; #2 rd=0;
#1 rd=1; #2 rd=0;
#1 rd=1; #2 rd=0;
#1 rd=1; #2 rd=0;
#1 rd=1; #2 rd=0;
#1 rd=1; #2 rd=0;
#1 rd=1; #2 rd=0;
#1 rd=1; #2 rd=0;
#1 rd=1; #2 rd=0;
#1 rd=1; #2 rd=0;
#1 rd=1; #2 rd=0;
#1 rd=1; #2 rd=0;
#1 rd=1; #2 rd=0;
#1 rd=1; #2 rd=0;
#1 rd=1; #2 rd=0;


end
initial begin: TEST_CASE
     $dumpfile("fifo_TB.vcd");
     $dumpvars(-1, uut);
     #(200) $finish;
   end

endmodule //

HW/01GRUPO1/02verilog/Liss/Camara/FIFO/simulation/fifo_TB.vcd
$date
	Mon Mar 12 20:43:33 2018
$end
$version
	Icarus Verilog
$end
$timescale
	100ps
$end
$scope module fifo_TB $end
$scope module uut $end
$var wire 1 ! clock $end
$var wire 8 " din [7:0] $end
$var wire 8 # dout [7:0] $end
$var wire 1 $ empty $end
$var wire 1 % href $end
$var wire 1 & rd $end
$var wire 1 ' reset $end
$var wire 1 ( vsync $end
$var wire 1 ) wr $end
$var wire 1 * wr_en $end
$var wire 1 + full $end
$var reg 1 , empty_next $end
$var reg 1 - empty_reg $end
$var reg 1 . full_next $end
$var reg 1 + full_reg $end
$var reg 8 / out [7:0] $end
$var reg 14 0 rd_next [13:0] $end
$var reg 14 1 rd_reg [13:0] $end
$var reg 14 2 rd_succ [13:0] $end
$var reg 14 3 wr_next [13:0] $end
$var reg 14 4 wr_reg [13:0] $end
$var reg 14 5 wr_succ [13:0] $end
$upscope $end
$upscope $end
$enddefinitions $end
#0
$dumpvars
b1 5
b0 4
b0 3
b1 2
b0 1
b0 0
bx /
0.
1-
1,
0+
x*
x)
x(
1'
x&
x%
1$
bx #
bx "
0!
$end
#10
1!
#20
0!
#30
1!
#40
0!
b1101000 "
#50
1!
#60
0*
0)
0!
0(
0%
0&
b1101111 "
0'
#70
1!
#80
0!
b1101100 "
#90
1!
#100
0!
b1100001 "
#110
1!
#120
0!
b100000 "
#130
1!
#140
0!
b1101101 "
#150
1!
#160
0!
b1110101 "
#170
1!
#180
0!
b1101110 "
#190
1!
#200
0!
b1100100 "
#210
1!
#220
0!
b1101111 "
#230
1!
#240
0!
b101110 "
#250
1!
#260
0!
b110010 "
#270
1!
#280
0!
b110011 "
#290
1!
#300
0!
b110100 "
#310
1!
#320
0!
b110101 "
#330
1!
#340
0!
b110110 "
#350
1!
#360
1*
0,
b1 3
1)
0!
1%
b110111 "
#370
b10 3
b10 5
0$
0-
b1 4
1!
#380
0!
b111000 "
#390
b11 3
b11 5
b10 4
1!
#400
0!
b111001 "
#410
b100 3
b100 5
b11 4
1!
#420
0!
b110000 "
#430
b101 3
b101 5
b100 4
1!
#440
0!
#450
b110 3
b110 5
b101 4
1!
#460
0!
b1 0
b110 3
1&
#470
b10 0
b111 3
b10 2
b111 5
b1 1
b110 4
b110111 #
b110111 /
1!
#480
0!
b1 0
b111 3
0&
#490
b1000 3
b1000 5
b111 4
1!
#500
0!
b10 0
b1000 3
1&
#510
b11 0
b1001 3
b11 2
b1001 5
b10 1
b1000 4
b111000 #
b111000 /
1!
#520
0!
b10 0
b1001 3
0&
#530
b1010 3
b1010 5
b1001 4
1!
#540
0!
b11 0
b1010 3
1&
#550
b100 0
b1011 3
b100 2
b1011 5
b11 1
b1010 4
b111001 #
b111001 /
1!
#560
0!
b11 0
b1011 3
0&
#570
b1100 3
b1100 5
b1011 4
1!
#580
0!
#590
b1101 3
b1101 5
b1100 4
1!
#600
0!
#610
b1110 3
b1110 5
b1101 4
1!
#620
0!
#630
b1111 3
b1111 5
b1110 4
1!
#640
0!
#650
b10000 3
b10000 5
b1111 4
1!
#660
0!
#670
b10001 3
b10001 5
b10000 4
1!
#680
0!
#690
b10010 5
b10001 4
0*
b10001 3
0)
1!
0%
#700
0!
#710
1!
#720
0!
#730
1!
#740
0!
#750
1!
#760
0!
#770
1!
#780
0!
#790
1!
#800
0!
#810
1!
#820
0!
#830
1!
#840
0!
#850
1!
#860
0!
#870
1!
#880
0!
#890
1!
#900
0!
#910
1!
#920
0!
#930
1!
#940
0!
#950
1!
#960
0!
#970
1!
#980
0!
#990
1!
#1000
0!
#1010
1!
#1020
1*
b10010 3
1)
0!
1%
#1030
b10011 3
b10011 5
b10010 4
1!
#1040
0!
#1050
b10100 3
b10100 5
b10011 4
1!
#1060
0!
#1070
b10101 3
b10101 5
b10100 4
1!
#1080
0!
#1090
b10110 3
b10110 5
b10101 4
1!
#1100
0!
#1110
b10111 3
b10111 5
b10110 4
1!
#1120
0!
#1130
b11000 3
b11000 5
b10111 4
1!
#1140
0!
#1150
b11001 3
b11001 5
b11000 4
1!
#1160
0!
#1170
b11010 3
b11010 5
b11001 4
1!
#1180
0!
#1190
b11011 3
b11011 5
b11010 4
1!
#1200
0!
#1210
b11100 3
b11100 5
b11011 4
1!
#1220
0!
#1230
b11101 3
b11101 5
b11100 4
1!
#1240
0!
#1250
b11110 3
b11110 5
b11101 4
1!
#1260
0!
#1270
b11111 3
b11111 5
b11110 4
1!
#1280
0!
#1290
b100000 3
b100000 5
b11111 4
1!
#1300
0!
#1310
b100001 3
b100001 5
b100000 4
1!
#1320
0!
#1330
b100010 3
b100010 5
b100001 4
1!
#1340
0!
#1350
b100011 5
b100010 4
0*
b100010 3
0)
1!
0%
#1360
0!
#1370
1!
#1380
0!
#1390
1!
#1400
0!
#1410
1!
#1420
0!
#1430
1!
#1440
0!
#1450
1!
#1460
0!
#1470
1!
#1480
0!
#1490
1!
#1500
0!
#1510
1!
#1520
0!
#1530
1!
#1540
0!
#1550
1!
#1560
0!
#1570
1!
#1580
0!
#1590
1!
#1600
0!
#1610
1!
#1620
0!
#1630
1!
#1640
0!
#1650
1!
#1660
0!
#1670
1!
#1680
1*
b100011 3
1)
0!
1%
#1690
b100100 3
b100100 5
b100011 4
1!
#1700
0!
#1710
b100101 3
b100101 5
b100100 4
1!
#1720
0!
#1730
b100110 3
b100110 5
b100101 4
1!
#1740
0!
#1750
b100111 3
b100111 5
b100110 4
1!
#1760
0!
#1770
b101000 3
b101000 5
b100111 4
1!
#1780
0!
#1790
b101001 3
b101001 5
b101000 4
1!
#1800
0!
#1810
b101010 3
b101010 5
b101001 4
1!
#1820
0!
#1830
b101011 3
b101011 5
b101010 4
1!
#1840
0!
#1850
b101100 3
b101100 5
b101011 4
1!
#1860
0!
#1870
b101101 3
b101101 5
b101100 4
1!
#1880
0!
#1890
b101110 3
b101110 5
b101101 4
1!
#1900
0!
#1910
b101111 3
b101111 5
b101110 4
1!
#1920
0!
#1930
b110000 3
b110000 5
b101111 4
1!
#1940
0!
#1950
b110001 3
b110001 5
b110000 4
1!
#1960
0!
#1970
b110010 3
b110010 5
b110001 4
1!
#1980
0!
#1990
b110011 3
b110011 5
b110010 4
1!
#2000
0!
#2010
b110100 5
b110011 4
0*
b110011 3
0)
1!
0%
#2020
0!
#2030
1!
#2040
0!
#2050
1!
#2060
0!
#2070
1!
#2080
0!
#2090
1!
#2100
0!
#2110
1!
#2120
0!
#2130
1!
#2140
0!
#2150
1!
#2160
0!
#2170
1!
#2180
0!
#2190
1!
#2200
0!
#2210
1!
#2220
0!
#2230
1!
#2240
0!
#2250
1!
#2260
0!
#2270
1!
#2280
0!
#2290
1!
#2300
0!
#2310
1!
#2320
0!
#2330
1!
#2340
1*
b110100 3
1)
0!
1%
#2350
b110101 3
b110101 5
b110100 4
1!
#2360
0!
#2370
b110110 3
b110110 5
b110101 4
1!
#2380
0!
#2390
b110111 3
b110111 5
b110110 4
1!
#2400
0!
#2410
b111000 3
b111000 5
b110111 4
1!
#2420
0!
#2430
b111001 3
b111001 5
b111000 4
1!
#2440
0!
#2450
b111010 3
b111010 5
b111001 4
1!
#2460
0!
#2470
b111011 3
b111011 5
b111010 4
1!
#2480
0!
#2490
b111100 3
b111100 5
b111011 4
1!
#2500
0!
#2510
b111101 3
b111101 5
b111100 4
1!
#2520
0!
#2530
b111110 3
b111110 5
b111101 4
1!
#2540
0!
#2550
b111111 3
b111111 5
b111110 4
1!
#2560
0!
#2570
b1000000 3
b1000000 5
b111111 4
1!
#2580
0!
#2590
b1000001 3
b1000001 5
b1000000 4
1!
#2600
0!
#2610
b1000010 3
b1000010 5
b1000001 4
1!
#2620
0!
#2630
b1000011 3
b1000011 5
b1000010 4
1!
#2640
0!
#2650
b1000100 3
b1000100 5
b1000011 4
1!
#2660
0!
#2670
b1000101 5
b1000100 4
0*
b1000100 3
0)
1!
0%
#2680
0!
#2690
1!
#2700
0!
#2710
1!
#2720
0!
#2730
1!
#2740
0!
#2750
1!
#2760
0!
#2770
1!
#2780
0!
#2790
1!
#2800
0!
#2810
1!
#2820
0!
#2830
1!
#2840
0!
#2850
1!
#2860
0!
#2870
1!
#2880
0!
#2890
1!
#2900
0!
#2910
1!
#2920
0!
#2930
1!
#2940
0!
#2950
1!
#2960
0!
#2970
1!
#2980
0!
#2990
1!
#3000
1*
b1000101 3
1)
0!
1%
#3010
b1000110 3
b1000110 5
b1000101 4
1!
#3020
0!
#3030
b1000111 3
b1000111 5
b1000110 4
1!
#3040
0!
#3050
b1001000 3
b1001000 5
b1000111 4
1!
#3060
0*
b1000111 3
0)
0!
1(
#3070
1!
#3080
0!
#3090
1!
#3100
0!
#3110
1!
#3120
0!
#3130
1!
#3140
0!
#3150
1!
#3160
0!
#3170
1!
#3180
0!
#3190
1!
#3200
0!
#3210
1!
#3220
0!
#3230
1!
#3240
0!
#3250
1!
#3260
0!
#3270
1!
#3280
0!
#3290
1!
#3300
0!
#3310
1!
#3320
0!
#3330
1!
0%
#3340
0!
#3350
1!
#3360
0!
#3370
1!
#3380
0!
#3390
1!
#3400
0!
#3410
1!
#3420
0!
#3430
1!
#3440
0!
#3450
1!
#3460
0!
#3470
1!
#3480
0!
#3490
1!
#3500
0!
#3510
1!
#3520
0!
#3530
1!
#3540
0!
#3550
1!
#3560
0!
#3570
1!
#3580
0!
#3590
1!
#3600
0!
#3610
1!
#3620
0!
#3630
1!
#3640
0!
#3650
1!
#3660
0!
1%
#3670
1!
#3680
0!
#3690
1!
#3700
0!
#3710
1!
#3720
0!
#3730
1!
#3740
0!
#3750
1!
#3760
0!
#3770
1!
#3780
0!
#3790
1!
#3800
0!
#3810
1!
#3820
0!
#3830
1!
#3840
0!
#3850
1!
#3860
0!
#3870
1!
#3880
0!
#3890
1!
#3900
0!
#3910
1!
#3920
0!
#3930
1!
#3940
0!
#3950
1!
#3960
0!
#3970
1!
#3980
0!
#3990
1!
0%
#4000
0!
#4010
1!
#4020
0!
#4030
1!
#4040
0!
#4050
1!
#4060
0!
#4070
1!
#4080
0!
#4090
1!
#4100
0!
#4110
1!
#4120
0!
#4130
1!
#4140
0!
#4150
1!
#4160
0!
#4170
1!
#4180
0!
#4190
1!
#4200
0!
#4210
1!
#4220
0!
#4230
1!
#4240
0!
#4250
1!
#4260
0!
#4270
1!
#4280
0!
#4290
1!
#4300
0!
#4310
1!
#4320
0!
1%
#4330
1!
#4340
0!
#4350
1!
#4360
0!
#4370
1!
#4380
0!
#4390
1!
#4400
0!
#4410
1!
#4420
0!
#4430
1!
#4440
0!
#4450
1!
#4460
0!
#4470
1!
#4480
0!
#4490
1!
#4500
0!
#4510
1!
#4520
0!
#4530
1!
#4540
0!
#4550
1!
#4560
0!
#4570
1!
#4580
0!
#4590
1!
#4600
0!
#4610
1!
#4620
0!
#4630
1!
#4640
0!
#4650
1!
0%
#4660
0!
#4670
1!
#4680
0!
#4690
1!
#4700
0!
#4710
1!
#4720
0!
#4730
1!
#4740
0!
#4750
1!
#4760
0!
#4770
1!
#4780
0!
#4790
1!
#4800
0!
#4810
1!
#4820
0!
#4830
1!
#4840
0!
#4850
1!
#4860
0!
#4870
1!
#4880
0!
#4890
1!
#4900
0!
#4910
1!
#4920
0!
#4930
1!
#4940
0!
#4950
1!
#4960
0!
#4970
1!
#4980
0!
1%
#4990
1!
#5000
0!
#5010
1!
#5020
0!
#5030
1!
#5040
0!
#5050
1!
#5060
0!
#5070
1!
#5080
0!
#5090
1!
#5100
0!
#5110
1!
#5120
0!
#5130
1!
#5140
0!
#5150
1!
#5160
0!
#5170
1!
#5180
0!
#5190
1!
#5200
0!
#5210
1!
#5220
0!
#5230
1!
#5240
0!
#5250
1!
#5260
0!
#5270
1!
#5280
0!
#5290
1!
#5300
0!
#5310
1!
0%
#5320
0!
#5330
1!
#5340
0!
#5350
1!
#5360
0!
#5370
1!
#5380
0!
#5390
1!
#5400
0!
#5410
1!
#5420
0!
#5430
1!
#5440
0!
#5450
1!
#5460
0!
#5470
1!
#5480
0!
#5490
1!
#5500
0!
#5510
1!
#5520
0!
#5530
1!
#5540
0!
#5550
1!
#5560
0!
#5570
1!
#5580
0!
#5590
1!
#5600
0!
#5610
1!
#5620
0!
#5630
1!
#5640
0!
1%
#5650
1!
#5660
0!
#5670
1!
#5680
0!
#5690
1!
#5700
0!
#5710
1!
#5720
0!
#5730
1!
#5740
0!
#5750
1!
#5760
0!
#5770
1!
#5780
0!
#5790
1!
#5800
0!
#5810
1!
#5820
0!
#5830
1!
#5840
0!
#5850
1!
#5860
0!
#5870
1!
#5880
0!
#5890
1!
#5900
0!
#5910
1!
#5920
0!
#5930
1!
#5940
0!
#5950
1!
#5960
0!
#5970
1!
0%
#5980
0!
#5990
1!
#6000
0!
#6010
1!
#6020
0!
#6030
1!
#6040
0!
#6050
1!
#6060
0!
#6070
1!
#6080
0!
#6090
1!
0(
#6100
0!
#6110
1!
#6120
0!
#6130
1!
#6140
0!
#6150
1!
#6160
0!
#6170
1!
#6180
0!
#6190
1!
#6200
0!
#6210
1!
#6220
0!
#6230
1!
#6240
0!
#6250
1!
#6260
0!
#6270
1!
#6280
0!
#6290
1!
#6300
1*
b1001000 3
1)
0!
1%
#6310
b1001001 3
b1001001 5
b1001000 4
1!
#6320
0!
#6330
b1001010 3
b1001010 5
b1001001 4
1!
#6340
0!
#6350
b1001011 3
b1001011 5
b1001010 4
1!
#6360
0!
#6370
b1001100 3
b1001100 5
b1001011 4
1!
#6380
0!
#6390
b1001101 3
b1001101 5
b1001100 4
1!
#6400
0!
#6410
b1001110 3
b1001110 5
b1001101 4
1!
#6420
0!
#6430
b1001111 3
b1001111 5
b1001110 4
1!
#6440
0!
#6450
b1010000 3
b1010000 5
b1001111 4
1!
#6460
0!
#6470
b1010001 3
b1010001 5
b1010000 4
1!
#6480
0!
#6490
b1010010 3
b1010010 5
b1010001 4
1!
#6500
0!
#6510
b1010011 3
b1010011 5
b1010010 4
1!
#6520
0!
#6530
b1010100 3
b1010100 5
b1010011 4
1!
#6540
0!
#6550
b1010101 3
b1010101 5
b1010100 4
1!
#6560
0!
#6570
b1010110 3
b1010110 5
b1010101 4
1!
#6580
0!
#6590
b1010111 3
b1010111 5
b1010110 4
1!
#6600
0!
#6610
b1011000 3
b1011000 5
b1010111 4
1!
#6620
0!
#6630
b1011001 5
b1011000 4
0*
b1011000 3
0)
1!
0%
#6640
0!
#6650
1!
#6660
0!
#6670
1!
#6680
0!
#6690
1!
#6700
0!
#6710
1!
#6720
0!
#6730
1!
#6740
0!
#6750
1!
#6760
0!
#6770
1!
#6780
0!
#6790
1!
#6800
0!
#6810
1!
#6820
0!
#6830
1!
#6840
0!
#6850
1!
#6860
0!
#6870
1!
#6880
0!
#6890
1!
#6900
0!
#6910
1!
#6920
0!
#6930
1!
#6940
0!
#6950
1!
#6960
1*
b1011001 3
1)
0!
1%
#6970
b1011010 3
b1011010 5
b1011001 4
1!
#6980
0!
#6990
b1011011 3
b1011011 5
b1011010 4
1!
#7000
0!
#7010
b1011100 3
b1011100 5
b1011011 4
1!
#7020
0!
#7030
b1011101 3
b1011101 5
b1011100 4
1!
#7040
0!
#7050
b1011110 3
b1011110 5
b1011101 4
1!
#7060
0!
#7070
b1011111 3
b1011111 5
b1011110 4
1!
#7080
0!
#7090
b1100000 3
b1100000 5
b1011111 4
1!
#7100
0!
#7110
b1100001 3
b1100001 5
b1100000 4
1!
#7120
0!
#7130
b1100010 3
b1100010 5
b1100001 4
1!
#7140
0!
#7150
b1100011 3
b1100011 5
b1100010 4
1!
#7160
0!
#7170
b1100100 3
b1100100 5
b1100011 4
1!
#7180
0!
#7190
b1100101 3
b1100101 5
b1100100 4
1!
#7200
0!
#7210
b1100110 3
b1100110 5
b1100101 4
1!
#7220
0!
#7230
b1100111 3
b1100111 5
b1100110 4
1!
#7240
0!
#7250
b1101000 3
b1101000 5
b1100111 4
1!
#7260
0!
#7270
b1101001 3
b1101001 5
b1101000 4
1!
#7280
0!
#7290
b1101010 5
b1101001 4
0*
b1101001 3
0)
1!
0%
#7300
0!
#7310
1!
#7320
0!
#7330
1!
#7340
0!
#7350
1!
#7360
0!
#7370
1!
#7380
0!
#7390
1!
#7400
0!
#7410
1!
#7420
0!
#7430
1!
#7440
0!
#7450
1!
#7460
0!
#7470
1!
#7480
0!
#7490
1!
#7500
0!
#7510
1!
#7520
0!
#7530
1!
#7540
0!
#7550
1!
#7560
0!
#7570
1!
#7580
0!
#7590
1!
#7600
0!
#7610
1!
#7620
1*
b1101010 3
1)
0!
1%
#7630
b1101011 3
b1101011 5
b1101010 4
1!
#7640
0!
#7650
b1101100 3
b1101100 5
b1101011 4
1!
#7660
0!
#7670
b1101101 3
b1101101 5
b1101100 4
1!
#7680
0!
#7690
b1101110 3
b1101110 5
b1101101 4
1!
#7700
0!
#7710
b1101111 3
b1101111 5
b1101110 4
1!
#7720
0!
#7730
b1110000 3
b1110000 5
b1101111 4
1!
#7740
0!
#7750
b1110001 3
b1110001 5
b1110000 4
1!
#7760
0!
#7770
b1110010 3
b1110010 5
b1110001 4
1!
#7780
0!
#7790
b1110011 3
b1110011 5
b1110010 4
1!
#7800
0!
#7810
b1110100 3
b1110100 5
b1110011 4
1!
#7820
0!
#7830
b1110101 3
b1110101 5
b1110100 4
1!
#7840
0!
#7850
b1110110 3
b1110110 5
b1110101 4
1!
#7860
0!
#7870
b1110111 3
b1110111 5
b1110110 4
1!
#7880
0!
#7890
b1111000 3
b1111000 5
b1110111 4
1!
#7900
0!
#7910
b1111001 3
b1111001 5
b1111000 4
1!
#7920
0!
#7930
b1111010 3
b1111010 5
b1111001 4
1!
#7940
0!
#7950
b1111011 5
b1111010 4
0*
b1111010 3
0)
1!
0%
#7960
0!
#7970
1!
#7980
0!
#7990
1!
#8000
0!
#8010
1!
#8020
0!
#8030
1!
#8040
0!
#8050
1!
#8060
0!
#8070
1!
#8080
0!
#8090
1!
#8100
0!
#8110
1!
#8120
0!
#8130
1!
#8140
0!
#8150
1!
#8160
0!
#8170
1!
#8180
0!
#8190
1!
#8200
0!
#8210
1!
#8220
0!
#8230
1!
#8240
0!
#8250
1!
#8260
0!
#8270
1!
#8280
1*
b1111011 3
1)
0!
1%
#8290
b1111100 3
b1111100 5
b1111011 4
1!
#8300
0!
#8310
b1111101 3
b1111101 5
b1111100 4
1!
#8320
0!
#8330
b1111110 3
b1111110 5
b1111101 4
1!
#8340
0!
#8350
b1111111 3
b1111111 5
b1111110 4
1!
#8360
0!
#8370
b10000000 3
b10000000 5
b1111111 4
1!
#8380
0!
#8390
b10000001 3
b10000001 5
b10000000 4
1!
#8400
0!
#8410
b10000010 3
b10000010 5
b10000001 4
1!
#8420
0!
#8430
b10000011 3
b10000011 5
b10000010 4
1!
#8440
0!
#8450
b10000100 3
b10000100 5
b10000011 4
1!
#8460
0!
#8470
b10000101 3
b10000101 5
b10000100 4
1!
#8480
0!
#8490
b10000110 3
b10000110 5
b10000101 4
1!
#8500
0!
#8510
b10000111 3
b10000111 5
b10000110 4
1!
#8520
0!
#8530
b10001000 3
b10001000 5
b10000111 4
1!
#8540
0!
#8550
b10001001 3
b10001001 5
b10001000 4
1!
#8560
0!
#8570
b10001010 3
b10001010 5
b10001001 4
1!
#8580
0!
#8590
b10001011 3
b10001011 5
b10001010 4
1!
#8600
0!
#8610
b10001100 5
b10001011 4
0*
b10001011 3
0)
1!
0%
#8620
0!
#8630
1!
#8640
0!
#8650
1!
#8660
0!
#8670
1!
#8680
0!
#8690
1!
#8700
0!
#8710
1!
#8720
0!
#8730
1!
#8740
0!
#8750
1!
#8760
0!
#8770
1!
#8780
0!
#8790
1!
#8800
0!
#8810
1!
#8820
0!
#8830
1!
#8840
0!
#8850
1!
#8860
0!
#8870
1!
#8880
0!
#8890
1!
#8900
0!
#8910
1!
#8920
0!
#8930
1!
#8940
1*
b10001100 3
1)
0!
1%
#8950
b10001101 3
b10001101 5
b10001100 4
1!
#8960
0!
#8970
b10001110 3
b10001110 5
b10001101 4
1!
#8980
0!
#8990
b10001111 3
b10001111 5
b10001110 4
1!
#9000
0!
#9010
b10010000 3
b10010000 5
b10001111 4
1!
#9020
0!
#9030
b10010001 3
b10010001 5
b10010000 4
1!
#9040
0!
#9050
b10010010 3
b10010010 5
b10010001 4
1!
#9060
0!
#9070
b10010011 3
b10010011 5
b10010010 4
1!
#9080
0!
#9090
b10010100 3
b10010100 5
b10010011 4
1!
#9100
0!
#9110
b10010101 3
b10010101 5
b10010100 4
1!
#9120
0*
b10010100 3
0)
0!
1(
#9130
1!
#9140
0!
#9150
1!
#9160
0!
#9170
1!
#9180
0!
#9190
1!
#9200
0!
#9210
1!
#9220
0!
#9230
1!
#9240
0!
#9250
1!
#9260
0!
#9270
1!
0%
#9280
0!
#9290
1!
#9300
0!
#9310
1!
#9320
0!
#9330
1!
#9340
0!
#9350
1!
#9360
0!
#9370
1!
#9380
0!
#9390
1!
#9400
0!
#9410
1!
#9420
0!
#9430
1!
#9440
0!
#9450
1!
#9460
0!
#9470
1!
#9480
0!
#9490
1!
#9500
0!
#9510
1!
#9520
0!
#9530
1!
#9540
0!
#9550
1!
#9560
0!
#9570
1!
#9580
0!
#9590
1!
#9600
0!
1%
#9610
1!
#9620
0!
#9630
1!
#9640
0!
#9650
1!
#9660
0!
#9670
1!
#9680
0!
#9690
1!
#9700
0!
#9710
1!
#9720
0!
#9730
1!
#9740
0!
#9750
1!
#9760
0!
#9770
1!
#9780
0!
#9790
1!
#9800
0!
#9810
1!
#9820
0!
#9830
1!
#9840
0!
#9850
1!
#9860
0!
#9870
1!
#9880
0!
#9890
1!
#9900
0!
#9910
1!
#9920
0!
#9930
1!
0%
#9940
0!
#9950
1!
#9960
0!
#9970
1!
#9980
0!
#9990
1!
#10000
0!
#10010
1!
#10020
0!
#10030
1!
#10040
0!
#10050
1!
#10060
0!
#10070
1!
#10080
0!
#10090
1!
#10100
0!
#10110
1!
#10120
0!
#10130
1!
#10140
0!
#10150
1!
#10160
0!
#10170
1!
#10180
0!
#10190
1!
#10200
0!
#10210
1!
#10220
0!
#10230
1!
#10240
0!
#10250
1!
#10260
0!
1%
#10270
1!
#10280
0!
#10290
1!
#10300
0!
#10310
1!
#10320
0!
#10330
1!
#10340
0!
#10350
1!
#10360
0!
#10370
1!
#10380
0!
#10390
1!
#10400
0!
#10410
1!
#10420
0!
#10430
1!
#10440
0!
#10450
1!
#10460
0!
#10470
1!
#10480
0!
#10490
1!
#10500
0!
#10510
1!
#10520
0!
#10530
1!
#10540
0!
#10550
1!
#10560
0!
#10570
1!
#10580
0!
#10590
1!
0%
#10600
0!
#10610
1!
#10620
0!
#10630
1!
#10640
0!
#10650
1!
#10660
0!
#10670
1!
#10680
0!
#10690
1!
#10700
0!
#10710
1!
#10720
0!
#10730
1!
#10740
0!
#10750
1!
#10760
0!
#10770
1!
#10780
0!
#10790
1!
#10800
0!
#10810
1!
#10820
0!
#10830
1!
#10840
0!
#10850
1!
#10860
0!
#10870
1!
#10880
0!
#10890
1!
#10900
0!
#10910
1!
#10920
0!
1%
#10930
1!
#10940
0!
#10950
1!
#10960
0!
#10970
1!
#10980
0!
#10990
1!
#11000
0!
#11010
1!
#11020
0!
#11030
1!
#11040
0!
#11050
1!
#11060
0!
#11070
1!
#11080
0!
#11090
1!
#11100
0!
#11110
1!
#11120
0!
#11130
1!
#11140
0!
#11150
1!
#11160
0!
#11170
1!
#11180
0!
#11190
1!
#11200
0!
#11210
1!
#11220
0!
#11230
1!
#11240
0!
#11250
1!
0%
#11260
0!
#11270
1!
#11280
0!
#11290
1!
#11300
0!
#11310
1!
#11320
0!
#11330
1!
#11340
0!
#11350
1!
#11360
0!
#11370
1!
#11380
0!
#11390
1!
#11400
0!
#11410
1!
#11420
0!
#11430
1!
#11440
0!
#11450
1!
#11460
0!
#11470
1!
#11480
0!
#11490
1!
#11500
0!
#11510
1!
#11520
0!
#11530
1!
#11540
0!
#11550
1!
#11560
0!
#11570
1!
#11580
0!
1%
#11590
1!
#11600
0!
#11610
1!
#11620
0!
#11630
1!
#11640
0!
#11650
1!
#11660
0!
#11670
1!
#11680
0!
#11690
1!
#11700
0!
#11710
1!
#11720
0!
#11730
1!
#11740
0!
#11750
1!
#11760
0!
#11770
1!
#11780
0!
#11790
1!
#11800
0!
#11810
1!
#11820
0!
#11830
1!
#11840
0!
#11850
1!
#11860
0!
#11870
1!
#11880
0!
#11890
1!
#11900
0!
#11910
1!
0%
#11920
0!
#11930
1!
#11940
0!
