HW/01GRUPO1/02verilog/Daniel/FIFO/fifo.v
module fifo # (parameter abits = 14, dbits = 8)(
    input pclk,
    input reset,
    input href,
    input vsync,
    input [dbits-1:0] din,
    output empty,
    output full,
    output [dbits-1:0] dout,
    input rd );

wire wr;
assign wr=1;
wire rd2;
assign rd2=1;
reg [dbits-1:0] out;

//assign wr = href & ~vsync;

reg [dbits-1:0] regarray[2**abits-1:0]; //number of words in fifo = 2^(number of address bits)
reg [abits-1:0] wr_reg, wr_next, wr_succ; //points to the register that needs to be written to
reg [abits-1:0] rd_reg, rd_next, rd_succ; //points to the register that needs to be read from
reg full_reg, empty_reg, full_next, empty_next;
 
assign wr_en = wr & ~full; //only write if write signal is high and fifo is not full
 
//always block for write operation
always @ (posedge pclk)
 begin
  //if(wr)
   regarray[wr_reg] <= din;  //at wr_reg location of regarray store what is given at din
 
 end
  
//always block for read operation
always @ (posedge rd)
 begin
 // if(rd2)
   out <= regarray[rd_reg];
 end
  
 
always @ (posedge pclk or posedge reset)
 begin
  if (reset)
   begin
   wr_reg <= 0;
   rd_reg <= 0;
   full_reg <= 1'b0;
   empty_reg <= 1'b1;
   end
   
  else
   begin
   wr_reg <= wr_next; //created the next registers to avoid the error of mixing blocking and non blocking assignment to the same signal
   rd_reg <= rd_next;
   full_reg <= full_next;
   empty_reg <= empty_next;
   end
 end
  
always @(*)
 begin
  wr_succ = wr_reg + 1; //assigned to new value as wr_next cannot be tested for in same always block
  rd_succ = rd_reg + 1; //assigned to new value as rd_next cannot be tested for in same always block
  wr_next = wr_reg;  //defaults state stays the same
  rd_next = rd_reg;  //defaults state stays the same
  full_next = full_reg;  //defaults state stays the same
  empty_next = empty_reg;  //defaults state stays the same
   
   case({wr,rd})
    //2'b00: do nothing LOL..
     
    2'b01: //read
     begin
      if(~empty) //if fifo is not empty continue
       begin
        rd_next = rd_succ;
        full_next = 1'b0;
       if(rd_succ == wr_reg) //all data has been read
         empty_next = 1'b1;  //its empty again
       end
     end
     
    2'b10: //write
     begin
       
      if(~full) //if fifo is not full continue
       begin
        wr_next = wr_succ;
        empty_next = 1'b0;
        if(wr_succ == (2**abits-1)) //all registers have been written to
         full_next = 1'b1;   //its full now
       end
     end
      
    2'b11: //read and write
     begin
      wr_next = wr_succ;
      rd_next = rd_succ;
     end
     //no empty or full flag will be checked for or asserted in this state since data is being written to and read from together it can  not get full in this state.
    endcase
    
 
 end
 
assign full = full_reg;
assign empty = empty_reg;
assign dout = out;
endmodule

HW/01GRUPO1/02verilog/Daniel/FIFO/fifo_TB.v
//----------------------------------------------------------------------------
`timescale 1 ns / 100 ps

module fifo_TB;

parameter tck              = 2;       // clock period in ns
//----------------------------------------------------------------------------
reg clk;
reg rst;

reg rd,href,vsync;
reg [8:0] data_in;

//----------------------------------------------------------------------------
// Device Under Test 
//------------------------------------------------------------------

fifo  uut(.reset(rst),.pclk(clk),.rd(rd),.href(href),.vsync(vsync),.din(data_in));

/* Clocking device */
initial begin
	clk <= 0;
	rst <=1;
	#(2*tck) rst=0;
	rd <=0;
	href<=0;
	vsync<=0;
end

always #(tck/2) clk <= ~clk;

always #(tck)
begin
href<=~href;#30;
end

always #(tck)
begin
vsync<=~vsync;#300;
end

initial begin
#4;
data_in="h"; #2;
data_in="o"; #2;
data_in="l"; #2;
data_in="a"; #2;
data_in=" "; #2;
data_in="m"; #2;
data_in="u"; #2;
data_in="n"; #2;
data_in="d"; #2;
data_in="o"; #2; 
data_in="."; #2;
data_in="2"; #2;
data_in="3"; #2;
data_in="4"; #2; 
data_in="5"; #2; 
data_in="6"; #2; 
data_in="7"; #2; 
data_in="8"; #2; 
data_in="9"; #2; 
data_in="0"; #2;

rd=0; #2;
rd=1; #2;
rd=0; #2;
rd=1; #2;
rd=0; #2;
rd=1; #2;
rd=0; #2;
rd=0; #2;
rd=1; #2;
rd=0; #2;
rd=1; #2;
rd=0; #2;
rd=1; #2;
rd=0; #2;
rd=0; #2;
rd=1; #2;
rd=0; #2;
rd=1; #2;
rd=0; #2;
rd=1; #2;
rd=0; #2;
rd=0; #2;
rd=1; #2;
rd=0; #2;
rd=1; #2;
rd=0; #2;
rd=1; #2;
rd=0; #2;
rd=0; #2;
rd=1; #2;
rd=0; #2;
rd=1; #2;
rd=0; #2;
rd=1; #2;
rd=0; #2;
rd=0; #2;
rd=1; #2;
rd=0; #2;
rd=1; #2;
rd=0; #2;
rd=1; #2;
rd=0; #2;
end

initial begin: TEST_CASE
     $dumpfile("fifo_TB.vcd");
     $dumpvars(-1, uut);
     #(200000) $finish;
   end

endmodule //

HW/01GRUPO1/02verilog/Daniel/FIFO/simulation/fifo_TB.vcd
$date
	Fri Mar 16 10:54:07 2018
$end
$version
	Icarus Verilog
$end
$timescale
	100ps
$end
$scope module fifo_TB $end
$scope module uut $end
$var wire 8 ! din [7:0] $end
$var wire 8 " dout [7:0] $end
$var wire 1 # empty $end
$var wire 1 $ full $end
$var wire 1 % href $end
$var wire 1 & pclk $end
$var wire 1 ' rd $end
$var wire 1 ( rd2 $end
$var wire 1 ) reset $end
$var wire 1 * vsync $end
$var wire 1 + wr $end
$var wire 1 , wr_en $end
$var reg 1 - empty_next $end
$var reg 1 . empty_reg $end
$var reg 1 / full_next $end
$var reg 1 0 full_reg $end
$var reg 8 1 out [7:0] $end
$var reg 14 2 rd_next [13:0] $end
$var reg 14 3 rd_reg [13:0] $end
$var reg 14 4 rd_succ [13:0] $end
$var reg 14 5 wr_next [13:0] $end
$var reg 14 6 wr_reg [13:0] $end
$var reg 14 7 wr_succ [13:0] $end
$upscope $end
$upscope $end
$enddefinitions $end
#0
$dumpvars
b1 7
b0 6
b0 5
b1 4
b0 3
b0 2
bx 1
00
0/
1.
1-
1,
1+
x*
1)
1(
x'
0&
x%
0$
1#
b0x "
bx !
$end
#10
1&
#20
0&
#30
1&
#40
b0 "
0-
b1 5
0&
0*
0%
0'
b1101000 !
0)
#50
b10 5
b10 7
0.
0#
b1 6
1&
#60
0&
b1101111 !
#70
b11 5
b11 7
b10 6
1&
#80
0&
b1101100 !
#90
b100 5
b100 7
b11 6
1&
#100
0&
b1100001 !
#110
b101 5
b101 7
b100 6
1&
#120
0&
b100000 !
#130
b110 5
b110 7
b101 6
1&
#140
0&
b1101101 !
#150
b111 5
b111 7
b110 6
1&
#160
0&
b1110101 !
#170
b1000 5
b1000 7
b111 6
1&
#180
0&
b1101110 !
#190
b1001 5
b1001 7
b1000 6
1&
#200
0&
b1100100 !
#210
b1010 5
b1010 7
b1001 6
1&
#220
0&
b1101111 !
#230
b1011 5
b1011 7
b1010 6
1&
#240
0&
b101110 !
#250
b1100 5
b1100 7
b1011 6
1&
#260
0&
b110010 !
#270
b1101 5
b1101 7
b1100 6
1&
#280
0&
b110011 !
#290
b1110 5
b1110 7
b1101 6
1&
#300
0&
b110100 !
#310
b1111 5
b1111 7
b1110 6
1&
#320
0&
b110101 !
#330
b10000 5
b10000 7
b1111 6
1&
#340
0&
1%
b110110 !
#350
b10001 5
b10001 7
b10000 6
1&
#360
0&
b110111 !
#370
b10010 5
b10010 7
b10001 6
1&
#380
0&
b111000 !
#390
b10011 5
b10011 7
b10010 6
1&
#400
0&
b111001 !
#410
b10100 5
b10100 7
b10011 6
1&
#420
0&
b110000 !
#430
b10101 5
b10101 7
b10100 6
1&
#440
0&
#450
b10110 5
b10110 7
b10101 6
1&
#460
b1101000 1
0&
b1 2
b10110 5
1'
#470
b10 2
b10111 5
b10 4
b10111 7
b1 3
b10110 6
1&
#480
0&
b1 2
b10111 5
0'
#490
b11000 5
b11000 7
b10111 6
1&
#500
b1101111 1
0&
b10 2
b11000 5
1'
#510
b11 2
b11001 5
b11 4
b11001 7
b10 3
b11000 6
1&
#520
0&
b10 2
b11001 5
0'
#530
b11010 5
b11010 7
b11001 6
1&
#540
b1101100 1
0&
b11 2
b11010 5
1'
#550
b100 2
b11011 5
b100 4
b11011 7
b11 3
b11010 6
1&
#560
0&
b11 2
b11011 5
0'
#570
b11100 5
b11100 7
b11011 6
1&
#580
0&
#590
b11101 5
b11101 7
b11100 6
1&
#600
b1100001 1
0&
b100 2
b11101 5
1'
#610
b101 2
b11110 5
b101 4
b11110 7
b100 3
b11101 6
1&
#620
0&
b100 2
b11110 5
0'
#630
b11111 5
b11111 7
b11110 6
1&
#640
b100000 1
0&
b101 2
b11111 5
1'
#650
b110 2
b100000 5
b110 4
b100000 7
b101 3
b11111 6
1&
#660
0&
0%
b101 2
b100000 5
0'
#670
b100001 5
b100001 7
b100000 6
1&
#680
b1101101 1
0&
b110 2
b100001 5
1'
#690
b111 2
b100010 5
b111 4
b100010 7
b110 3
b100001 6
1&
#700
0&
b110 2
b100010 5
0'
#710
b100011 5
b100011 7
b100010 6
1&
#720
0&
#730
b100100 5
b100100 7
b100011 6
1&
#740
b1110101 1
0&
b111 2
b100100 5
1'
#750
b1000 2
b100101 5
b1000 4
b100101 7
b111 3
b100100 6
1&
#760
0&
b111 2
b100101 5
0'
#770
b100110 5
b100110 7
b100101 6
1&
#780
b1101110 1
0&
b1000 2
b100110 5
1'
#790
b1001 2
b100111 5
b1001 4
b100111 7
b1000 3
b100110 6
1&
#800
0&
b1000 2
b100111 5
0'
#810
b101000 5
b101000 7
b100111 6
1&
#820
b1100100 1
0&
b1001 2
b101000 5
1'
#830
b1010 2
b101001 5
b1010 4
b101001 7
b1001 3
b101000 6
1&
#840
0&
b1001 2
b101001 5
0'
#850
b101010 5
b101010 7
b101001 6
1&
#860
0&
#870
b101011 5
b101011 7
b101010 6
1&
#880
b1101111 1
0&
b1010 2
b101011 5
1'
#890
b1011 2
b101100 5
b1011 4
b101100 7
b1010 3
b101011 6
1&
#900
0&
b1010 2
b101100 5
0'
#910
b101101 5
b101101 7
b101100 6
1&
#920
b101110 1
0&
b1011 2
b101101 5
1'
#930
b1100 2
b101110 5
b1100 4
b101110 7
b1011 3
b101101 6
1&
#940
0&
b1011 2
b101110 5
0'
#950
b101111 5
b101111 7
b101110 6
1&
#960
b110010 1
0&
b1100 2
b101111 5
1'
#970
b1101 2
b110000 5
b1101 4
b110000 7
b1100 3
b101111 6
1&
#980
0&
1%
b1100 2
b110000 5
0'
#990
b110001 5
b110001 7
b110000 6
1&
#1000
0&
#1010
b110010 5
b110010 7
b110001 6
1&
#1020
b110011 1
0&
b1101 2
b110010 5
1'
#1030
b1110 2
b110011 5
b1110 4
b110011 7
b1101 3
b110010 6
1&
#1040
0&
b1101 2
b110011 5
0'
#1050
b110100 5
b110100 7
b110011 6
1&
#1060
b110100 1
0&
b1110 2
b110100 5
1'
#1070
b1111 2
b110101 5
b1111 4
b110101 7
b1110 3
b110100 6
1&
#1080
0&
b1110 2
b110101 5
0'
#1090
b110110 5
b110110 7
b110101 6
1&
#1100
b110101 1
0&
b1111 2
b110110 5
1'
#1110
b10000 2
b110111 5
b10000 4
b110111 7
b1111 3
b110110 6
1&
#1120
0&
b1111 2
b110111 5
0'
#1130
b111000 5
b111000 7
b110111 6
1&
#1140
0&
#1150
b111001 5
b111001 7
b111000 6
1&
#1160
b110110 1
0&
b10000 2
b111001 5
1'
#1170
b10001 2
b111010 5
b10001 4
b111010 7
b10000 3
b111001 6
1&
#1180
0&
b10000 2
b111010 5
0'
#1190
b111011 5
b111011 7
b111010 6
1&
#1200
b110111 1
0&
b10001 2
b111011 5
1'
#1210
b10010 2
b111100 5
b10010 4
b111100 7
b10001 3
b111011 6
1&
#1220
0&
b10001 2
b111100 5
0'
#1230
b111101 5
b111101 7
b111100 6
1&
#1240
b111000 1
0&
b10010 2
b111101 5
1'
#1250
b10011 2
b111110 5
b10011 4
b111110 7
b10010 3
b111101 6
1&
#1260
0&
b10010 2
b111110 5
0'
#1270
b111111 5
b111111 7
b111110 6
1&
#1280
0&
#1290
b1000000 5
b1000000 7
b111111 6
1&
#1300
0&
0%
#1310
b1000001 5
b1000001 7
b1000000 6
1&
#1320
0&
#1330
b1000010 5
b1000010 7
b1000001 6
1&
#1340
0&
#1350
b1000011 5
b1000011 7
b1000010 6
1&
#1360
0&
#1370
b1000100 5
b1000100 7
b1000011 6
1&
#1380
0&
#1390
b1000101 5
b1000101 7
b1000100 6
1&
#1400
0&
#1410
b1000110 5
b1000110 7
b1000101 6
1&
#1420
0&
#1430
b1000111 5
b1000111 7
b1000110 6
1&
#1440
0&
#1450
b1001000 5
b1001000 7
b1000111 6
1&
#1460
0&
#1470
b1001001 5
b1001001 7
b1001000 6
1&
#1480
0&
#1490
b1001010 5
b1001010 7
b1001001 6
1&
#1500
0&
#1510
b1001011 5
b1001011 7
b1001010 6
1&
#1520
0&
#1530
b1001100 5
b1001100 7
b1001011 6
1&
#1540
0&
#1550
b1001101 5
b1001101 7
b1001100 6
1&
#1560
0&
#1570
b1001110 5
b1001110 7
b1001101 6
1&
#1580
0&
#1590
b1001111 5
b1001111 7
b1001110 6
1&
#1600
0&
#1610
b1010000 5
b1010000 7
b1001111 6
1&
#1620
0&
1%
#1630
b1010001 5
b1010001 7
b1010000 6
1&
#1640
0&
#1650
b1010010 5
b1010010 7
b1010001 6
1&
#1660
0&
#1670
b1010011 5
b1010011 7
b1010010 6
1&
#1680
0&
#1690
b1010100 5
b1010100 7
b1010011 6
1&
#1700
0&
#1710
b1010101 5
b1010101 7
b1010100 6
1&
#1720
0&
#1730
b1010110 5
b1010110 7
b1010101 6
1&
#1740
0&
#1750
b1010111 5
b1010111 7
b1010110 6
1&
#1760
0&
#1770
b1011000 5
b1011000 7
b1010111 6
1&
#1780
0&
#1790
b1011001 5
b1011001 7
b1011000 6
1&
#1800
0&
#1810
b1011010 5
b1011010 7
b1011001 6
1&
#1820
0&
#1830
b1011011 5
b1011011 7
b1011010 6
1&
#1840
0&
#1850
b1011100 5
b1011100 7
b1011011 6
1&
#1860
0&
#1870
b1011101 5
b1011101 7
b1011100 6
1&
#1880
0&
#1890
b1011110 5
b1011110 7
b1011101 6
1&
#1900
0&
#1910
b1011111 5
b1011111 7
b1011110 6
1&
#1920
0&
#1930
b1100000 5
b1100000 7
b1011111 6
1&
#1940
0&
0%
#1950
b1100001 5
b1100001 7
b1100000 6
1&
#1960
0&
#1970
b1100010 5
b1100010 7
b1100001 6
1&
#1980
0&
#1990
b1100011 5
b1100011 7
b1100010 6
1&
#2000
0&
#2010
b1100100 5
b1100100 7
b1100011 6
1&
#2020
0&
#2030
b1100101 5
b1100101 7
b1100100 6
1&
#2040
0&
#2050
b1100110 5
b1100110 7
b1100101 6
1&
#2060
0&
#2070
b1100111 5
b1100111 7
b1100110 6
1&
#2080
0&
#2090
b1101000 5
b1101000 7
b1100111 6
1&
#2100
0&
#2110
b1101001 5
b1101001 7
b1101000 6
1&
#2120
0&
#2130
b1101010 5
b1101010 7
b1101001 6
1&
#2140
0&
#2150
b1101011 5
b1101011 7
b1101010 6
1&
#2160
0&
#2170
b1101100 5
b1101100 7
b1101011 6
1&
#2180
0&
#2190
b1101101 5
b1101101 7
b1101100 6
1&
#2200
0&
#2210
b1101110 5
b1101110 7
b1101101 6
1&
#2220
0&
#2230
b1101111 5
b1101111 7
b1101110 6
1&
#2240
0&
#2250
b1110000 5
b1110000 7
b1101111 6
1&
#2260
0&
1%
#2270
b1110001 5
b1110001 7
b1110000 6
1&
#2280
0&
#2290
b1110010 5
b1110010 7
b1110001 6
1&
#2300
0&
#2310
b1110011 5
b1110011 7
b1110010 6
1&
#2320
0&
#2330
b1110100 5
b1110100 7
b1110011 6
1&
#2340
0&
#2350
b1110101 5
b1110101 7
b1110100 6
1&
#2360
0&
#2370
b1110110 5
b1110110 7
b1110101 6
1&
#2380
0&
#2390
b1110111 5
b1110111 7
b1110110 6
1&
#2400
0&
#2410
b1111000 5
b1111000 7
b1110111 6
1&
#2420
0&
#2430
b1111001 5
b1111001 7
b1111000 6
1&
#2440
0&
#2450
b1111010 5
b1111010 7
b1111001 6
1&
#2460
0&
#2470
b1111011 5
b1111011 7
b1111010 6
1&
#2480
0&
#2490
b1111100 5
b1111100 7
b1111011 6
1&
#2500
0&
#2510
b1111101 5
b1111101 7
b1111100 6
1&
#2520
0&
#2530
b1111110 5
b1111110 7
b1111101 6
1&
#2540
0&
#2550
b1111111 5
b1111111 7
b1111110 6
1&
#2560
0&
#2570
b10000000 5
b10000000 7
b1111111 6
1&
#2580
0&
0%
#2590
b10000001 5
b10000001 7
b10000000 6
1&
#2600
0&
#2610
b10000010 5
b10000010 7
b10000001 6
1&
#2620
0&
#2630
b10000011 5
b10000011 7
b10000010 6
1&
#2640
0&
#2650
b10000100 5
b10000100 7
b10000011 6
1&
#2660
0&
#2670
b10000101 5
b10000101 7
b10000100 6
1&
#2680
0&
#2690
b10000110 5
b10000110 7
b10000101 6
1&
#2700
0&
#2710
b10000111 5
b10000111 7
b10000110 6
1&
#2720
0&
#2730
b10001000 5
b10001000 7
b10000111 6
1&
#2740
0&
#2750
b10001001 5
b10001001 7
b10001000 6
1&
#2760
0&
#2770
b10001010 5
b10001010 7
b10001001 6
1&
#2780
0&
#2790
b10001011 5
b10001011 7
b10001010 6
1&
#2800
0&
#2810
b10001100 5
b10001100 7
b10001011 6
1&
#2820
0&
#2830
b10001101 5
b10001101 7
b10001100 6
1&
#2840
0&
#2850
b10001110 5
b10001110 7
b10001101 6
1&
#2860
0&
#2870
b10001111 5
b10001111 7
b10001110 6
1&
#2880
0&
#2890
b10010000 5
b10010000 7
b10001111 6
1&
#2900
0&
1%
#2910
b10010001 5
b10010001 7
b10010000 6
1&
#2920
0&
#2930
b10010010 5
b10010010 7
b10010001 6
1&
#2940
0&
#2950
b10010011 5
b10010011 7
b10010010 6
1&
#2960
0&
#2970
b10010100 5
b10010100 7
b10010011 6
1&
#2980
0&
#2990
b10010101 5
b10010101 7
b10010100 6
1&
#3000
0&
#3010
b10010110 5
b10010110 7
b10010101 6
1&
#3020
0&
#3030
b10010111 5
b10010111 7
b10010110 6
1&
#3040
0&
1*
#3050
b10011000 5
b10011000 7
b10010111 6
1&
#3060
0&
#3070
b10011001 5
b10011001 7
b10011000 6
1&
#3080
0&
#3090
b10011010 5
b10011010 7
b10011001 6
1&
#3100
0&
#3110
b10011011 5
b10011011 7
b10011010 6
1&
#3120
0&
#3130
b10011100 5
b10011100 7
b10011011 6
1&
#3140
0&
#3150
b10011101 5
b10011101 7
b10011100 6
1&
#3160
0&
#3170
b10011110 5
b10011110 7
b10011101 6
1&
#3180
0&
#3190
b10011111 5
b10011111 7
b10011110 6
1&
#3200
0&
#3210
b10100000 5
b10100000 7
b10011111 6
1&
#3220
0&
0%
#3230
b10100001 5
b10100001 7
b10100000 6
1&
#3240
0&
#3250
b10100010 5
b10100010 7
b10100001 6
1&
#3260
0&
#3270
b10100011 5
b10100011 7
b10100010 6
1&
#3280
0&
#3290
b10100100 5
b10100100 7
b10100011 6
1&
#3300
0&
#3310
b10100101 5
b10100101 7
b10100100 6
1&
#3320
0&
#3330
b10100110 5
b10100110 7
b10100101 6
1&
#3340
0&
#3350
b10100111 5
b10100111 7
b10100110 6
1&
#3360
0&
#3370
b10101000 5
b10101000 7
b10100111 6
1&
#3380
0&
#3390
b10101001 5
b10101001 7
b10101000 6
1&
#3400
0&
#3410
b10101010 5
b10101010 7
b10101001 6
1&
#3420
0&
#3430
b10101011 5
b10101011 7
b10101010 6
1&
#3440
0&
#3450
b10101100 5
b10101100 7
b10101011 6
1&
#3460
0&
#3470
b10101101 5
b10101101 7
b10101100 6
1&
#3480
0&
#3490
b10101110 5
b10101110 7
b10101101 6
1&
#3500
0&
#3510
b10101111 5
b10101111 7
b10101110 6
1&
#3520
0&
#3530
b10110000 5
b10110000 7
b10101111 6
1&
#3540
0&
1%
#3550
b10110001 5
b10110001 7
b10110000 6
1&
#3560
0&
#3570
b10110010 5
b10110010 7
b10110001 6
1&
#3580
0&
#3590
b10110011 5
b10110011 7
b10110010 6
1&
#3600
0&
#3610
b10110100 5
b10110100 7
b10110011 6
1&
#3620
0&
#3630
b10110101 5
b10110101 7
b10110100 6
1&
#3640
0&
#3650
b10110110 5
b10110110 7
b10110101 6
1&
#3660
0&
#3670
b10110111 5
b10110111 7
b10110110 6
1&
#3680
0&
#3690
b10111000 5
b10111000 7
b10110111 6
1&
#3700
0&
#3710
b10111001 5
b10111001 7
b10111000 6
1&
#3720
0&
#3730
b10111010 5
b10111010 7
b10111001 6
1&
#3740
0&
#3750
b10111011 5
b10111011 7
b10111010 6
1&
#3760
0&
#3770
b10111100 5
b10111100 7
b10111011 6
1&
#3780
0&
#3790
b10111101 5
b10111101 7
b10111100 6
1&
#3800
0&
#3810
b10111110 5
b10111110 7
b10111101 6
1&
#3820
0&
#3830
b10111111 5
b10111111 7
b10111110 6
1&
#3840
0&
#3850
b11000000 5
b11000000 7
b10111111 6
1&
#3860
0&
0%
#3870
b11000001 5
b11000001 7
b11000000 6
1&
#3880
0&
#3890
b11000010 5
b11000010 7
b11000001 6
1&
#3900
0&
#3910
b11000011 5
b11000011 7
b11000010 6
1&
#3920
0&
#3930
b11000100 5
b11000100 7
b11000011 6
1&
#3940
0&
#3950
b11000101 5
b11000101 7
b11000100 6
1&
#3960
0&
#3970
b11000110 5
b11000110 7
b11000101 6
1&
#3980
0&
#3990
b11000111 5
b11000111 7
b11000110 6
1&
#4000
0&
#4010
b11001000 5
b11001000 7
b11000111 6
1&
#4020
0&
#4030
b11001001 5
b11001001 7
b11001000 6
1&
#4040
0&
#4050
b11001010 5
b11001010 7
b11001001 6
1&
#4060
0&
#4070
b11001011 5
b11001011 7
b11001010 6
1&
#4080
0&
#4090
b11001100 5
b11001100 7
b11001011 6
1&
#4100
0&
#4110
b11001101 5
b11001101 7
b11001100 6
1&
#4120
0&
#4130
b11001110 5
b11001110 7
b11001101 6
1&
#4140
0&
#4150
b11001111 5
b11001111 7
b11001110 6
1&
#4160
0&
#4170
b11010000 5
b11010000 7
b11001111 6
1&
#4180
0&
1%
#4190
b11010001 5
b11010001 7
b11010000 6
1&
#4200
0&
#4210
b11010010 5
b11010010 7
b11010001 6
1&
#4220
0&
#4230
b11010011 5
b11010011 7
b11010010 6
1&
#4240
0&
#4250
b11010100 5
b11010100 7
b11010011 6
1&
#4260
0&
#4270
b11010101 5
b11010101 7
b11010100 6
1&
#4280
0&
#4290
b11010110 5
b11010110 7
b11010101 6
1&
#4300
0&
#4310
b11010111 5
b11010111 7
b11010110 6
1&
#4320
0&
#4330
b11011000 5
b11011000 7
b11010111 6
1&
#4340
0&
#4350
b11011001 5
b11011001 7
b11011000 6
1&
#4360
0&
#4370
b11011010 5
b11011010 7
b11011001 6
1&
#4380
0&
#4390
b11011011 5
b11011011 7
b11011010 6
1&
#4400
0&
#4410
b11011100 5
b11011100 7
b11011011 6
1&
#4420
0&
#4430
b11011101 5
b11011101 7
b11011100 6
1&
#4440
0&
#4450
b11011110 5
b11011110 7
b11011101 6
1&
#4460
0&
#4470
b11011111 5
b11011111 7
b11011110 6
1&
#4480
0&
#4490
b11100000 5
b11100000 7
b11011111 6
1&
#4500
0&
0%
#4510
b11100001 5
b11100001 7
b11100000 6
1&
#4520
0&
#4530
b11100010 5
b11100010 7
b11100001 6
1&
#4540
0&
#4550
b11100011 5
b11100011 7
b11100010 6
1&
#4560
0&
#4570
b11100100 5
b11100100 7
b11100011 6
1&
#4580
0&
#4590
b11100101 5
b11100101 7
b11100100 6
1&
#4600
0&
#4610
b11100110 5
b11100110 7
b11100101 6
1&
#4620
0&
#4630
b11100111 5
b11100111 7
b11100110 6
1&
#4640
0&
#4650
b11101000 5
b11101000 7
b11100111 6
1&
#4660
0&
#4670
b11101001 5
b11101001 7
b11101000 6
1&
#4680
0&
#4690
b11101010 5
b11101010 7
b11101001 6
1&
#4700
0&
#4710
b11101011 5
b11101011 7
b11101010 6
1&
#4720
0&
#4730
b11101100 5
b11101100 7
b11101011 6
1&
#4740
0&
#4750
b11101101 5
b11101101 7
b11101100 6
1&
#4760
0&
#4770
b11101110 5
b11101110 7
b11101101 6
1&
#4780
0&
#4790
b11101111 5
b11101111 7
b11101110 6
1&
#4800
0&
#4810
b11110000 5
b11110000 7
b11101111 6
1&
#4820
0&
1%
#4830
b11110001 5
b11110001 7
b11110000 6
1&
#4840
0&
#4850
b11110010 5
b11110010 7
b11110001 6
1&
#4860
0&
#4870
b11110011 5
b11110011 7
b11110010 6
1&
#4880
0&
#4890
b11110100 5
b11110100 7
b11110011 6
1&
#4900
0&
#4910
b11110101 5
b11110101 7
b11110100 6
1&
#4920
0&
#4930
b11110110 5
b11110110 7
b11110101 6
1&
#4940
0&
#4950
b11110111 5
b11110111 7
b11110110 6
1&
#4960
0&
#4970
b11111000 5
b11111000 7
b11110111 6
1&
#4980
0&
#4990
b11111001 5
b11111001 7
b11111000 6
1&
#5000
0&
#5010
b11111010 5
b11111010 7
b11111001 6
1&
#5020
0&
#5030
b11111011 5
b11111011 7
b11111010 6
1&
#5040
0&
#5050
b11111100 5
b11111100 7
b11111011 6
1&
#5060
0&
#5070
b11111101 5
b11111101 7
b11111100 6
1&
#5080
0&
#5090
b11111110 5
b11111110 7
b11111101 6
1&
#5100
0&
#5110
b11111111 5
b11111111 7
b11111110 6
1&
#5120
0&
#5130
b100000000 5
b100000000 7
b11111111 6
1&
#5140
0&
0%
#5150
b100000001 5
b100000001 7
b100000000 6
1&
#5160
0&
#5170
b100000010 5
b100000010 7
b100000001 6
1&
#5180
0&
#5190
b100000011 5
b100000011 7
b100000010 6
1&
#5200
0&
#5210
b100000100 5
b100000100 7
b100000011 6
1&
#5220
0&
#5230
b100000101 5
b100000101 7
b100000100 6
1&
#5240
0&
#5250
b100000110 5
b100000110 7
b100000101 6
1&
#5260
0&
#5270
b100000111 5
b100000111 7
b100000110 6
1&
#5280
0&
#5290
b100001000 5
b100001000 7
b100000111 6
1&
#5300
0&
#5310
b100001001 5
b100001001 7
b100001000 6
1&
#5320
0&
#5330
b100001010 5
b100001010 7
b100001001 6
1&
#5340
0&
#5350
b100001011 5
b100001011 7
b100001010 6
1&
#5360
0&
#5370
b100001100 5
b100001100 7
b100001011 6
1&
#5380
0&
#5390
b100001101 5
b100001101 7
b100001100 6
1&
#5400
0&
#5410
b100001110 5
b100001110 7
b100001101 6
1&
#5420
0&
#5430
b100001111 5
b100001111 7
b100001110 6
1&
#5440
0&
#5450
b100010000 5
b100010000 7
b100001111 6
1&
#5460
0&
1%
#5470
b100010001 5
b100010001 7
b100010000 6
1&
#5480
0&
#5490
b100010010 5
b100010010 7
b100010001 6
1&
#5500
0&
#5510
b100010011 5
b100010011 7
b100010010 6
1&
#5520
0&
#5530
b100010100 5
b100010100 7
b100010011 6
1&
#5540
0&
#5550
b100010101 5
b100010101 7
b100010100 6
1&
#5560
0&
#5570
b100010110 5
b100010110 7
b100010101 6
1&
#5580
0&
#5590
b100010111 5
b100010111 7
b100010110 6
1&
#5600
0&
#5610
b100011000 5
b100011000 7
b100010111 6
1&
#5620
0&
#5630
b100011001 5
b100011001 7
b100011000 6
1&
#5640
0&
#5650
b100011010 5
b100011010 7
b100011001 6
1&
#5660
0&
#5670
b100011011 5
b100011011 7
b100011010 6
1&
#5680
0&
#5690
b100011100 5
b100011100 7
b100011011 6
1&
#5700
0&
#5710
b100011101 5
b100011101 7
b100011100 6
1&
#5720
0&
#5730
b100011110 5
b100011110 7
b100011101 6
1&
#5740
0&
#5750
b100011111 5
b100011111 7
b100011110 6
1&
#5760
0&
#5770
b100100000 5
b100100000 7
b100011111 6
1&
#5780
0&
0%
#5790
b100100001 5
b100100001 7
b100100000 6
1&
#5800
0&
#5810
b100100010 5
b100100010 7
b100100001 6
1&
#5820
0&
#5830
b100100011 5
b100100011 7
b100100010 6
1&
#5840
0&
#5850
b100100100 5
b100100100 7
b100100011 6
1&
#5860
0&
#5870
b100100101 5
b100100101 7
b100100100 6
1&
#5880
0&
#5890
b100100110 5
b100100110 7
b100100101 6
1&
#5900
0&
#5910
b100100111 5
b100100111 7
b100100110 6
1&
#5920
0&
#5930
b100101000 5
b100101000 7
b100100111 6
1&
#5940
0&
#5950
b100101001 5
b100101001 7
b100101000 6
1&
#5960
0&
#5970
b100101010 5
b100101010 7
b100101001 6
1&
#5980
0&
#5990
b100101011 5
b100101011 7
b100101010 6
1&
#6000
0&
#6010
b100101100 5
b100101100 7
b100101011 6
1&
#6020
0&
#6030
b100101101 5
b100101101 7
b100101100 6
1&
#6040
0&
#6050
b100101110 5
b100101110 7
b100101101 6
1&
#6060
0&
0*
#6070
b100101111 5
b100101111 7
b100101110 6
1&
#6080
0&
#6090
b100110000 5
b100110000 7
b100101111 6
1&
#6100
0&
1%
#6110
b100110001 5
b100110001 7
b100110000 6
1&
#6120
0&
#6130
b100110010 5
b100110010 7
b100110001 6
1&
#6140
0&
#6150
b100110011 5
b100110011 7
b100110010 6
1&
#6160
0&
#6170
b100110100 5
b100110100 7
b100110011 6
1&
#6180
0&
#6190
b100110101 5
b100110101 7
b100110100 6
1&
#6200
0&
#6210
b100110110 5
b100110110 7
b100110101 6
1&
#6220
0&
#6230
b100110111 5
b100110111 7
b100110110 6
1&
#6240
0&
#6250
b100111000 5
b100111000 7
b100110111 6
1&
#6260
0&
#6270
b100111001 5
b100111001 7
b100111000 6
1&
#6280
0&
#6290
b100111010 5
b100111010 7
b100111001 6
1&
#6300
0&
#6310
b100111011 5
b100111011 7
b100111010 6
1&
#6320
0&
#6330
b100111100 5
b100111100 7
b100111011 6
1&
#6340
0&
#6350
b100111101 5
b100111101 7
b100111100 6
1&
#6360
0&
#6370
b100111110 5
b100111110 7
b100111101 6
1&
#6380
0&
#6390
b100111111 5
b100111111 7
b100111110 6
1&
#6400
0&
#6410
b101000000 5
b101000000 7
b100111111 6
1&
#6420
0&
0%
