HW/01GRUPO1/02verilog/Proyecto_P/FIFO/div_freq.v
module div_freq #(
              parameter   fi     = 50000000,        //<- fFPGA/2=fi  
              parameter   fs	 = 36000000    ,    //<- flckout=fs
parameter   fi1     = 50000000,        //<- fFPGA/2=fi  
              parameter   fs1	 = 50000  ,      //<- flckout=fs
parameter   fi2     = 50000000,        //<- fFPGA/2=fi  
              parameter   fs2	 = 33000       //<- flckout=fs
  )(input clk, output reg clkout,output reg clkout1,output reg clkout2,input reset, input reset1, input reset2, output reg led, output reg led1, output reg led2);


initial clkout=0;
initial clkout1=0;
initial clkout2=0;

initial led=0;
initial led1=0;
initial led2=0;

reg [31:0] count;
initial count<= fi/fs;

reg [31:0] count1;
initial count1<= fi1/fs1;

reg [31:0] count2;
initial count2<= fi2/fs2;

always @(posedge  clk)
begin
	if (reset) begin
	led=1;
		
		if (count==0)begin
			clkout <=~clkout;
			count <= fi/fs;
		end	
		else begin
		count <=count-1;
		end

	end
	else begin
	led=0;
		count <= fi/fs;
		clkout <=0;
	end	
end

always @(posedge  clk)
begin
	if (reset1) begin
	led1=1;
		
		if (count1==0)begin
			clkout1 <=~clkout1;
			count1 <= fi1/fs1;
		end	
		else begin
		count1 <=count1-1;
		end

	end
	else begin
	led1=0;
		count1 <= fi1/fs1;
		clkout1 <=0;
	end	
end

always @(posedge  clk)
begin
	if (reset2) begin
	led2=1;
		
		if (count2==0)begin
			clkout2 <=~clkout2;
			count2 <= fi2/fs2;
		end	
		else begin
		count2 <=count2-1;
		end

	end
	else begin
	led2=0;
		count2 <= fi2/fs2;
		clkout2 <=0;
	end	
end

endmodule

HW/01GRUPO1/02verilog/Proyecto_P/FIFO/fifo.v
module fifo # (parameter abits = 4, dbits = 2)(
    input clk,
    input reset,
   // input href,
   // input vsync,
    //input rd,
  input [dbits-1:0] din,
    output empty,
    output full,
  output [dbits-1:0] dout,
	input rs,rs1,rs2,
	output l0,l1,l2,
	input rd
    );

wire clock,href,vsync;

div_freq ucc (.clk(clk), .clkout(clock),.clkout1(href),.clkout2(vsync),.reset(rs), .reset1(rs1), .reset2(rs2), .led(l0), .led1(l1), .led2(l2));

wire wr;
reg [dbits-1:0] out;
assign wr = href & ~vsync;

reg [dbits-1:0] regarray[2**abits-1:0]; //number of words in fifo = 2^(number of address bits)
reg [abits-1:0] wr_reg, wr_next, wr_succ; //points to the register that needs to be written to
reg [abits-1:0] rd_reg, rd_next, rd_succ; //points to the register that needs to be read from
reg full_reg, empty_reg, full_next, empty_next;
 
assign wr_en = wr & ~full; //only write if write signal is high and fifo is not full
 
//always block for write operation
always @ (posedge clock)
 begin
  if(wr_en)
   regarray[wr_reg] <= din;  //at wr_reg location of regarray store what is given at din
 
 end
  
//always block for read operation
always @ (posedge clock)
 begin
  if(rd)
   out <= regarray[rd_reg];
 end
  
 
always @ (posedge clock or posedge reset)
 begin
  if (reset)
   begin
   wr_reg <= 0;
   rd_reg <= 0;
   full_reg <= 1'b0;
   empty_reg <= 1'b1;
   end
   
  else
   begin
   wr_reg <= wr_next; //created the next registers to avoid the error of mixing blocking and non blocking assignment to the same signal
   rd_reg <= rd_next;
   full_reg <= full_next;
   empty_reg <= empty_next;
   end
 end
  
always @(*)
 begin
  wr_succ = wr_reg + 1; //assigned to new value as wr_next cannot be tested for in same always block
  rd_succ = rd_reg + 1; //assigned to new value as rd_next cannot be tested for in same always block
  wr_next = wr_reg;  //defaults state stays the same
  rd_next = rd_reg;  //defaults state stays the same
  full_next = full_reg;  //defaults state stays the same
  empty_next = empty_reg;  //defaults state stays the same
   
   case({wr,rd})
    //2'b00: do nothing LOL..
     
    2'b01: //read
     begin
      if(~empty) //if fifo is not empty continue
       begin
        rd_next = rd_succ;
        full_next = 1'b0;
       if(rd_succ == wr_reg) //all data has been read
         empty_next = 1'b1;  //its empty again
       end
     end
     
    2'b10: //write
     begin
       
      if(~full) //if fifo is not full continue
       begin
        wr_next = wr_succ;
        empty_next = 1'b0;
        if(wr_succ == (2**abits-1)) //all registers have been written to
         full_next = 1'b1;   //its full now
       end
     end
      
    2'b11: //read and write
     begin
      wr_next = wr_succ;
      rd_next = rd_succ;
     end
     //no empty or full flag will be checked for or asserted in this state since data is being written to and read from together it can  not get full in this state.
    endcase
    
 
 end
 
assign full = full_reg;
assign empty = empty_reg;
assign dout = out;
endmodule

HW/01GRUPO1/02verilog/FIFO/FIFO/fifo_TB.v
//----------------------------------------------------------------------------
`timescale 1 ns / 100 ps

module fifo_TB;

parameter tck              = 3;       // clock period in ns
//----------------------------------------------------------------------------
//----------------------------------------------------------------------------
reg rs,rs1,rs2;
reg clk;
reg rst;
reg rd;
reg [1:0] data_in;

//----------------------------------------------------------------------------
// Device Under Test 
//------------------------------------------------------------------

fifo  uut(.reset(rst),.clk(clk),.din(data_in),.rs(rs),.rs1(rs1),.rs2(rs2),.rd(rd));


/* Clocking device */
initial begin
	clk <= 0;
	rst <=1;
	rs1 <=1;
rs <=1;
rs2 <=1;
rd<=0;
	#(2*tck) rst=0;
	 
	
end

always #(tck/2) clk <= ~clk;


initial begin
#4;
data_in=1; #200; 

data_in=1;  #200; 
data_in=1;   #200; 
data_in=1;  #200; 
data_in=1;   #200; 
data_in=1;  #200; 
data_in=1;   #200; 

data_in=0;  #200; 
data_in=0;   #200; 
data_in=0;   #200; 
data_in=0;   #200; 
data_in=0; #200; 

data_in=1;   #200; 
data_in=1;   #200; 
data_in=1;   #200; 
data_in=1;  #200; 
data_in=1;  #200; 
rs2=0;
rs1=0;
rd <= ~rd;#200; 
rd <= ~rd;#200; 
rd <= ~rd;#200; 
rd <= ~rd;#200; 
rd <= ~rd;#200; 
rd <= ~rd;#200; 
rd <= ~rd;#200; 
rd <= ~rd;#200; 
rd <= ~rd;#200;
rd <= ~rd;#200; 
rd <= ~rd;#200; 
rd <= ~rd;#200; 
rd <= ~rd;#200; 
rd <= ~rd;#200; 
rd <= ~rd;#200; 
rd <= ~rd;#200; 
rd <= ~rd;#200; 
rd <= ~rd;#200;
rd <= ~rd;#200; 
rd <= ~rd;#200; 
rd <= ~rd;#200; 
rd <= ~rd;#200; 
rd <= ~rd;#200; 
rd <= ~rd;#200; 
rd <= ~rd;#200; 
rd <= ~rd;#200; 
rd <= ~rd;#200;
rd <= ~rd;#200; 
rd <= ~rd;#200; 
rd <= ~rd;#200; 
rd <= ~rd;#200; 
rd <= ~rd;#200; 
rd <= ~rd;#200; 
rd <= ~rd;#200; 
rd <= ~rd;#200; 
rd <= ~rd;#200;    

end

initial begin: TEST_CASE
     $dumpfile("fifo_TB.vcd");
     $dumpvars(-1, uut);
     #(20000) $finish;
   end

endmodule //

HW/01GRUPO1/02verilog/FIFO/FIFO/simulation/fifo_TB.vcd
$date
	Fri Mar  9 14:02:45 2018
$end
$version
	Icarus Verilog
$end
$timescale
	100ps
$end
$scope module fifo_TB $end
$scope module uut $end
$var wire 1 ! clk $end
$var wire 1 " clock $end
$var wire 2 # din [1:0] $end
$var wire 2 $ dout [1:0] $end
$var wire 1 % empty $end
$var wire 1 & full $end
$var wire 1 ' href $end
$var wire 1 ( l0 $end
$var wire 1 ) l1 $end
$var wire 1 * l2 $end
$var wire 1 + rd $end
$var wire 1 , reset $end
$var wire 1 - rs $end
$var wire 1 . rs1 $end
$var wire 1 / rs2 $end
$var wire 1 0 vsync $end
$var wire 1 1 wr $end
$var wire 1 2 wr_en $end
$var reg 1 3 empty_next $end
$var reg 1 4 empty_reg $end
$var reg 1 5 full_next $end
$var reg 1 6 full_reg $end
$var reg 2 7 out [1:0] $end
$var reg 4 8 rd_next [3:0] $end
$var reg 4 9 rd_reg [3:0] $end
$var reg 4 : rd_succ [3:0] $end
$var reg 4 ; wr_next [3:0] $end
$var reg 4 < wr_reg [3:0] $end
$var reg 4 = wr_succ [3:0] $end
$scope module ucc $end
$var wire 1 ! clk $end
$var wire 1 - reset $end
$var wire 1 . reset1 $end
$var wire 1 / reset2 $end
$var reg 1 > clkout $end
$var reg 1 ? clkout1 $end
$var reg 1 @ clkout2 $end
$var reg 32 A count [31:0] $end
$var reg 32 B count1 [31:0] $end
$var reg 32 C count2 [31:0] $end
$var reg 1 D led $end
$var reg 1 E led1 $end
$var reg 1 F led2 $end
$upscope $end
$upscope $end
$upscope $end
$enddefinitions $end
#0
$dumpvars
0F
0E
0D
b11111010000 C
b1111101000 B
b111110100 A
0@
0?
0>
b1 =
b0 <
b0 ;
b1 :
b0 9
b0 8
bx 7
06
05
14
13
02
01
00
1/
1.
1-
1,
0+
0*
0)
0(
0'
0&
1%
bx $
bx #
0"
0!
$end
#10
b111110011 A
b1111100111 B
b11111001111 C
1D
1(
1E
1)
1F
1*
1!
#20
0!
#30
b11111001110 C
b1111100110 B
b111110010 A
1!
#40
0!
b1 #
#50
b111110001 A
b1111100101 B
b11111001101 C
1!
#60
0!
0,
#70
b11111001100 C
b1111100100 B
b111110000 A
1!
#80
0!
#90
b111101111 A
b1111100011 B
b11111001011 C
1!
#100
0!
#110
b11111001010 C
b1111100010 B
b111101110 A
1!
#120
0!
#130
b111101101 A
b1111100001 B
b11111001001 C
1!
#140
0!
#150
b11111001000 C
b1111100000 B
b111101100 A
1!
#160
0!
#170
b111101011 A
b1111011111 B
b11111000111 C
1!
#180
0!
#190
b11111000110 C
b1111011110 B
b111101010 A
1!
#200
0!
#210
b111101001 A
b1111011101 B
b11111000101 C
1!
#220
0!
#230
b11111000100 C
b1111011100 B
b111101000 A
1!
#240
0!
#250
b111100111 A
b1111011011 B
b11111000011 C
1!
#260
0!
#270
b11111000010 C
b1111011010 B
b111100110 A
1!
#280
0!
#290
b111100101 A
b1111011001 B
b11111000001 C
1!
#300
0!
#310
b11111000000 C
b1111011000 B
b111100100 A
1!
#320
0!
#330
b111100011 A
b1111010111 B
b11110111111 C
1!
#340
0!
#350
b11110111110 C
b1111010110 B
b111100010 A
1!
#360
0!
#370
b111100001 A
b1111010101 B
b11110111101 C
1!
#380
0!
#390
b11110111100 C
b1111010100 B
b111100000 A
1!
#400
0!
#410
b111011111 A
b1111010011 B
b11110111011 C
1!
#420
0!
#430
b11110111010 C
b1111010010 B
b111011110 A
1!
#440
0!
#450
b111011101 A
b1111010001 B
b11110111001 C
1!
#460
0!
#470
b11110111000 C
b1111010000 B
b111011100 A
1!
#480
0!
#490
b111011011 A
b1111001111 B
b11110110111 C
1!
#500
0!
#510
b11110110110 C
b1111001110 B
b111011010 A
1!
#520
0!
#530
b111011001 A
b1111001101 B
b11110110101 C
1!
#540
0!
#550
b11110110100 C
b1111001100 B
b111011000 A
1!
#560
0!
#570
b111010111 A
b1111001011 B
b11110110011 C
1!
#580
0!
#590
b11110110010 C
b1111001010 B
b111010110 A
1!
#600
0!
#610
b111010101 A
b1111001001 B
b11110110001 C
1!
#620
0!
#630
b11110110000 C
b1111001000 B
b111010100 A
1!
#640
0!
#650
b111010011 A
b1111000111 B
b11110101111 C
1!
#660
0!
#670
b11110101110 C
b1111000110 B
b111010010 A
1!
#680
0!
#690
b111010001 A
b1111000101 B
b11110101101 C
1!
#700
0!
#710
b11110101100 C
b1111000100 B
b111010000 A
1!
#720
0!
#730
b111001111 A
b1111000011 B
b11110101011 C
1!
#740
0!
#750
b11110101010 C
b1111000010 B
b111001110 A
1!
#760
0!
#770
b111001101 A
b1111000001 B
b11110101001 C
1!
#780
0!
#790
b11110101000 C
b1111000000 B
b111001100 A
1!
#800
0!
#810
b111001011 A
b1110111111 B
b11110100111 C
1!
#820
0!
#830
b11110100110 C
b1110111110 B
b111001010 A
1!
#840
0!
#850
b111001001 A
b1110111101 B
b11110100101 C
1!
#860
0!
#870
b11110100100 C
b1110111100 B
b111001000 A
1!
#880
0!
#890
b111000111 A
b1110111011 B
b11110100011 C
1!
#900
0!
#910
b11110100010 C
b1110111010 B
b111000110 A
1!
#920
0!
#930
b111000101 A
b1110111001 B
b11110100001 C
1!
#940
0!
#950
b11110100000 C
b1110111000 B
b111000100 A
1!
#960
0!
#970
b111000011 A
b1110110111 B
b11110011111 C
1!
#980
0!
#990
b11110011110 C
b1110110110 B
b111000010 A
1!
#1000
0!
#1010
b111000001 A
b1110110101 B
b11110011101 C
1!
#1020
0!
#1030
b11110011100 C
b1110110100 B
b111000000 A
1!
#1040
0!
#1050
b110111111 A
b1110110011 B
b11110011011 C
1!
#1060
0!
#1070
b11110011010 C
b1110110010 B
b110111110 A
1!
#1080
0!
#1090
b110111101 A
b1110110001 B
b11110011001 C
1!
#1100
0!
#1110
b11110011000 C
b1110110000 B
b110111100 A
1!
#1120
0!
#1130
b110111011 A
b1110101111 B
b11110010111 C
1!
#1140
0!
#1150
b11110010110 C
b1110101110 B
b110111010 A
1!
#1160
0!
#1170
b110111001 A
b1110101101 B
b11110010101 C
1!
#1180
0!
#1190
b11110010100 C
b1110101100 B
b110111000 A
1!
#1200
0!
#1210
b110110111 A
b1110101011 B
b11110010011 C
1!
#1220
0!
#1230
b11110010010 C
b1110101010 B
b110110110 A
1!
#1240
0!
#1250
b110110101 A
b1110101001 B
b11110010001 C
1!
#1260
0!
#1270
b11110010000 C
b1110101000 B
b110110100 A
1!
#1280
0!
#1290
b110110011 A
b1110100111 B
b11110001111 C
1!
#1300
0!
#1310
b11110001110 C
b1110100110 B
b110110010 A
1!
#1320
0!
#1330
b110110001 A
b1110100101 B
b11110001101 C
1!
#1340
0!
#1350
b11110001100 C
b1110100100 B
b110110000 A
1!
#1360
0!
#1370
b110101111 A
b1110100011 B
b11110001011 C
1!
#1380
0!
#1390
b11110001010 C
b1110100010 B
b110101110 A
1!
#1400
0!
#1410
b110101101 A
b1110100001 B
b11110001001 C
1!
#1420
0!
#1430
b11110001000 C
b1110100000 B
b110101100 A
1!
#1440
0!
#1450
b110101011 A
b1110011111 B
b11110000111 C
1!
#1460
0!
#1470
b11110000110 C
b1110011110 B
b110101010 A
1!
#1480
0!
#1490
b110101001 A
b1110011101 B
b11110000101 C
1!
#1500
0!
#1510
b11110000100 C
b1110011100 B
b110101000 A
1!
#1520
0!
#1530
b110100111 A
b1110011011 B
b11110000011 C
1!
#1540
0!
#1550
b11110000010 C
b1110011010 B
b110100110 A
1!
#1560
0!
#1570
b110100101 A
b1110011001 B
b11110000001 C
1!
#1580
0!
#1590
b11110000000 C
b1110011000 B
b110100100 A
1!
#1600
0!
#1610
b110100011 A
b1110010111 B
b11101111111 C
1!
#1620
0!
#1630
b11101111110 C
b1110010110 B
b110100010 A
1!
#1640
0!
#1650
b110100001 A
b1110010101 B
b11101111101 C
1!
#1660
0!
#1670
b11101111100 C
b1110010100 B
b110100000 A
1!
#1680
0!
#1690
b110011111 A
b1110010011 B
b11101111011 C
1!
#1700
0!
#1710
b11101111010 C
b1110010010 B
b110011110 A
1!
#1720
0!
#1730
b110011101 A
b1110010001 B
b11101111001 C
1!
#1740
0!
#1750
b11101111000 C
b1110010000 B
b110011100 A
1!
#1760
0!
#1770
b110011011 A
b1110001111 B
b11101110111 C
1!
#1780
0!
#1790
b11101110110 C
b1110001110 B
b110011010 A
1!
#1800
0!
#1810
b110011001 A
b1110001101 B
b11101110101 C
1!
#1820
0!
#1830
b11101110100 C
b1110001100 B
b110011000 A
1!
#1840
0!
#1850
b110010111 A
b1110001011 B
b11101110011 C
1!
#1860
0!
#1870
b11101110010 C
b1110001010 B
b110010110 A
1!
#1880
0!
#1890
b110010101 A
b1110001001 B
b11101110001 C
1!
#1900
0!
#1910
b11101110000 C
b1110001000 B
b110010100 A
1!
#1920
0!
#1930
b110010011 A
b1110000111 B
b11101101111 C
1!
#1940
0!
#1950
b11101101110 C
b1110000110 B
b110010010 A
1!
#1960
0!
#1970
b110010001 A
b1110000101 B
b11101101101 C
1!
#1980
0!
#1990
b11101101100 C
b1110000100 B
b110010000 A
1!
#2000
0!
#2010
b110001111 A
b1110000011 B
b11101101011 C
1!
#2020
0!
#2030
b11101101010 C
b1110000010 B
b110001110 A
1!
#2040
0!
#2050
b110001101 A
b1110000001 B
b11101101001 C
1!
#2060
0!
#2070
b11101101000 C
b1110000000 B
b110001100 A
1!
#2080
0!
#2090
b110001011 A
b1101111111 B
b11101100111 C
1!
#2100
0!
#2110
b11101100110 C
b1101111110 B
b110001010 A
1!
#2120
0!
#2130
b110001001 A
b1101111101 B
b11101100101 C
1!
#2140
0!
#2150
b11101100100 C
b1101111100 B
b110001000 A
1!
#2160
0!
#2170
b110000111 A
b1101111011 B
b11101100011 C
1!
#2180
0!
#2190
b11101100010 C
b1101111010 B
b110000110 A
1!
#2200
0!
#2210
b110000101 A
b1101111001 B
b11101100001 C
1!
#2220
0!
#2230
b11101100000 C
b1101111000 B
b110000100 A
1!
#2240
0!
#2250
b110000011 A
b1101110111 B
b11101011111 C
1!
#2260
0!
#2270
b11101011110 C
b1101110110 B
b110000010 A
1!
#2280
0!
#2290
b110000001 A
b1101110101 B
b11101011101 C
1!
#2300
0!
#2310
b11101011100 C
b1101110100 B
b110000000 A
1!
#2320
0!
#2330
b101111111 A
b1101110011 B
b11101011011 C
1!
#2340
0!
#2350
b11101011010 C
b1101110010 B
b101111110 A
1!
#2360
0!
#2370
b101111101 A
b1101110001 B
b11101011001 C
1!
#2380
0!
#2390
b11101011000 C
b1101110000 B
b101111100 A
1!
#2400
0!
#2410
b101111011 A
b1101101111 B
b11101010111 C
1!
#2420
0!
#2430
b11101010110 C
b1101101110 B
b101111010 A
1!
#2440
0!
#2450
b101111001 A
b1101101101 B
b11101010101 C
1!
#2460
0!
#2470
b11101010100 C
b1101101100 B
b101111000 A
1!
#2480
0!
#2490
b101110111 A
b1101101011 B
b11101010011 C
1!
#2500
0!
#2510
b11101010010 C
b1101101010 B
b101110110 A
1!
#2520
0!
#2530
b101110101 A
b1101101001 B
b11101010001 C
1!
#2540
0!
#2550
b11101010000 C
b1101101000 B
b101110100 A
1!
#2560
0!
#2570
b101110011 A
b1101100111 B
b11101001111 C
1!
#2580
0!
#2590
b11101001110 C
b1101100110 B
b101110010 A
1!
#2600
0!
#2610
b101110001 A
b1101100101 B
b11101001101 C
1!
#2620
0!
#2630
b11101001100 C
b1101100100 B
b101110000 A
1!
#2640
0!
#2650
b101101111 A
b1101100011 B
b11101001011 C
1!
#2660
0!
#2670
b11101001010 C
b1101100010 B
b101101110 A
1!
#2680
0!
#2690
b101101101 A
b1101100001 B
b11101001001 C
1!
#2700
0!
#2710
b11101001000 C
b1101100000 B
b101101100 A
1!
#2720
0!
#2730
b101101011 A
b1101011111 B
b11101000111 C
1!
#2740
0!
#2750
b11101000110 C
b1101011110 B
b101101010 A
1!
#2760
0!
#2770
b101101001 A
b1101011101 B
b11101000101 C
1!
#2780
0!
#2790
b11101000100 C
b1101011100 B
b101101000 A
1!
#2800
0!
#2810
b101100111 A
b1101011011 B
b11101000011 C
1!
#2820
0!
#2830
b11101000010 C
b1101011010 B
b101100110 A
1!
#2840
0!
#2850
b101100101 A
b1101011001 B
b11101000001 C
1!
#2860
0!
#2870
b11101000000 C
b1101011000 B
b101100100 A
1!
#2880
0!
#2890
b101100011 A
b1101010111 B
b11100111111 C
1!
#2900
0!
#2910
b11100111110 C
b1101010110 B
b101100010 A
1!
#2920
0!
#2930
b101100001 A
b1101010101 B
b11100111101 C
1!
#2940
0!
#2950
b11100111100 C
b1101010100 B
b101100000 A
1!
#2960
0!
#2970
b101011111 A
b1101010011 B
b11100111011 C
1!
#2980
0!
#2990
b11100111010 C
b1101010010 B
b101011110 A
1!
#3000
0!
#3010
b101011101 A
b1101010001 B
b11100111001 C
1!
#3020
0!
#3030
b11100111000 C
b1101010000 B
b101011100 A
1!
#3040
0!
#3050
b101011011 A
b1101001111 B
b11100110111 C
1!
#3060
0!
#3070
b11100110110 C
b1101001110 B
b101011010 A
1!
#3080
0!
#3090
b101011001 A
b1101001101 B
b11100110101 C
1!
#3100
0!
#3110
b11100110100 C
b1101001100 B
b101011000 A
1!
#3120
0!
#3130
b101010111 A
b1101001011 B
b11100110011 C
1!
#3140
0!
#3150
b11100110010 C
b1101001010 B
b101010110 A
1!
#3160
0!
#3170
b101010101 A
b1101001001 B
b11100110001 C
1!
#3180
0!
#3190
b11100110000 C
b1101001000 B
b101010100 A
1!
#3200
0!
#3210
b101010011 A
b1101000111 B
b11100101111 C
1!
#3220
0!
#3230
b11100101110 C
b1101000110 B
b101010010 A
1!
#3240
0!
#3250
b101010001 A
b1101000101 B
b11100101101 C
1!
#3260
0!
#3270
b11100101100 C
b1101000100 B
b101010000 A
1!
#3280
0!
#3290
b101001111 A
b1101000011 B
b11100101011 C
1!
#3300
0!
#3310
b11100101010 C
b1101000010 B
b101001110 A
1!
#3320
0!
#3330
b101001101 A
b1101000001 B
b11100101001 C
1!
#3340
0!
#3350
b11100101000 C
b1101000000 B
b101001100 A
1!
#3360
0!
#3370
b101001011 A
b1100111111 B
b11100100111 C
1!
#3380
0!
#3390
b11100100110 C
b1100111110 B
b101001010 A
1!
#3400
0!
#3410
b101001001 A
b1100111101 B
b11100100101 C
1!
#3420
0!
#3430
b11100100100 C
b1100111100 B
b101001000 A
1!
#3440
0!
#3450
b101000111 A
b1100111011 B
b11100100011 C
1!
#3460
0!
#3470
b11100100010 C
b1100111010 B
b101000110 A
1!
#3480
0!
#3490
b101000101 A
b1100111001 B
b11100100001 C
1!
#3500
0!
#3510
b11100100000 C
b1100111000 B
b101000100 A
1!
#3520
0!
#3530
b101000011 A
b1100110111 B
b11100011111 C
1!
#3540
0!
#3550
b11100011110 C
b1100110110 B
b101000010 A
1!
#3560
0!
#3570
b101000001 A
b1100110101 B
b11100011101 C
1!
#3580
0!
#3590
b11100011100 C
b1100110100 B
b101000000 A
1!
#3600
0!
#3610
b100111111 A
b1100110011 B
b11100011011 C
1!
#3620
0!
#3630
b11100011010 C
b1100110010 B
b100111110 A
1!
#3640
0!
#3650
b100111101 A
b1100110001 B
b11100011001 C
1!
#3660
0!
#3670
b11100011000 C
b1100110000 B
b100111100 A
1!
#3680
0!
#3690
b100111011 A
b1100101111 B
b11100010111 C
1!
#3700
0!
#3710
b11100010110 C
b1100101110 B
b100111010 A
1!
#3720
0!
#3730
b100111001 A
b1100101101 B
b11100010101 C
1!
#3740
0!
#3750
b11100010100 C
b1100101100 B
b100111000 A
1!
#3760
0!
#3770
b100110111 A
b1100101011 B
b11100010011 C
1!
#3780
0!
#3790
b11100010010 C
b1100101010 B
b100110110 A
1!
#3800
0!
#3810
b100110101 A
b1100101001 B
b11100010001 C
1!
#3820
0!
#3830
b11100010000 C
b1100101000 B
b100110100 A
1!
#3840
0!
#3850
b100110011 A
b1100100111 B
b11100001111 C
1!
#3860
0!
#3870
b11100001110 C
b1100100110 B
b100110010 A
1!
#3880
0!
#3890
b100110001 A
b1100100101 B
b11100001101 C
1!
#3900
0!
#3910
b11100001100 C
b1100100100 B
b100110000 A
1!
#3920
0!
#3930
b100101111 A
b1100100011 B
b11100001011 C
1!
#3940
0!
#3950
b11100001010 C
b1100100010 B
b100101110 A
1!
#3960
0!
#3970
b100101101 A
b1100100001 B
b11100001001 C
1!
#3980
0!
#3990
b11100001000 C
b1100100000 B
b100101100 A
1!
#4000
0!
#4010
b100101011 A
b1100011111 B
b11100000111 C
1!
#4020
0!
#4030
b11100000110 C
b1100011110 B
b100101010 A
1!
#4040
0!
#4050
b100101001 A
b1100011101 B
b11100000101 C
1!
#4060
0!
#4070
b11100000100 C
b1100011100 B
b100101000 A
1!
#4080
0!
#4090
b100100111 A
b1100011011 B
b11100000011 C
1!
#4100
0!
#4110
b11100000010 C
b1100011010 B
b100100110 A
1!
#4120
0!
#4130
b100100101 A
b1100011001 B
b11100000001 C
1!
#4140
0!
#4150
b11100000000 C
b1100011000 B
b100100100 A
1!
#4160
0!
#4170
b100100011 A
b1100010111 B
b11011111111 C
1!
#4180
0!
#4190
b11011111110 C
b1100010110 B
b100100010 A
1!
#4200
0!
#4210
b100100001 A
b1100010101 B
b11011111101 C
1!
#4220
0!
#4230
b11011111100 C
b1100010100 B
b100100000 A
1!
#4240
0!
#4250
b100011111 A
b1100010011 B
b11011111011 C
1!
#4260
0!
#4270
b11011111010 C
b1100010010 B
b100011110 A
1!
#4280
0!
#4290
b100011101 A
b1100010001 B
b11011111001 C
1!
#4300
0!
#4310
b11011111000 C
b1100010000 B
b100011100 A
1!
#4320
0!
#4330
b100011011 A
b1100001111 B
b11011110111 C
1!
#4340
0!
#4350
b11011110110 C
b1100001110 B
b100011010 A
1!
#4360
0!
#4370
b100011001 A
b1100001101 B
b11011110101 C
1!
#4380
0!
#4390
b11011110100 C
b1100001100 B
b100011000 A
1!
#4400
0!
#4410
b100010111 A
b1100001011 B
b11011110011 C
1!
#4420
0!
#4430
b11011110010 C
b1100001010 B
b100010110 A
1!
#4440
0!
#4450
b100010101 A
b1100001001 B
b11011110001 C
1!
#4460
0!
#4470
b11011110000 C
b1100001000 B
b100010100 A
1!
#4480
0!
#4490
b100010011 A
b1100000111 B
b11011101111 C
1!
#4500
0!
#4510
b11011101110 C
b1100000110 B
b100010010 A
1!
#4520
0!
#4530
b100010001 A
b1100000101 B
b11011101101 C
1!
#4540
0!
#4550
b11011101100 C
b1100000100 B
b100010000 A
1!
#4560
0!
#4570
b100001111 A
b1100000011 B
b11011101011 C
1!
#4580
0!
#4590
b11011101010 C
b1100000010 B
b100001110 A
1!
#4600
0!
#4610
b100001101 A
b1100000001 B
b11011101001 C
1!
#4620
0!
#4630
b11011101000 C
b1100000000 B
b100001100 A
1!
#4640
0!
#4650
b100001011 A
b1011111111 B
b11011100111 C
1!
#4660
0!
#4670
b11011100110 C
b1011111110 B
b100001010 A
1!
#4680
0!
#4690
b100001001 A
b1011111101 B
b11011100101 C
1!
#4700
0!
#4710
b11011100100 C
b1011111100 B
b100001000 A
1!
#4720
0!
#4730
b100000111 A
b1011111011 B
b11011100011 C
1!
#4740
0!
#4750
b11011100010 C
b1011111010 B
b100000110 A
1!
#4760
0!
#4770
b100000101 A
b1011111001 B
b11011100001 C
1!
#4780
0!
#4790
b11011100000 C
b1011111000 B
b100000100 A
1!
#4800
0!
#4810
b100000011 A
b1011110111 B
b11011011111 C
1!
#4820
0!
#4830
b11011011110 C
b1011110110 B
b100000010 A
1!
#4840
0!
#4850
b100000001 A
b1011110101 B
b11011011101 C
1!
#4860
0!
#4870
b11011011100 C
b1011110100 B
b100000000 A
1!
#4880
0!
#4890
b11111111 A
b1011110011 B
b11011011011 C
1!
#4900
0!
#4910
b11011011010 C
b1011110010 B
b11111110 A
1!
#4920
0!
#4930
b11111101 A
b1011110001 B
b11011011001 C
1!
#4940
0!
#4950
b11011011000 C
b1011110000 B
b11111100 A
1!
#4960
0!
#4970
b11111011 A
b1011101111 B
b11011010111 C
1!
#4980
0!
#4990
b11011010110 C
b1011101110 B
b11111010 A
1!
#5000
0!
#5010
b11111001 A
b1011101101 B
b11011010101 C
1!
#5020
0!
#5030
b11011010100 C
b1011101100 B
b11111000 A
1!
#5040
0!
#5050
b11110111 A
b1011101011 B
b11011010011 C
1!
#5060
0!
#5070
b11011010010 C
b1011101010 B
b11110110 A
1!
#5080
0!
#5090
b11110101 A
b1011101001 B
b11011010001 C
1!
#5100
0!
#5110
b11011010000 C
b1011101000 B
b11110100 A
1!
#5120
0!
#5130
b11110011 A
b1011100111 B
b11011001111 C
1!
#5140
0!
#5150
b11011001110 C
b1011100110 B
b11110010 A
1!
#5160
0!
#5170
b11110001 A
b1011100101 B
b11011001101 C
1!
#5180
0!
#5190
b11011001100 C
b1011100100 B
b11110000 A
1!
#5200
0!
#5210
b11101111 A
b1011100011 B
b11011001011 C
1!
#5220
0!
#5230
b11011001010 C
b1011100010 B
b11101110 A
1!
#5240
0!
#5250
b11101101 A
b1011100001 B
b11011001001 C
1!
#5260
0!
#5270
b11011001000 C
b1011100000 B
b11101100 A
1!
#5280
0!
#5290
b11101011 A
b1011011111 B
b11011000111 C
1!
#5300
0!
#5310
b11011000110 C
b1011011110 B
b11101010 A
1!
#5320
0!
#5330
b11101001 A
b1011011101 B
b11011000101 C
1!
#5340
0!
#5350
b11011000100 C
b1011011100 B
b11101000 A
1!
#5360
0!
#5370
b11100111 A
b1011011011 B
b11011000011 C
1!
#5380
0!
#5390
b11011000010 C
b1011011010 B
b11100110 A
1!
#5400
0!
#5410
b11100101 A
b1011011001 B
b11011000001 C
1!
#5420
0!
#5430
b11011000000 C
b1011011000 B
b11100100 A
1!
#5440
0!
#5450
b11100011 A
b1011010111 B
b11010111111 C
1!
#5460
0!
#5470
b11010111110 C
b1011010110 B
b11100010 A
1!
#5480
0!
#5490
b11100001 A
b1011010101 B
b11010111101 C
1!
#5500
0!
#5510
b11010111100 C
b1011010100 B
b11100000 A
1!
#5520
0!
#5530
b11011111 A
b1011010011 B
b11010111011 C
1!
#5540
0!
#5550
b11010111010 C
b1011010010 B
b11011110 A
1!
#5560
0!
#5570
b11011101 A
b1011010001 B
b11010111001 C
1!
#5580
0!
#5590
b11010111000 C
b1011010000 B
b11011100 A
1!
#5600
0!
#5610
b11011011 A
b1011001111 B
b11010110111 C
1!
#5620
0!
#5630
b11010110110 C
b1011001110 B
b11011010 A
1!
#5640
0!
#5650
b11011001 A
b1011001101 B
b11010110101 C
1!
#5660
0!
#5670
b11010110100 C
b1011001100 B
b11011000 A
1!
#5680
0!
#5690
b11010111 A
b1011001011 B
b11010110011 C
1!
#5700
0!
#5710
b11010110010 C
b1011001010 B
b11010110 A
1!
#5720
0!
#5730
b11010101 A
b1011001001 B
b11010110001 C
1!
#5740
0!
#5750
b11010110000 C
b1011001000 B
b11010100 A
1!
#5760
0!
#5770
b11010011 A
b1011000111 B
b11010101111 C
1!
#5780
0!
#5790
b11010101110 C
b1011000110 B
b11010010 A
1!
#5800
0!
