HW/03GRUPO3/02verilog/PWM_Top/pwm_servo7.v
module pwm_servo7(input clk,
input enable,
input reset,
input [31:0] d,
input [31:0] t,
output reg pwm
);

reg [31:0] cnt_d;
reg [31:0] cnt_t;

initial begin
 pwm <= 0;
 cnt_d <= 0;
 cnt_t <=0;
end


always @(posedge clk) begin
    if (reset) begin
        pwm <= 0;
        cnt_d <= 0;
        cnt_t <=0;
      end
     else if (cnt_d < d) begin
        cnt_d <= cnt_d +1;
        cnt_t <=0;
        pwm <=1;
     end 
    else if (cnt_t < (t-d)) begin
        cnt_t <= cnt_t + 1;
        pwm <= 0;
    end
    else begin
        cnt_d <= 0;
        cnt_t <=0;
    end
end


endmodule

HW/03GRUPO3/02verilog/LM32_PWM/rtl/wb_pwm/pwm_servo6.v
module pwm_servo6(input clk,
input enable,
input reset,
input [31:0] d,
input [31:0] t,
output reg pwm
);

reg [31:0] cnt_d;
reg [31:0] cnt_t;

initial begin
 pwm <= 0;
 cnt_d <= 0;
 cnt_t <=0;
end

always @(posedge clk) begin
    if (reset) begin
        pwm <= 0;
        cnt_d <= 0;
        cnt_t <=0;
    end
    else if (enable) begin
        if (cnt_d < d) begin
            cnt_d <= cnt_d +1;
            cnt_t <=0;
            pwm <=1;
        end 
        else if (cnt_t < (t-d)) begin
            cnt_t <= cnt_t + 1;
            pwm <= 0;
        end
        else begin
            cnt_d <= 0;
            cnt_t <=0;
            pwm<=0;
        end
    end
end

endmodule

HW/03GRUPO3/02verilog/PWM_Top/pwm_servo5.v
module pwm_servo5(input clk,
input enable,
input reset,
input [31:0] d,
input [31:0] t,
output reg pwm
);

reg [31:0] cnt_d;
reg [31:0] cnt_t;


initial begin
 pwm <= 0;
 cnt_d <= 0;
 cnt_t <=0;
end


always @(posedge clk) begin
    if (reset) begin
        pwm <= 0;
        cnt_d <= 0;
        cnt_t <=0;
      end
     else if (cnt_d < d) begin
        cnt_d <= cnt_d +1;
        cnt_t <=0;
        pwm <=1;
     end 
    else if (cnt_t < (t-d)) begin
        cnt_t <= cnt_t + 1;
        pwm <= 0;
    end
    else begin
        cnt_d <= 0;
        cnt_t <=0;
    end
end


endmodule

HW/03GRUPO3/02verilog/PWM_Top/pwm_servo4.v
module pwm_servo4(input clk,
input enable,
input reset,
input [31:0] d,
input [31:0] t,
output reg pwm
);

reg [31:0] cnt_d;
reg [31:0] cnt_t;

initial begin
 pwm <= 0;
 cnt_d <= 0;
 cnt_t <=0;
end


always @(posedge clk) begin
    if (reset) begin
        pwm <= 0;
        cnt_d <= 0;
        cnt_t <=0;
      end
     else if (cnt_d < d) begin
        cnt_d <= cnt_d +1;
        cnt_t <=0;
        pwm <=1;
     end 
    else if (cnt_t < (t-d)) begin
        cnt_t <= cnt_t + 1;
        pwm <= 0;
    end
    else begin
        cnt_d <= 0;
        cnt_t <=0;
    end
end


endmodule

HW/03GRUPO3/02verilog/PWM_Top/pwm_servo3.v
module pwm_servo3(input clk,
input enable,
input reset,
input [31:0] d,
input [31:0] t,
output reg pwm
);

reg [31:0] cnt_d;
reg [31:0] cnt_t;


initial begin
 pwm <= 0;
 cnt_d <= 0;
 cnt_t <=0;
end


always @(posedge clk) begin
    if (reset) begin
        pwm <= 0;
        cnt_d <= 0;
        cnt_t <=0;
      end
     else if (cnt_d < d) begin
        cnt_d <= cnt_d +1;
        cnt_t <=0;
        pwm <=1;
     end 
    else if (cnt_t < (t-d)) begin
        cnt_t <= cnt_t + 1;
        pwm <= 0;
    end
    else begin
        cnt_d <= 0;
        cnt_t <=0;
    end
end


endmodule

HW/03GRUPO3/02verilog/PWM_Top/pwm_servo2.v
module pwm_servo2(input clk,
input enable,
input reset,
input [31:0] d,
input [31:0] t,
output reg pwm
);

reg [31:0] cnt_d;
reg [31:0] cnt_t;

initial begin
 pwm <= 0;
 cnt_d <= 0;
 cnt_t <=0;
end


always @(posedge clk) begin
    if (reset) begin
        pwm <= 0;
        cnt_d <= 0;
        cnt_t <=0;
      end
     else if (cnt_d < d) begin
        cnt_d <= cnt_d +1;
        cnt_t <=0;
        pwm <=1;
     end 
    else if (cnt_t < (t-d)) begin
        cnt_t <= cnt_t + 1;
        pwm <= 0;
    end
    else begin
        cnt_d <= 0;
        cnt_t <=0;
    end
end


endmodule

HW/03GRUPO3/02verilog/PWM_Top/pwm_servo1.v
module pwm_servo1(input clk,
input enable,
input reset,
input [31:0] d,
input [31:0] t,
output reg pwm
);

reg [31:0] cnt_d;
reg [31:0] cnt_t;


initial begin
 pwm <= 0;
 cnt_d <= 0;
 cnt_t <=0;
end


always @(posedge clk) begin
    if (reset) begin
        pwm <= 0;
        cnt_d <= 0;
        cnt_t <=0;
      end
     else if (cnt_d < d) begin
        cnt_d <= cnt_d +1;
        cnt_t <=0;
        pwm <=1;
     end 
    else if (cnt_t < (t-d)) begin
        cnt_t <= cnt_t + 1;
        pwm <= 0;
    end
    else begin
        cnt_d <= 0;
        cnt_t <=0;
    end
end


endmodule

HW/03GRUPO3/02verilog/LM32_PWM/rtl/wb_pwm/pwm_servo0.v
module pwm_servo0(input clk,
input enable,
input reset,
input [31:0] d,
input [31:0] t,
output reg pwm
);

reg [31:0] cnt_d;
reg [31:0] cnt_t;


initial begin
 pwm <= 0;
 cnt_d <= 0;
 cnt_t <=0;
end


always @(posedge clk) begin
    if (reset) begin
        pwm <= 0;
        cnt_d <= 0;
        cnt_t <=0;
    end
    else if (enable) begin
        if (cnt_d < d) begin
            cnt_d <= cnt_d +1;
            cnt_t <=0;
            pwm <=1;
        end 
        else if (cnt_t < (t-d)) begin
            cnt_t <= cnt_t + 1;
            pwm <= 0;
        end
        else begin
            cnt_d <= 0;
            cnt_t <=0;
            pwm<=0;
        end
    end
end

endmodule

HW/03GRUPO3/02verilog/PWM_Top/pwm_top.v
//`timescale 1ns/1ps

module pwm_top (
    input clk,
    input res,
    input rd,
    input wr,
    input [31:0] data_in,
    input [31:0] addr,
    output pwm7,
    output pwm6,
    output pwm5,
    output pwm4,
    output pwm3,
    output pwm2,
    output pwm1,
    output pwm0,
    output reg [31:0] data_out
);

//Memory Map Registers

reg [31:0] e0;
reg [31:0] d0;
reg [31:0] t0;
reg [31:0] e1;
reg [31:0] d1;
reg [31:0] t1;
reg [31:0] e2;
reg [31:0] d2;
reg [31:0] t2;
reg [31:0] e3;
reg [31:0] d3;
reg [31:0] t3;
reg [31:0] e4;
reg [31:0] d4;
reg [31:0] t4;
reg [31:0] e5;
reg [31:0] d5;
reg [31:0] t5;
reg [31:0] e6;
reg [31:0] d6;
reg [31:0] t6;
reg [31:0] e7;
reg [31:0] d7;
reg [31:0] t7;

//PWM modules instances

pwm_servo0 servo0 (.enable(e0), .clk(clk), .reset(res), .d(d0), .t(t0), .pwm(pwm0));
pwm_servo1 servo1 (.enable(e1), .clk(clk), .reset(res), .d(d1), .t(t1), .pwm(pwm1));
pwm_servo2 servo2 (.enable(e2), .clk(clk), .reset(res), .d(d2), .t(t2), .pwm(pwm2));
pwm_servo3 servo3 (.enable(e3), .clk(clk), .reset(res), .d(d3), .t(t3), .pwm(pwm3));
pwm_servo4 servo4 (.enable(e4), .clk(clk), .reset(res), .d(d4), .t(t4), .pwm(pwm4));
pwm_servo5 servo5 (.enable(e5), .clk(clk), .reset(res), .d(d5), .t(t5), .pwm(pwm5));
pwm_servo6 servo6 (.enable(e6), .clk(clk), .reset(res), .d(d6), .t(t6), .pwm(pwm6));
pwm_servo7 servo7 (.enable(e7), .clk(clk), .reset(res), .d(d7), .t(t7), .pwm(pwm7));

//Demux 1 to 21

always @(posedge clk)begin
    if(res)begin
    data_out<=32'b0;
    end
    else if(wr)begin  
        case(addr)
        16'h00: begin 
        e0 <= data_in;
        end
    
        16'h04: begin 
        d0 <= data_in;
        end
    
        16'h08: begin 
        t0 <= data_in;
        end
    
        16'h0C: begin 
        e1 <= data_in;
        end
    
        16'h10: begin 
        d1 <= data_in;
        end
    
        16'h14: begin 
        t1 <= data_in;
        end
    
        16'h18: begin 
        e2 <= data_in;
        end
    
        16'h1C: begin 
        d2 <= data_in;
        end
    
        16'h20: begin 
        t2 <= data_in;
        end
    
        16'h24: begin 
        e3 <= data_in;
        end
    
        16'h28: begin 
        d3 <= data_in;
        end
    
        16'h2C: begin 
        t3 <= data_in;
        end
    
        16'h30: begin 
        e4 <= data_in;
        end
    
        16'h34: begin 
        d4 <= data_in;
        end
    
        16'h38: begin 
        t4 <= data_in;
        end
    
        16'h3C: begin 
        e5 = data_in;
        end
    
    
        16'h40: begin 
        d5 <= data_in;
        end
    
        16'h44: begin 
        t5 <= data_in;
        end
    
        16'h48: begin 
        e6 <= data_in;
        end
    
        16'h4C: begin 
        d6 <= data_in;
        end
     
        16'h50: begin 
        t6 <= data_in;
        end
    
        16'h54: begin 
        e7 <= data_in;
        end
    
        16'h58: begin 
        d7 <= data_in;
        end
    
        16'h5C: begin 
        t7 <= data_in;
        end
    
     endcase
    end
    else if (rd)begin
     case(addr)
        16'h00: begin 
        data_out <= e0;
        end
    
        16'h04: begin 
        data_out <= d0;
        end
    
        16'h08: begin 
        data_out <= t0;
        end
    
        16'h0C: begin 
        data_out <= e1;
        end
    
        16'h10: begin 
        data_out <= d1;
        end
    
        16'h14: begin 
        data_out <= t1;
        end
    
        16'h18: begin 
        data_out <= e2;
        end
    
        16'h1C: begin 
        data_out <= d2;
        end
    
        16'h20: begin 
        data_out <= t2;
        end
    
        16'h24: begin 
        data_out <= e3;
        end
    
        16'h28: begin 
        data_out <= d3;
        end
    
        16'h2C: begin 
        data_out <= t3;
        end
    
        16'h30: begin 
        data_out <= e4;
        end
    
        16'h34: begin 
        data_out <= d4;
        end
    
        16'h38: begin 
        data_out <= t4;
        end
    
        16'h3C: begin 
        data_out <= e5;
        end
    
    
        16'h40: begin 
        data_out <= d5;
        end
    
        16'h44: begin 
        data_out <= t5;
        end
    
        16'h48: begin 
        data_out <= e6;
        end
    
        16'h4C: begin 
        data_out <= d6 ;
        end
    
        16'h50: begin 
        data_out <= t6 ;
        end
    
        16'h54: begin 
        data_out <= e7 ;
        end
    
        16'h58: begin 
        data_out <= d7;
        end
    
        16'h5C: begin 
        data_out <= t7;
        end
    
      endcase
    end
end 
endmodule

HW/03GRUPO3/02verilog/PWM_Top/pwm_top_TB.v
//`timescale 1 ns/100 ps

module pwm_top_TB;
    reg clk=0;
    reg res=0;
    reg rd;
    reg wr;
    reg [31:0] data_in;
    reg [31:0] addr;

pwm_top uut(.clk(clk), .res(res), .rd(rd), .wr(wr), .data_in(data_in), .addr(addr));

always #1 clk = ~clk;

initial begin
wr=1'b1;
#10;
addr= 32'h08;
#10;
data_in=2000;
#10;
addr= 32'h04;
#10
data_in=130;
#10
addr= 32'h00;
#10
data_in=1;
#10000;
addr= 32'h5C;
#10;
data_in=2000;
#10;
addr= 32'h58;
#10;
data_in=50;
#10;
addr= 32'h54;
#10;
data_in=1;
#10000;
res=1;
end


initial begin: TEST_CASE
     $dumpfile("pwm_top_TB.vcd");
     $dumpvars(-1, uut);
     #(100000) $finish;
   


end
endmodule

HW/03GRUPO3/02verilog/LM32_PWM/rtl/wb_pwm/simulation/pwm_top_TB.vcd
$date
	Thu Apr 19 19:07:11 2018
$end
$version
	Icarus Verilog
$end
$timescale
	1s
$end
$scope module pwm_top_TB $end
$scope module uut $end
$var wire 32 ! addr [31:0] $end
$var wire 1 " clk $end
$var wire 32 # data_in [31:0] $end
$var wire 1 $ pwm0 $end
$var wire 1 % pwm1 $end
$var wire 1 & pwm2 $end
$var wire 1 ' pwm3 $end
$var wire 1 ( pwm4 $end
$var wire 1 ) pwm5 $end
$var wire 1 * pwm6 $end
$var wire 1 + pwm7 $end
$var wire 1 , rd $end
$var wire 1 - res $end
$var wire 1 . wr $end
$var reg 32 / d0 [31:0] $end
$var reg 32 0 d1 [31:0] $end
$var reg 32 1 d2 [31:0] $end
$var reg 32 2 d3 [31:0] $end
$var reg 32 3 d4 [31:0] $end
$var reg 32 4 d5 [31:0] $end
$var reg 32 5 d6 [31:0] $end
$var reg 32 6 d7 [31:0] $end
$var reg 32 7 data_out [31:0] $end
$var reg 32 8 e0 [31:0] $end
$var reg 32 9 e1 [31:0] $end
$var reg 32 : e2 [31:0] $end
$var reg 32 ; e3 [31:0] $end
$var reg 32 < e4 [31:0] $end
$var reg 32 = e5 [31:0] $end
$var reg 32 > e6 [31:0] $end
$var reg 32 ? e7 [31:0] $end
$var reg 32 @ t0 [31:0] $end
$var reg 32 A t1 [31:0] $end
$var reg 32 B t2 [31:0] $end
$var reg 32 C t3 [31:0] $end
$var reg 32 D t4 [31:0] $end
$var reg 32 E t5 [31:0] $end
$var reg 32 F t6 [31:0] $end
$var reg 32 G t7 [31:0] $end
$scope module servo0 $end
$var wire 1 " clk $end
$var wire 32 H d [31:0] $end
$var wire 1 I enable $end
$var wire 1 - reset $end
$var wire 32 J t [31:0] $end
$var reg 32 K cnt_d [31:0] $end
$var reg 32 L cnt_t [31:0] $end
$var reg 1 M pwm $end
$upscope $end
$scope module servo1 $end
$var wire 1 " clk $end
$var wire 32 N d [31:0] $end
$var wire 1 O enable $end
$var wire 1 - reset $end
$var wire 32 P t [31:0] $end
$var reg 32 Q cnt_d [31:0] $end
$var reg 32 R cnt_t [31:0] $end
$var reg 1 S pwm $end
$upscope $end
$scope module servo2 $end
$var wire 1 " clk $end
$var wire 32 T d [31:0] $end
$var wire 1 U enable $end
$var wire 1 - reset $end
$var wire 32 V t [31:0] $end
$var reg 32 W cnt_d [31:0] $end
$var reg 32 X cnt_t [31:0] $end
$var reg 1 Y pwm $end
$upscope $end
$scope module servo3 $end
$var wire 1 " clk $end
$var wire 32 Z d [31:0] $end
$var wire 1 [ enable $end
$var wire 1 - reset $end
$var wire 32 \ t [31:0] $end
$var reg 32 ] cnt_d [31:0] $end
$var reg 32 ^ cnt_t [31:0] $end
$var reg 1 _ pwm $end
$upscope $end
$scope module servo4 $end
$var wire 1 " clk $end
$var wire 32 ` d [31:0] $end
$var wire 1 a enable $end
$var wire 1 - reset $end
$var wire 32 b t [31:0] $end
$var reg 32 c cnt_d [31:0] $end
$var reg 32 d cnt_t [31:0] $end
$var reg 1 e pwm $end
$upscope $end
$scope module servo5 $end
$var wire 1 " clk $end
$var wire 32 f d [31:0] $end
$var wire 1 g enable $end
$var wire 1 - reset $end
$var wire 32 h t [31:0] $end
$var reg 32 i cnt_d [31:0] $end
$var reg 32 j cnt_t [31:0] $end
$var reg 1 k pwm $end
$upscope $end
$scope module servo6 $end
$var wire 1 " clk $end
$var wire 32 l d [31:0] $end
$var wire 1 m enable $end
$var wire 1 - reset $end
$var wire 32 n t [31:0] $end
$var reg 32 o cnt_d [31:0] $end
$var reg 32 p cnt_t [31:0] $end
$var reg 1 q pwm $end
$upscope $end
$scope module servo7 $end
$var wire 1 " clk $end
$var wire 32 r d [31:0] $end
$var wire 1 s enable $end
$var wire 1 - reset $end
$var wire 32 t t [31:0] $end
$var reg 32 u cnt_d [31:0] $end
$var reg 32 v cnt_t [31:0] $end
$var reg 1 w pwm $end
$upscope $end
$upscope $end
$upscope $end
$enddefinitions $end
#0
$dumpvars
0w
b0 v
b0 u
bx t
xs
bx r
0q
b0 p
b0 o
bx n
xm
bx l
0k
b0 j
b0 i
bx h
xg
bx f
0e
b0 d
b0 c
bx b
xa
bx `
0_
b0 ^
b0 ]
bx \
x[
bx Z
0Y
b0 X
b0 W
bx V
xU
bx T
0S
b0 R
b0 Q
bx P
xO
bx N
0M
b0 L
b0 K
bx J
xI
bx H
bx G
bx F
bx E
bx D
bx C
bx B
bx A
bx @
bx ?
bx >
bx =
bx <
bx ;
bx :
bx 9
bx 8
bx 7
bx 6
bx 5
bx 4
bx 3
bx 2
bx 1
bx 0
bx /
1.
0-
x,
0+
0*
0)
0(
0'
0&
0%
0$
bx #
0"
bx !
$end
#1
1"
#2
0"
#3
1"
#4
0"
#5
1"
#6
0"
#7
1"
#8
0"
#9
1"
#10
0"
b1000 !
#11
1"
#12
0"
#13
1"
#14
0"
#15
1"
#16
0"
#17
1"
#18
0"
#19
1"
#20
0"
b11111010000 #
#21
b11111010000 @
b11111010000 J
1"
#22
0"
#23
1"
#24
0"
#25
1"
#26
0"
#27
1"
#28
0"
#29
1"
#30
0"
b100 !
#31
b11111010000 /
b11111010000 H
1"
#32
0"
#33
1M
1$
b1 K
1"
#34
0"
#35
b10 K
1"
#36
0"
#37
b11 K
1"
#38
0"
#39
b100 K
1"
#40
0"
b10000010 #
#41
b101 K
b10000010 /
b10000010 H
1"
#42
0"
#43
b110 K
1"
#44
0"
#45
b111 K
1"
#46
0"
#47
b1000 K
1"
#48
0"
#49
b1001 K
1"
#50
0"
b0 !
#51
0I
b10000010 8
b1010 K
1"
#52
0"
#53
b1011 K
1"
#54
0"
#55
b1100 K
1"
#56
0"
#57
b1101 K
1"
#58
0"
#59
b1110 K
1"
#60
0"
b1 #
#61
1I
b1111 K
b1 8
1"
#62
0"
#63
b10000 K
1"
#64
0"
#65
b10001 K
1"
#66
0"
#67
b10010 K
1"
#68
0"
#69
b10011 K
1"
#70
0"
#71
b10100 K
1"
#72
0"
#73
b10101 K
1"
#74
0"
#75
b10110 K
1"
#76
0"
#77
b10111 K
1"
#78
0"
#79
b11000 K
1"
#80
0"
#81
b11001 K
1"
#82
0"
#83
b11010 K
1"
#84
0"
#85
b11011 K
1"
#86
0"
#87
b11100 K
1"
#88
0"
#89
b11101 K
1"
#90
0"
#91
b11110 K
1"
#92
0"
#93
b11111 K
1"
#94
0"
#95
b100000 K
1"
#96
0"
#97
b100001 K
1"
#98
0"
#99
b100010 K
1"
#100
0"
#101
b100011 K
1"
#102
0"
#103
b100100 K
1"
#104
0"
#105
b100101 K
1"
#106
0"
#107
b100110 K
1"
#108
0"
#109
b100111 K
1"
#110
0"
#111
b101000 K
1"
#112
0"
#113
b101001 K
1"
#114
0"
#115
b101010 K
1"
#116
0"
#117
b101011 K
1"
#118
0"
#119
b101100 K
1"
#120
0"
#121
b101101 K
1"
#122
0"
#123
b101110 K
1"
#124
0"
#125
b101111 K
1"
#126
0"
#127
b110000 K
1"
#128
0"
#129
b110001 K
1"
#130
0"
#131
b110010 K
1"
#132
0"
#133
b110011 K
1"
#134
0"
#135
b110100 K
1"
#136
0"
#137
b110101 K
1"
#138
0"
#139
b110110 K
1"
#140
0"
#141
b110111 K
1"
#142
0"
#143
b111000 K
1"
#144
0"
#145
b111001 K
1"
#146
0"
#147
b111010 K
1"
#148
0"
#149
b111011 K
1"
#150
0"
#151
b111100 K
1"
#152
0"
#153
b111101 K
1"
#154
0"
#155
b111110 K
1"
#156
0"
#157
b111111 K
1"
#158
0"
#159
b1000000 K
1"
#160
0"
#161
b1000001 K
1"
#162
0"
#163
b1000010 K
1"
#164
0"
#165
b1000011 K
1"
#166
0"
#167
b1000100 K
1"
#168
0"
#169
b1000101 K
1"
#170
0"
#171
b1000110 K
1"
#172
0"
#173
b1000111 K
1"
#174
0"
#175
b1001000 K
1"
#176
0"
#177
b1001001 K
1"
#178
0"
#179
b1001010 K
1"
#180
0"
#181
b1001011 K
1"
#182
0"
#183
b1001100 K
1"
#184
0"
#185
b1001101 K
1"
#186
0"
#187
b1001110 K
1"
#188
0"
#189
b1001111 K
1"
#190
0"
#191
b1010000 K
1"
#192
0"
#193
b1010001 K
1"
#194
0"
#195
b1010010 K
1"
#196
0"
#197
b1010011 K
1"
#198
0"
#199
b1010100 K
1"
#200
0"
#201
b1010101 K
1"
#202
0"
#203
b1010110 K
1"
#204
0"
#205
b1010111 K
1"
#206
0"
#207
b1011000 K
1"
#208
0"
#209
b1011001 K
1"
#210
0"
#211
b1011010 K
1"
#212
0"
#213
b1011011 K
1"
#214
0"
#215
b1011100 K
1"
#216
0"
#217
b1011101 K
1"
#218
0"
#219
b1011110 K
1"
#220
0"
#221
b1011111 K
1"
#222
0"
#223
b1100000 K
1"
#224
0"
#225
b1100001 K
1"
#226
0"
#227
b1100010 K
1"
#228
0"
#229
b1100011 K
1"
#230
0"
#231
b1100100 K
1"
#232
0"
#233
b1100101 K
1"
#234
0"
#235
b1100110 K
1"
#236
0"
#237
b1100111 K
1"
#238
0"
#239
b1101000 K
1"
#240
0"
#241
b1101001 K
1"
#242
0"
#243
b1101010 K
1"
#244
0"
#245
b1101011 K
1"
#246
0"
#247
b1101100 K
1"
#248
0"
#249
b1101101 K
1"
#250
0"
#251
b1101110 K
1"
#252
0"
#253
b1101111 K
1"
#254
0"
#255
b1110000 K
1"
#256
0"
#257
b1110001 K
1"
#258
0"
#259
b1110010 K
1"
#260
0"
#261
b1110011 K
1"
#262
0"
#263
b1110100 K
1"
#264
0"
#265
b1110101 K
1"
#266
0"
#267
b1110110 K
1"
#268
0"
#269
b1110111 K
1"
#270
0"
#271
b1111000 K
1"
#272
0"
#273
b1111001 K
1"
#274
0"
#275
b1111010 K
1"
#276
0"
#277
b1111011 K
1"
#278
0"
#279
b1111100 K
1"
#280
0"
#281
b1111101 K
1"
#282
0"
#283
b1111110 K
1"
#284
0"
#285
b1111111 K
1"
#286
0"
#287
b10000000 K
1"
#288
0"
#289
b10000001 K
1"
#290
0"
#291
b10000010 K
1"
#292
0"
#293
0M
0$
b1 L
1"
#294
0"
#295
b10 L
1"
#296
0"
#297
b11 L
1"
#298
0"
#299
b100 L
1"
#300
0"
#301
b101 L
1"
#302
0"
#303
b110 L
1"
#304
0"
#305
b111 L
1"
#306
0"
#307
b1000 L
1"
#308
0"
#309
b1001 L
1"
#310
0"
#311
b1010 L
1"
#312
0"
#313
b1011 L
1"
#314
0"
#315
b1100 L
1"
#316
0"
#317
b1101 L
1"
#318
0"
#319
b1110 L
1"
#320
0"
#321
b1111 L
1"
#322
0"
#323
b10000 L
1"
#324
0"
#325
b10001 L
1"
#326
0"
#327
b10010 L
1"
#328
0"
#329
b10011 L
1"
#330
0"
#331
b10100 L
1"
#332
0"
#333
b10101 L
1"
#334
0"
#335
b10110 L
1"
#336
0"
#337
b10111 L
1"
#338
0"
#339
b11000 L
1"
#340
0"
#341
b11001 L
1"
#342
0"
#343
b11010 L
1"
#344
0"
#345
b11011 L
1"
#346
0"
#347
b11100 L
1"
#348
0"
#349
b11101 L
1"
#350
0"
#351
b11110 L
1"
#352
0"
#353
b11111 L
1"
#354
0"
#355
b100000 L
1"
#356
0"
#357
b100001 L
1"
#358
0"
#359
b100010 L
1"
#360
0"
#361
b100011 L
1"
#362
0"
#363
b100100 L
1"
#364
0"
#365
b100101 L
1"
#366
0"
#367
b100110 L
1"
#368
0"
#369
b100111 L
1"
#370
0"
#371
b101000 L
1"
#372
0"
#373
b101001 L
1"
#374
0"
#375
b101010 L
1"
#376
0"
#377
b101011 L
1"
#378
0"
#379
b101100 L
1"
#380
0"
#381
b101101 L
1"
#382
0"
#383
b101110 L
1"
#384
0"
#385
b101111 L
1"
#386
0"
#387
b110000 L
1"
#388
0"
#389
b110001 L
1"
#390
0"
#391
b110010 L
1"
#392
0"
#393
b110011 L
1"
#394
0"
#395
b110100 L
1"
#396
0"
#397
b110101 L
1"
#398
0"
#399
b110110 L
1"
#400
0"
#401
b110111 L
1"
#402
0"
#403
b111000 L
1"
#404
0"
#405
b111001 L
1"
#406
0"
#407
b111010 L
1"
#408
0"
#409
b111011 L
1"
#410
0"
#411
b111100 L
1"
#412
0"
#413
b111101 L
1"
#414
0"
#415
b111110 L
1"
#416
0"
#417
b111111 L
1"
#418
0"
#419
b1000000 L
1"
#420
0"
#421
b1000001 L
1"
#422
0"
#423
b1000010 L
1"
#424
0"
#425
b1000011 L
1"
#426
0"
#427
b1000100 L
1"
#428
0"
#429
b1000101 L
1"
#430
0"
#431
b1000110 L
1"
#432
0"
#433
b1000111 L
1"
#434
0"
#435
b1001000 L
1"
#436
0"
#437
b1001001 L
1"
#438
0"
#439
b1001010 L
1"
#440
0"
#441
b1001011 L
1"
#442
0"
#443
b1001100 L
1"
#444
0"
#445
b1001101 L
1"
#446
0"
#447
b1001110 L
1"
#448
0"
#449
b1001111 L
1"
#450
0"
#451
b1010000 L
1"
#452
0"
#453
b1010001 L
1"
#454
0"
#455
b1010010 L
1"
#456
0"
#457
b1010011 L
1"
#458
0"
#459
b1010100 L
1"
#460
0"
#461
b1010101 L
1"
#462
0"
#463
b1010110 L
1"
#464
0"
#465
b1010111 L
1"
#466
0"
#467
b1011000 L
1"
#468
0"
#469
b1011001 L
1"
#470
0"
#471
b1011010 L
1"
#472
0"
#473
b1011011 L
1"
#474
0"
#475
b1011100 L
1"
#476
0"
#477
b1011101 L
1"
#478
0"
#479
b1011110 L
1"
#480
0"
#481
b1011111 L
1"
#482
0"
#483
b1100000 L
1"
#484
0"
#485
b1100001 L
1"
#486
0"
#487
b1100010 L
1"
#488
0"
#489
b1100011 L
1"
#490
0"
#491
b1100100 L
1"
#492
0"
#493
b1100101 L
1"
#494
0"
#495
b1100110 L
1"
#496
0"
#497
b1100111 L
1"
#498
0"
#499
b1101000 L
1"
#500
0"
#501
b1101001 L
1"
#502
0"
#503
b1101010 L
1"
#504
0"
#505
b1101011 L
1"
#506
0"
#507
b1101100 L
1"
#508
0"
#509
b1101101 L
1"
#510
0"
#511
b1101110 L
1"
#512
0"
#513
b1101111 L
1"
#514
0"
#515
b1110000 L
1"
#516
0"
#517
b1110001 L
1"
#518
0"
#519
b1110010 L
1"
#520
0"
#521
b1110011 L
1"
#522
0"
#523
b1110100 L
1"
#524
0"
#525
b1110101 L
1"
#526
0"
#527
b1110110 L
1"
#528
0"
#529
b1110111 L
1"
#530
0"
#531
b1111000 L
1"
#532
0"
#533
b1111001 L
1"
#534
0"
#535
b1111010 L
1"
#536
0"
#537
b1111011 L
1"
#538
0"
#539
b1111100 L
1"
#540
0"
#541
b1111101 L
1"
#542
0"
#543
b1111110 L
1"
#544
0"
#545
b1111111 L
1"
#546
0"
#547
b10000000 L
1"
#548
0"
#549
b10000001 L
1"
#550
0"
#551
b10000010 L
1"
#552
0"
#553
b10000011 L
1"
#554
0"
#555
b10000100 L
1"
#556
0"
#557
b10000101 L
1"
#558
0"
#559
b10000110 L
1"
#560
0"
#561
b10000111 L
1"
#562
0"
#563
b10001000 L
1"
#564
0"
#565
b10001001 L
1"
#566
0"
#567
b10001010 L
1"
#568
0"
#569
b10001011 L
1"
#570
0"
#571
b10001100 L
1"
#572
0"
#573
b10001101 L
1"
#574
0"
#575
b10001110 L
1"
#576
0"
#577
b10001111 L
1"
#578
0"
#579
b10010000 L
1"
#580
0"
#581
b10010001 L
1"
#582
0"
#583
b10010010 L
1"
#584
0"
#585
b10010011 L
1"
#586
0"
#587
b10010100 L
1"
#588
0"
#589
b10010101 L
1"
#590
0"
#591
b10010110 L
1"
#592
0"
#593
b10010111 L
1"
#594
0"
#595
b10011000 L
1"
#596
0"
#597
b10011001 L
1"
#598
0"
#599
b10011010 L
1"
#600
0"
#601
b10011011 L
1"
#602
0"
#603
b10011100 L
1"
#604
0"
#605
b10011101 L
1"
#606
0"
#607
b10011110 L
1"
#608
0"
#609
b10011111 L
1"
#610
0"
#611
b10100000 L
1"
#612
0"
#613
b10100001 L
1"
#614
0"
#615
b10100010 L
1"
#616
0"
#617
b10100011 L
1"
#618
0"
#619
b10100100 L
1"
#620
0"
#621
b10100101 L
1"
#622
0"
#623
b10100110 L
1"
#624
0"
#625
b10100111 L
1"
#626
0"
#627
b10101000 L
1"
#628
0"
#629
b10101001 L
1"
#630
0"
#631
b10101010 L
1"
#632
0"
#633
b10101011 L
1"
#634
0"
#635
b10101100 L
1"
#636
0"
#637
b10101101 L
1"
#638
0"
#639
b10101110 L
1"
#640
0"
#641
b10101111 L
1"
#642
0"
#643
b10110000 L
1"
#644
0"
#645
b10110001 L
1"
#646
0"
#647
b10110010 L
1"
#648
0"
#649
b10110011 L
1"
#650
0"
#651
b10110100 L
1"
#652
0"
#653
b10110101 L
1"
#654
0"
#655
b10110110 L
1"
#656
0"
#657
b10110111 L
1"
#658
0"
#659
b10111000 L
1"
#660
0"
#661
b10111001 L
1"
#662
0"
#663
b10111010 L
1"
#664
0"
#665
b10111011 L
1"
#666
0"
#667
b10111100 L
1"
#668
0"
#669
b10111101 L
1"
#670
0"
#671
b10111110 L
1"
#672
0"
#673
b10111111 L
1"
#674
0"
#675
b11000000 L
1"
#676
0"
#677
b11000001 L
1"
#678
0"
#679
b11000010 L
1"
#680
0"
#681
b11000011 L
1"
#682
0"
#683
b11000100 L
1"
#684
0"
#685
b11000101 L
1"
#686
0"
#687
b11000110 L
1"
#688
0"
#689
b11000111 L
1"
#690
0"
#691
b11001000 L
1"
#692
0"
#693
b11001001 L
1"
#694
0"
#695
b11001010 L
1"
#696
0"
#697
b11001011 L
1"
#698
0"
#699
b11001100 L
1"
#700
0"
#701
b11001101 L
1"
#702
0"
#703
b11001110 L
1"
#704
0"
#705
b11001111 L
1"
#706
0"
#707
b11010000 L
1"
#708
0"
#709
b11010001 L
1"
#710
0"
#711
b11010010 L
1"
#712
0"
#713
b11010011 L
1"
#714
0"
#715
b11010100 L
1"
#716
0"
#717
b11010101 L
1"
#718
0"
#719
b11010110 L
1"
#720
0"
#721
b11010111 L
1"
#722
0"
#723
b11011000 L
1"
#724
0"
#725
b11011001 L
1"
#726
0"
#727
b11011010 L
1"
#728
0"
#729
b11011011 L
1"
#730
0"
#731
b11011100 L
1"
#732
0"
#733
b11011101 L
1"
#734
0"
#735
b11011110 L
1"
#736
0"
#737
b11011111 L
1"
#738
0"
#739
b11100000 L
1"
#740
0"
#741
b11100001 L
1"
#742
0"
#743
b11100010 L
1"
#744
0"
#745
b11100011 L
1"
#746
0"
#747
b11100100 L
1"
#748
0"
#749
b11100101 L
1"
#750
0"
#751
b11100110 L
1"
#752
0"
