HW/01GRUPO1/02verilog/Proyecto_P/FIFO/div_freq.v
module div_freq #(
              parameter   fi     = 50000000,        //<- fFPGA/2=fi  
              parameter   fs	 = 36000000    ,    //<- flckout=fs
parameter   fi1     = 50000000,        //<- fFPGA/2=fi  
              parameter   fs1	 = 50000  ,      //<- flckout=fs
parameter   fi2     = 50000000,        //<- fFPGA/2=fi  
              parameter   fs2	 = 33000       //<- flckout=fs
  )(input clk, output reg clkout,output reg clkout1,output reg clkout2,input reset, input reset1, input reset2, output reg led, output reg led1, output reg led2);


initial clkout=0;
initial clkout1=0;
initial clkout2=0;

initial led=0;
initial led1=0;
initial led2=0;

reg [31:0] count;
initial count<= fi/fs;

reg [31:0] count1;
initial count1<= fi1/fs1;

reg [31:0] count2;
initial count2<= fi2/fs2;

always @(posedge  clk)
begin
	if (reset) begin
	led=1;
		
		if (count==0)begin
			clkout <=~clkout;
			count <= fi/fs;
		end	
		else begin
		count <=count-1;
		end

	end
	else begin
	led=0;
		count <= fi/fs;
		clkout <=0;
	end	
end

always @(posedge  clk)
begin
	if (reset1) begin
	led1=1;
		
		if (count1==0)begin
			clkout1 <=~clkout1;
			count1 <= fi1/fs1;
		end	
		else begin
		count1 <=count1-1;
		end

	end
	else begin
	led1=0;
		count1 <= fi1/fs1;
		clkout1 <=0;
	end	
end

always @(posedge  clk)
begin
	if (reset2) begin
	led2=1;
		
		if (count2==0)begin
			clkout2 <=~clkout2;
			count2 <= fi2/fs2;
		end	
		else begin
		count2 <=count2-1;
		end

	end
	else begin
	led2=0;
		count2 <= fi2/fs2;
		clkout2 <=0;
	end	
end

endmodule

HW/01GRUPO1/02verilog/Proyecto_P/Camara/FIFO/datos.v
module datos (clock,d_in, enable);

input clock;
output reg [8:0] d_in;
input enable;
reg [8:0] count;

initial count<=0; 
initial d_in<=0;
always @(posedge  clock)
begin

	if (enable)

	begin

		if (count==2)
		begin
		d_in<=8'h0A;
		end
		else
		begin
		count<=count+1;
		end
		
		if (count==4)
		begin
		d_in<=8'h0C ;
		end
		else
		begin
		count<=count+1;		
		end		

		if (count==6)
		begin
		d_in<=8'h0E ;
		count<=0;
		end
		else
		begin
		count<=count+1;
		end	


	
	end
end
endmodule

HW/01GRUPO1/02verilog/Proyecto_P/FIFO/fifo.v
module fifo # (parameter abits = 14, dbits = 9)(
    input clk,
    input reset,
   // input href,
   // input vsync,
 // input [dbits-1:0] din,
    output empty,
    output full,
  output [dbits-1:0] dout,
	input rs,rs1,rs2,
	output l0,l1,l2,
	input rd,
	input enable
    );
wire [dbits-1:0]din;
wire clock,href,vsync;

datos dt(.clock(clock),.d_in(din),. enable(enable));
div_freq ucc (.clk(clk), .clkout(clock),.clkout1(href),.clkout2(vsync),.reset(rs), .reset1(rs1), .reset2(rs2), .led(l0), .led1(l1), .led2(l2));

wire wr;
reg [dbits-1:0] out;
assign wr = href & ~vsync;

reg [dbits-1:0] regarray[2**abits-1:0]; //number of words in fifo = 2^(number of address bits)
reg [abits-1:0] wr_reg, wr_next, wr_succ; //points to the register that needs to be written to
reg [abits-1:0] rd_reg, rd_next, rd_succ; //points to the register that needs to be read from
reg full_reg, empty_reg, full_next, empty_next;
 
assign wr_en = wr & ~full; //only write if write signal is high and fifo is not full
 
//always block for write operation
always @ (posedge clock)
 begin
  if(wr_en)
   regarray[wr_reg] <= din;  //at wr_reg location of regarray store what is given at din
 
 end
  
//always block for read operation
always @ (posedge clock)
 begin
  if(rd)
   out <= regarray[rd_reg];
 end
  
 
always @ (posedge clock or posedge reset)
 begin
  if (reset)
   begin
   wr_reg <= 0;
   rd_reg <= 0;
   full_reg <= 1'b0;
   empty_reg <= 1'b1;
   end
   
  else
   begin
   wr_reg <= wr_next; //created the next registers to avoid the error of mixing blocking and non blocking assignment to the same signal
   rd_reg <= rd_next;
   full_reg <= full_next;
   empty_reg <= empty_next;
   end
 end
  
always @(*)
 begin
  wr_succ = wr_reg + 1; //assigned to new value as wr_next cannot be tested for in same always block
  rd_succ = rd_reg + 1; //assigned to new value as rd_next cannot be tested for in same always block
  wr_next = wr_reg;  //defaults state stays the same
  rd_next = rd_reg;  //defaults state stays the same
  full_next = full_reg;  //defaults state stays the same
  empty_next = empty_reg;  //defaults state stays the same
   
   case({wr,rd})
    //2'b00: do nothing LOL..
     
    2'b01: //read
     begin
      if(~empty) //if fifo is not empty continue
       begin
        rd_next = rd_succ;
        full_next = 1'b0;
       if(rd_succ == wr_reg) //all data has been read
         empty_next = 1'b1;  //its empty again
       end
     end
     
    2'b10: //write
     begin
       
      if(~full) //if fifo is not full continue
       begin
        wr_next = wr_succ;
        empty_next = 1'b0;
        if(wr_succ == (2**abits-1)) //all registers have been written to
         full_next = 1'b1;   //its full now
       end
     end
      
    2'b11: //read and write
     begin
      wr_next = wr_succ;
      rd_next = rd_succ;
     end
     //no empty or full flag will be checked for or asserted in this state since data is being written to and read from together it can  not get full in this state.
    endcase
    
 
 end
 
assign full = full_reg;
assign empty = empty_reg;
assign dout = out;
endmodule

HW/01GRUPO1/02verilog/Proyecto_P/FIFO/fifo_TB.v
//----------------------------------------------------------------------------
`timescale 1 ns / 100 ps

module fifo_TB;

parameter tck              = 3;       // clock period in ns
//----------------------------------------------------------------------------
//----------------------------------------------------------------------------
reg rs,rs1,rs2;
reg clk;
reg rst;
reg rd;
/*reg [1:0] data_in;*/
reg enable;
//----------------------------------------------------------------------------
// Device Under Test 
//------------------------------------------------------------------

fifo  uut(.reset(rst),.clk(clk)/*,.din(data_in)*/,.rs(rs),.rs1(rs1),.rs2(rs2),.rd(rd),.enable(enable));


/* Clocking device */
initial begin
	
	clk <= 0;
	rst <=1;
#2;
	rst<=0;
	rs1 <=1;
rs <=1;
rs2 <=1;
enable <=1;
rd<=0;
	#(2*tck) rst=0;
#10000;
enable<=0;
#10000;

rs1 <=0;
rs2 <=0;
rd=0; 	 
#2000;
rd=1;
#2000;
rd=0;
#2000;
rd=1;
#2000;
rd=0;
#2000;
rd=1;
#2000;
rd=0;
#2000;
rd=1;
#2000;
rd=0;	
end

always #(tck/2) clk <= ~clk;


/*initial begin
#4;
data_in=1; #200; 

data_in=1;  #200; 
data_in=1;   #200; 
data_in=1;  #200; 
data_in=1;   #200; 
data_in=1;  #200; 
data_in=1;   #200; 

data_in=0;  #200; 
data_in=0;   #200; 
data_in=0;   #200; 
data_in=0;   #200; 
data_in=0; #200; 

data_in=1;   #200; 
data_in=1;   #200; 
data_in=1;   #200; 
data_in=1;  #200; 
data_in=1;  #200; 
rs2=0;
rs1=0;
rd <= ~rd;#200; 
rd <= ~rd;#200; 
rd <= ~rd;#200; 
rd <= ~rd;#200; 
rd <= ~rd;#200; 
rd <= ~rd;#200; 
rd <= ~rd;#200; 
rd <= ~rd;#200; 
rd <= ~rd;#200;
rd <= ~rd;#200; 
rd <= ~rd;#200; 
rd <= ~rd;#200; 
rd <= ~rd;#200; 
rd <= ~rd;#200; 
rd <= ~rd;#200; 
rd <= ~rd;#200; 
rd <= ~rd;#200; 
rd <= ~rd;#200;
rd <= ~rd;#200; 
rd <= ~rd;#200; 
rd <= ~rd;#200; 
rd <= ~rd;#200; 
rd <= ~rd;#200; 
rd <= ~rd;#200; 
rd <= ~rd;#200; 
rd <= ~rd;#200; 
rd <= ~rd;#200;
rd <= ~rd;#200; 
rd <= ~rd;#200; 
rd <= ~rd;#200; 
rd <= ~rd;#200; 
rd <= ~rd;#200; 
rd <= ~rd;#200; 
rd <= ~rd;#200; 
rd <= ~rd;#200; 
rd <= ~rd;#200;    

end*/

initial begin: TEST_CASE
     $dumpfile("fifo_TB.vcd");
     $dumpvars(-1, uut);
     #(200000) $finish;
   end

endmodule //

HW/01GRUPO1/02verilog/Proyecto_P/FIFO/simulation/fifo_TB.vcd
$date
	Mon Mar 12 16:48:40 2018
$end
$version
	Icarus Verilog
$end
$timescale
	100ps
$end
$scope module fifo_TB $end
$scope module uut $end
$var wire 1 ! clk $end
$var wire 9 " dout [8:0] $end
$var wire 1 # empty $end
$var wire 1 $ enable $end
$var wire 1 % rd $end
$var wire 1 & reset $end
$var wire 1 ' rs $end
$var wire 1 ( rs1 $end
$var wire 1 ) rs2 $end
$var wire 1 * wr $end
$var wire 1 + wr_en $end
$var wire 1 , vsync $end
$var wire 1 - l2 $end
$var wire 1 . l1 $end
$var wire 1 / l0 $end
$var wire 1 0 href $end
$var wire 1 1 full $end
$var wire 9 2 din [8:0] $end
$var wire 1 3 clock $end
$var reg 1 4 empty_next $end
$var reg 1 5 empty_reg $end
$var reg 1 6 full_next $end
$var reg 1 1 full_reg $end
$var reg 9 7 out [8:0] $end
$var reg 14 8 rd_next [13:0] $end
$var reg 14 9 rd_reg [13:0] $end
$var reg 14 : rd_succ [13:0] $end
$var reg 14 ; wr_next [13:0] $end
$var reg 14 < wr_reg [13:0] $end
$var reg 14 = wr_succ [13:0] $end
$scope module dt $end
$var wire 1 $ enable $end
$var wire 1 3 clock $end
$var reg 9 > count [8:0] $end
$var reg 9 ? d_in [8:0] $end
$upscope $end
$scope module ucc $end
$var wire 1 ! clk $end
$var wire 1 ' reset $end
$var wire 1 ( reset1 $end
$var wire 1 ) reset2 $end
$var reg 1 3 clkout $end
$var reg 1 0 clkout1 $end
$var reg 1 , clkout2 $end
$var reg 32 @ count [31:0] $end
$var reg 32 A count1 [31:0] $end
$var reg 32 B count2 [31:0] $end
$var reg 1 / led $end
$var reg 1 . led1 $end
$var reg 1 - led2 $end
$upscope $end
$upscope $end
$upscope $end
$enddefinitions $end
#0
$dumpvars
b10101101100 B
b10001010 A
b1 @
b0 ?
b0 >
b1 =
b0 <
b0 ;
b1 :
b0 9
b0 8
bx 7
06
15
14
03
b0 2
01
00
0/
0.
0-
0,
0+
0*
x)
x(
x'
1&
x%
x$
1#
bx "
0!
$end
#10
1!
#20
0!
0%
1$
1)
1'
1(
0&
#30
b10101101011 B
b10001001 A
b0 @
1-
1.
1/
1!
#40
0!
#50
b1 >
b1 @
13
b10001000 A
b10101101010 B
1!
#60
0!
#70
b10101101001 B
b10000111 A
b0 @
1!
#80
0!
#90
b1 @
03
b10000110 A
b10101101000 B
1!
#100
0!
#110
b10101100111 B
b10000101 A
b0 @
1!
#120
0!
#130
b10 >
b1 @
13
b10000100 A
b10101100110 B
1!
#140
0!
#150
b10101100101 B
b10000011 A
b0 @
1!
#160
0!
#170
b1 @
03
b10000010 A
b10101100100 B
1!
#180
0!
#190
b10101100011 B
b10000001 A
b0 @
1!
#200
0!
#210
b11 >
b1010 2
b1010 ?
b1 @
13
b10000000 A
b10101100010 B
1!
#220
0!
#230
b10101100001 B
b1111111 A
b0 @
1!
#240
0!
#250
b1 @
03
b1111110 A
b10101100000 B
1!
#260
0!
#270
b10101011111 B
b1111101 A
b0 @
1!
#280
0!
#290
b100 >
b1 @
13
b1111100 A
b10101011110 B
1!
#300
0!
#310
b10101011101 B
b1111011 A
b0 @
1!
#320
0!
#330
b1 @
03
b1111010 A
b10101011100 B
1!
#340
0!
#350
b10101011011 B
b1111001 A
b0 @
1!
#360
0!
#370
b1100 2
b1100 ?
b101 >
b1 @
13
b1111000 A
b10101011010 B
1!
#380
0!
#390
b10101011001 B
b1110111 A
b0 @
1!
#400
0!
#410
b1 @
03
b1110110 A
b10101011000 B
1!
#420
0!
#430
b10101010111 B
b1110101 A
b0 @
1!
#440
0!
#450
b110 >
b1 @
13
b1110100 A
b10101010110 B
1!
#460
0!
#470
b10101010101 B
b1110011 A
b0 @
1!
#480
0!
#490
b1 @
03
b1110010 A
b10101010100 B
1!
#500
0!
#510
b10101010011 B
b1110001 A
b0 @
1!
#520
0!
#530
b1110 2
b1110 ?
b0 >
b1 @
13
b1110000 A
b10101010010 B
1!
#540
0!
#550
b10101010001 B
b1101111 A
b0 @
1!
#560
0!
#570
b1 @
03
b1101110 A
b10101010000 B
1!
#580
0!
#590
b10101001111 B
b1101101 A
b0 @
1!
#600
0!
#610
b1 >
b1 @
13
b1101100 A
b10101001110 B
1!
#620
0!
#630
b10101001101 B
b1101011 A
b0 @
1!
#640
0!
#650
b1 @
03
b1101010 A
b10101001100 B
1!
#660
0!
#670
b10101001011 B
b1101001 A
b0 @
1!
#680
0!
#690
b10 >
b1 @
13
b1101000 A
b10101001010 B
1!
#700
0!
#710
b10101001001 B
b1100111 A
b0 @
1!
#720
0!
#730
b1 @
03
b1100110 A
b10101001000 B
1!
#740
0!
#750
b10101000111 B
b1100101 A
b0 @
1!
#760
0!
#770
b11 >
b1010 2
b1010 ?
b1 @
13
b1100100 A
b10101000110 B
1!
#780
0!
#790
b10101000101 B
b1100011 A
b0 @
1!
#800
0!
#810
b1 @
03
b1100010 A
b10101000100 B
1!
#820
0!
#830
b10101000011 B
b1100001 A
b0 @
1!
#840
0!
#850
b100 >
b1 @
13
b1100000 A
b10101000010 B
1!
#860
0!
#870
b10101000001 B
b1011111 A
b0 @
1!
#880
0!
#890
b1 @
03
b1011110 A
b10101000000 B
1!
#900
0!
#910
b10100111111 B
b1011101 A
b0 @
1!
#920
0!
#930
b1100 2
b1100 ?
b101 >
b1 @
13
b1011100 A
b10100111110 B
1!
#940
0!
#950
b10100111101 B
b1011011 A
b0 @
1!
#960
0!
#970
b1 @
03
b1011010 A
b10100111100 B
1!
#980
0!
#990
b10100111011 B
b1011001 A
b0 @
1!
#1000
0!
#1010
b110 >
b1 @
13
b1011000 A
b10100111010 B
1!
#1020
0!
#1030
b10100111001 B
b1010111 A
b0 @
1!
#1040
0!
#1050
b1 @
03
b1010110 A
b10100111000 B
1!
#1060
0!
#1070
b10100110111 B
b1010101 A
b0 @
1!
#1080
0!
#1090
b1110 2
b1110 ?
b0 >
b1 @
13
b1010100 A
b10100110110 B
1!
#1100
0!
#1110
b10100110101 B
b1010011 A
b0 @
1!
#1120
0!
#1130
b1 @
03
b1010010 A
b10100110100 B
1!
#1140
0!
#1150
b10100110011 B
b1010001 A
b0 @
1!
#1160
0!
#1170
b1 >
b1 @
13
b1010000 A
b10100110010 B
1!
#1180
0!
#1190
b10100110001 B
b1001111 A
b0 @
1!
#1200
0!
#1210
b1 @
03
b1001110 A
b10100110000 B
1!
#1220
0!
#1230
b10100101111 B
b1001101 A
b0 @
1!
#1240
0!
#1250
b10 >
b1 @
13
b1001100 A
b10100101110 B
1!
#1260
0!
#1270
b10100101101 B
b1001011 A
b0 @
1!
#1280
0!
#1290
b1 @
03
b1001010 A
b10100101100 B
1!
#1300
0!
#1310
b10100101011 B
b1001001 A
b0 @
1!
#1320
0!
#1330
b11 >
b1010 2
b1010 ?
b1 @
13
b1001000 A
b10100101010 B
1!
#1340
0!
#1350
b10100101001 B
b1000111 A
b0 @
1!
#1360
0!
#1370
b1 @
03
b1000110 A
b10100101000 B
1!
#1380
0!
#1390
b10100100111 B
b1000101 A
b0 @
1!
#1400
0!
#1410
b100 >
b1 @
13
b1000100 A
b10100100110 B
1!
#1420
0!
#1430
b10100100101 B
b1000011 A
b0 @
1!
#1440
0!
#1450
b1 @
03
b1000010 A
b10100100100 B
1!
#1460
0!
#1470
b10100100011 B
b1000001 A
b0 @
1!
#1480
0!
#1490
b1100 2
b1100 ?
b101 >
b1 @
13
b1000000 A
b10100100010 B
1!
#1500
0!
#1510
b10100100001 B
b111111 A
b0 @
1!
#1520
0!
#1530
b1 @
03
b111110 A
b10100100000 B
1!
#1540
0!
#1550
b10100011111 B
b111101 A
b0 @
1!
#1560
0!
#1570
b110 >
b1 @
13
b111100 A
b10100011110 B
1!
#1580
0!
#1590
b10100011101 B
b111011 A
b0 @
1!
#1600
0!
#1610
b1 @
03
b111010 A
b10100011100 B
1!
#1620
0!
#1630
b10100011011 B
b111001 A
b0 @
1!
#1640
0!
#1650
b1110 2
b1110 ?
b0 >
b1 @
13
b111000 A
b10100011010 B
1!
#1660
0!
#1670
b10100011001 B
b110111 A
b0 @
1!
#1680
0!
#1690
b1 @
03
b110110 A
b10100011000 B
1!
#1700
0!
#1710
b10100010111 B
b110101 A
b0 @
1!
#1720
0!
#1730
b1 >
b1 @
13
b110100 A
b10100010110 B
1!
#1740
0!
#1750
b10100010101 B
b110011 A
b0 @
1!
#1760
0!
#1770
b1 @
03
b110010 A
b10100010100 B
1!
#1780
0!
#1790
b10100010011 B
b110001 A
b0 @
1!
#1800
0!
#1810
b10 >
b1 @
13
b110000 A
b10100010010 B
1!
#1820
0!
#1830
b10100010001 B
b101111 A
b0 @
1!
#1840
0!
#1850
b1 @
03
b101110 A
b10100010000 B
1!
#1860
0!
#1870
b10100001111 B
b101101 A
b0 @
1!
#1880
0!
#1890
b11 >
b1010 2
b1010 ?
b1 @
13
b101100 A
b10100001110 B
1!
#1900
0!
#1910
b10100001101 B
b101011 A
b0 @
1!
#1920
0!
#1930
b1 @
03
b101010 A
b10100001100 B
1!
#1940
0!
#1950
b10100001011 B
b101001 A
b0 @
1!
#1960
0!
#1970
b100 >
b1 @
13
b101000 A
b10100001010 B
1!
#1980
0!
#1990
b10100001001 B
b100111 A
b0 @
1!
#2000
0!
#2010
b1 @
03
b100110 A
b10100001000 B
1!
#2020
0!
#2030
b10100000111 B
b100101 A
b0 @
1!
#2040
0!
#2050
b1100 2
b1100 ?
b101 >
b1 @
13
b100100 A
b10100000110 B
1!
#2060
0!
#2070
b10100000101 B
b100011 A
b0 @
1!
#2080
0!
#2090
b1 @
03
b100010 A
b10100000100 B
1!
#2100
0!
#2110
b10100000011 B
b100001 A
b0 @
1!
#2120
0!
#2130
b110 >
b1 @
13
b100000 A
b10100000010 B
1!
#2140
0!
#2150
b10100000001 B
b11111 A
b0 @
1!
#2160
0!
#2170
b1 @
03
b11110 A
b10100000000 B
1!
#2180
0!
#2190
b10011111111 B
b11101 A
b0 @
1!
#2200
0!
#2210
b1110 2
b1110 ?
b0 >
b1 @
13
b11100 A
b10011111110 B
1!
#2220
0!
#2230
b10011111101 B
b11011 A
b0 @
1!
#2240
0!
#2250
b1 @
03
b11010 A
b10011111100 B
1!
#2260
0!
#2270
b10011111011 B
b11001 A
b0 @
1!
#2280
0!
#2290
b1 >
b1 @
13
b11000 A
b10011111010 B
1!
#2300
0!
#2310
b10011111001 B
b10111 A
b0 @
1!
#2320
0!
#2330
b1 @
03
b10110 A
b10011111000 B
1!
#2340
0!
#2350
b10011110111 B
b10101 A
b0 @
1!
#2360
0!
#2370
b10 >
b1 @
13
b10100 A
b10011110110 B
1!
#2380
0!
#2390
b10011110101 B
b10011 A
b0 @
1!
#2400
0!
#2410
b1 @
03
b10010 A
b10011110100 B
1!
#2420
0!
#2430
b10011110011 B
b10001 A
b0 @
1!
#2440
0!
#2450
b11 >
b1010 2
b1010 ?
b1 @
13
b10000 A
b10011110010 B
1!
#2460
0!
#2470
b10011110001 B
b1111 A
b0 @
1!
#2480
0!
#2490
b1 @
03
b1110 A
b10011110000 B
1!
#2500
0!
#2510
b10011101111 B
b1101 A
b0 @
1!
#2520
0!
#2530
b100 >
b1 @
13
b1100 A
b10011101110 B
1!
#2540
0!
#2550
b10011101101 B
b1011 A
b0 @
1!
#2560
0!
#2570
b1 @
03
b1010 A
b10011101100 B
1!
#2580
0!
#2590
b10011101011 B
b1001 A
b0 @
1!
#2600
0!
#2610
b1100 2
b1100 ?
b101 >
b1 @
13
b1000 A
b10011101010 B
1!
#2620
0!
#2630
b10011101001 B
b111 A
b0 @
1!
#2640
0!
#2650
b1 @
03
b110 A
b10011101000 B
1!
#2660
0!
#2670
b10011100111 B
b101 A
b0 @
1!
#2680
0!
#2690
b110 >
b1 @
13
b100 A
b10011100110 B
1!
#2700
0!
#2710
b10011100101 B
b11 A
b0 @
1!
#2720
0!
#2730
b1 @
03
b10 A
b10011100100 B
1!
#2740
0!
#2750
b10011100011 B
b1 A
b0 @
1!
#2760
0!
#2770
b1110 2
b1110 ?
b0 >
b1 @
13
b0 A
b10011100010 B
1!
#2780
0!
#2790
1+
04
b1 ;
1*
b10011100001 B
b10001010 A
10
b0 @
1!
#2800
0!
#2810
b1 @
03
b10001001 A
b10011100000 B
1!
#2820
0!
#2830
b10011011111 B
b10001000 A
b0 @
1!
#2840
0!
#2850
b10 ;
b10 =
0#
05
b1 <
b1 >
b1 @
13
b10000111 A
b10011011110 B
1!
#2860
0!
#2870
b10011011101 B
b10000110 A
b0 @
1!
#2880
0!
#2890
b1 @
03
b10000101 A
b10011011100 B
1!
#2900
0!
#2910
b10011011011 B
b10000100 A
b0 @
1!
#2920
0!
#2930
b11 ;
b11 =
b10 <
b10 >
b1 @
13
b10000011 A
b10011011010 B
1!
#2940
0!
#2950
b10011011001 B
b10000010 A
b0 @
1!
#2960
0!
#2970
b1 @
03
b10000001 A
b10011011000 B
1!
#2980
0!
#2990
b10011010111 B
b10000000 A
b0 @
1!
#3000
0!
#3010
b100 ;
b100 =
b11 <
b11 >
b1010 2
b1010 ?
b1 @
13
b1111111 A
b10011010110 B
1!
#3020
0!
#3030
b10011010101 B
b1111110 A
b0 @
1!
#3040
0!
#3050
b1 @
03
b1111101 A
b10011010100 B
1!
#3060
0!
#3070
b10011010011 B
b1111100 A
b0 @
1!
#3080
0!
#3090
b101 ;
b101 =
b100 <
b100 >
b1 @
13
b1111011 A
b10011010010 B
1!
#3100
0!
#3110
b10011010001 B
b1111010 A
b0 @
1!
#3120
0!
#3130
b1 @
03
b1111001 A
b10011010000 B
1!
#3140
0!
#3150
b10011001111 B
b1111000 A
b0 @
1!
#3160
0!
#3170
b110 ;
b110 =
b101 <
b1100 2
b1100 ?
b101 >
b1 @
13
b1110111 A
b10011001110 B
1!
#3180
0!
#3190
b10011001101 B
b1110110 A
b0 @
1!
#3200
0!
#3210
b1 @
03
b1110101 A
b10011001100 B
1!
#3220
0!
#3230
b10011001011 B
b1110100 A
b0 @
1!
#3240
0!
#3250
b111 ;
b111 =
b110 <
b110 >
b1 @
13
b1110011 A
b10011001010 B
1!
#3260
0!
#3270
b10011001001 B
b1110010 A
b0 @
1!
#3280
0!
#3290
b1 @
03
b1110001 A
b10011001000 B
1!
#3300
0!
#3310
b10011000111 B
b1110000 A
b0 @
1!
#3320
0!
#3330
b1000 ;
b1000 =
b111 <
b1110 2
b1110 ?
b0 >
b1 @
13
b1101111 A
b10011000110 B
1!
#3340
0!
#3350
b10011000101 B
b1101110 A
b0 @
1!
#3360
0!
#3370
b1 @
03
b1101101 A
b10011000100 B
1!
#3380
0!
#3390
b10011000011 B
b1101100 A
b0 @
1!
#3400
0!
#3410
b1001 ;
b1001 =
b1000 <
b1 >
b1 @
13
b1101011 A
b10011000010 B
1!
#3420
0!
#3430
b10011000001 B
b1101010 A
b0 @
1!
#3440
0!
#3450
b1 @
03
b1101001 A
b10011000000 B
1!
#3460
0!
#3470
b10010111111 B
b1101000 A
b0 @
1!
#3480
0!
#3490
b1010 ;
b1010 =
b1001 <
b10 >
b1 @
13
b1100111 A
b10010111110 B
1!
#3500
0!
#3510
b10010111101 B
b1100110 A
b0 @
1!
#3520
0!
#3530
b1 @
03
b1100101 A
b10010111100 B
1!
#3540
0!
#3550
b10010111011 B
b1100100 A
b0 @
1!
#3560
0!
#3570
b1011 ;
b1011 =
b1010 <
b11 >
b1010 2
b1010 ?
b1 @
13
b1100011 A
b10010111010 B
1!
#3580
0!
#3590
b10010111001 B
b1100010 A
b0 @
1!
#3600
0!
#3610
b1 @
03
b1100001 A
b10010111000 B
1!
#3620
0!
#3630
b10010110111 B
b1100000 A
b0 @
1!
#3640
0!
#3650
b1100 ;
b1100 =
b1011 <
b100 >
b1 @
13
b1011111 A
b10010110110 B
1!
#3660
0!
#3670
b10010110101 B
b1011110 A
b0 @
1!
#3680
0!
#3690
b1 @
03
b1011101 A
b10010110100 B
1!
#3700
0!
#3710
b10010110011 B
b1011100 A
b0 @
1!
#3720
0!
#3730
b1101 ;
b1101 =
b1100 <
b1100 2
b1100 ?
b101 >
b1 @
13
b1011011 A
b10010110010 B
1!
#3740
0!
#3750
b10010110001 B
b1011010 A
b0 @
1!
#3760
0!
#3770
b1 @
03
b1011001 A
b10010110000 B
1!
#3780
0!
#3790
b10010101111 B
b1011000 A
b0 @
1!
#3800
0!
#3810
b1110 ;
b1110 =
b1101 <
b110 >
b1 @
13
b1010111 A
b10010101110 B
1!
#3820
0!
#3830
b10010101101 B
b1010110 A
b0 @
1!
#3840
0!
#3850
b1 @
03
b1010101 A
b10010101100 B
1!
#3860
0!
#3870
b10010101011 B
b1010100 A
b0 @
1!
#3880
0!
#3890
b1111 ;
b1111 =
b1110 <
b1110 2
b1110 ?
b0 >
b1 @
13
b1010011 A
b10010101010 B
1!
#3900
0!
#3910
b10010101001 B
b1010010 A
b0 @
1!
#3920
0!
#3930
b1 @
03
b1010001 A
b10010101000 B
1!
#3940
0!
#3950
b10010100111 B
b1010000 A
b0 @
1!
#3960
0!
#3970
b10000 ;
b10000 =
b1111 <
b1 >
b1 @
13
b1001111 A
b10010100110 B
1!
#3980
0!
#3990
b10010100101 B
b1001110 A
b0 @
1!
#4000
0!
#4010
b1 @
03
b1001101 A
b10010100100 B
1!
#4020
0!
#4030
b10010100011 B
b1001100 A
b0 @
1!
#4040
0!
#4050
b10001 ;
b10001 =
b10000 <
b10 >
b1 @
13
b1001011 A
b10010100010 B
1!
#4060
0!
#4070
b10010100001 B
b1001010 A
b0 @
1!
#4080
0!
#4090
b1 @
03
b1001001 A
b10010100000 B
1!
#4100
0!
#4110
b10010011111 B
b1001000 A
b0 @
1!
#4120
0!
#4130
b10010 ;
b10010 =
b10001 <
b11 >
b1010 2
b1010 ?
b1 @
13
b1000111 A
b10010011110 B
1!
#4140
0!
#4150
b10010011101 B
b1000110 A
b0 @
1!
#4160
0!
#4170
b1 @
03
b1000101 A
b10010011100 B
1!
#4180
0!
#4190
b10010011011 B
b1000100 A
b0 @
1!
#4200
0!
#4210
b10011 ;
b10011 =
b10010 <
b100 >
b1 @
13
b1000011 A
b10010011010 B
1!
#4220
0!
#4230
b10010011001 B
b1000010 A
b0 @
1!
#4240
0!
#4250
b1 @
03
b1000001 A
b10010011000 B
1!
#4260
0!
#4270
b10010010111 B
b1000000 A
b0 @
1!
#4280
0!
#4290
b10100 ;
b10100 =
b10011 <
b1100 2
b1100 ?
b101 >
b1 @
13
b111111 A
b10010010110 B
1!
#4300
0!
#4310
b10010010101 B
b111110 A
b0 @
1!
#4320
0!
#4330
b1 @
03
b111101 A
b10010010100 B
1!
#4340
0!
#4350
b10010010011 B
b111100 A
b0 @
1!
#4360
0!
#4370
b10101 ;
b10101 =
b10100 <
b110 >
b1 @
13
b111011 A
b10010010010 B
1!
#4380
0!
#4390
b10010010001 B
b111010 A
b0 @
1!
#4400
0!
#4410
b1 @
03
b111001 A
b10010010000 B
1!
#4420
0!
#4430
b10010001111 B
b111000 A
b0 @
1!
#4440
0!
#4450
b10110 ;
b10110 =
b10101 <
b1110 2
b1110 ?
b0 >
b1 @
13
b110111 A
b10010001110 B
1!
#4460
0!
#4470
b10010001101 B
b110110 A
b0 @
1!
#4480
0!
#4490
b1 @
03
b110101 A
b10010001100 B
1!
#4500
0!
#4510
b10010001011 B
b110100 A
b0 @
1!
#4520
0!
#4530
b10111 ;
b10111 =
b10110 <
b1 >
b1 @
13
b110011 A
b10010001010 B
1!
#4540
0!
#4550
b10010001001 B
b110010 A
b0 @
1!
#4560
0!
#4570
b1 @
03
b110001 A
b10010001000 B
1!
#4580
0!
#4590
b10010000111 B
b110000 A
b0 @
1!
#4600
0!
#4610
b11000 ;
b11000 =
b10111 <
b10 >
b1 @
13
b101111 A
b10010000110 B
1!
#4620
0!
#4630
b10010000101 B
b101110 A
b0 @
1!
#4640
0!
#4650
b1 @
03
b101101 A
b10010000100 B
1!
#4660
0!
#4670
b10010000011 B
b101100 A
b0 @
1!
#4680
0!
#4690
b11001 ;
b11001 =
b11000 <
b11 >
b1010 2
b1010 ?
b1 @
13
b101011 A
b10010000010 B
1!
#4700
0!
#4710
b10010000001 B
b101010 A
b0 @
1!
#4720
0!
#4730
b1 @
03
b101001 A
b10010000000 B
1!
#4740
0!
#4750
b10001111111 B
b101000 A
b0 @
1!
#4760
0!
#4770
b11010 ;
b11010 =
b11001 <
b100 >
b1 @
13
b100111 A
b10001111110 B
1!
#4780
0!
#4790
b10001111101 B
b100110 A
b0 @
1!
#4800
0!
#4810
b1 @
03
b100101 A
b10001111100 B
1!
#4820
0!
#4830
b10001111011 B
b100100 A
b0 @
1!
#4840
0!
#4850
b11011 ;
b11011 =
b11010 <
b1100 2
b1100 ?
b101 >
b1 @
13
b100011 A
b10001111010 B
1!
#4860
0!
#4870
b10001111001 B
b100010 A
b0 @
1!
#4880
0!
#4890
b1 @
03
b100001 A
b10001111000 B
1!
#4900
0!
#4910
b10001110111 B
b100000 A
b0 @
1!
#4920
0!
#4930
b11100 ;
b11100 =
b11011 <
b110 >
b1 @
13
b11111 A
b10001110110 B
1!
#4940
0!
#4950
b10001110101 B
b11110 A
b0 @
1!
#4960
0!
#4970
b1 @
03
b11101 A
b10001110100 B
1!
#4980
0!
#4990
b10001110011 B
b11100 A
b0 @
1!
#5000
0!
#5010
b11101 ;
b11101 =
b11100 <
b1110 2
b1110 ?
b0 >
b1 @
13
b11011 A
b10001110010 B
1!
#5020
0!
#5030
b10001110001 B
b11010 A
b0 @
1!
#5040
0!
#5050
b1 @
03
b11001 A
b10001110000 B
1!
#5060
0!
#5070
b10001101111 B
b11000 A
b0 @
1!
#5080
0!
#5090
b11110 ;
b11110 =
b11101 <
b1 >
b1 @
13
b10111 A
b10001101110 B
1!
#5100
0!
#5110
b10001101101 B
b10110 A
b0 @
1!
#5120
0!
#5130
b1 @
03
b10101 A
b10001101100 B
1!
#5140
0!
#5150
b10001101011 B
b10100 A
b0 @
1!
#5160
0!
