HW/01GRUPO1/02verilog/Liss/FIFO1/fifo.v
module fifo # (parameter abits = 4, dbits = 3)(
    input clock,
    input reset,
    input wr,
    input rd,
  input [dbits-1:0] din,
    output empty,
    output full,
  output [dbits-1:0] dout
    );



reg [dbits-1:0] out;

reg [dbits-1:0] regarray[2**abits-1:0]; //number of words in fifo = 2^(number of address bits)
reg [abits-1:0] wr_reg, wr_next, wr_succ; //points to the register that needs to be written to
reg [abits-1:0] rd_reg, rd_next, rd_succ; //points to the register that needs to be read from
reg full_reg, empty_reg, full_next, empty_next;
 
assign wr_en = wr & ~full; //only write if write signal is high and fifo is not full
 
//always block for write operation
always @ (posedge clock)
 begin
  if(wr_en)
   regarray[wr_reg] <= din;  //at wr_reg location of regarray store what is given at din
 
 end
  
//always block for read operation
always @ (posedge clock)
 begin
  if(rd)
   out <= regarray[rd_reg];
 end
  
 
always @ (posedge clock or posedge reset)
 begin
  if (reset)
   begin
   wr_reg <= 0;
   rd_reg <= 0;
   full_reg <= 1'b0;
   empty_reg <= 1'b1;
   end
   
  else
   begin
   wr_reg <= wr_next; //created the next registers to avoid the error of mixing blocking and non blocking assignment to the same signal
   rd_reg <= rd_next;
   full_reg <= full_next;
   empty_reg <= empty_next;
   end
 end
  
always @(*)
 begin
  wr_succ = wr_reg + 1; //assigned to new value as wr_next cannot be tested for in same always block
  rd_succ = rd_reg + 1; //assigned to new value as rd_next cannot be tested for in same always block
  wr_next = wr_reg;  //defaults state stays the same
  rd_next = rd_reg;  //defaults state stays the same
  full_next = full_reg;  //defaults state stays the same
  empty_next = empty_reg;  //defaults state stays the same
   
   case({wr,rd})
    //2'b00: do nothing LOL..
     
    2'b01: //read
     begin
      if(~empty) //if fifo is not empty continue
       begin
        rd_next = rd_succ;
        full_next = 1'b0;
       if(rd_succ == wr_reg) //all data has been read
         empty_next = 1'b1;  //its empty again
       end
     end
     
    2'b10: //write
     begin
       
      if(~full) //if fifo is not full continue
       begin
        wr_next = wr_succ;
        empty_next = 1'b0;
        if(wr_succ == (2**abits-1)) //all registers have been written to
         full_next = 1'b1;   //its full now
       end
     end
      
    2'b11: //read and write
     begin
      wr_next = wr_succ;
      rd_next = rd_succ;
     end
     //no empty or full flag will be checked for or asserted in this state since data is being written to and read from together it can  not get full in this state.
    endcase
    
 
 end
 
assign full = full_reg;
assign empty = empty_reg;
assign dout = out;
endmodule

HW/01GRUPO1/02verilog/Liss/FIFO1/fifo_TB.v
//----------------------------------------------------------------------------
`timescale 1 ns / 100 ps

module fifo_TB;

parameter tck              = 2;       // clock period in ns
//----------------------------------------------------------------------------
//----------------------------------------------------------------------------

reg clk;
reg rst;

reg rd,wr;
reg [7:0] data_in;

//----------------------------------------------------------------------------
// Device Under Test 
//------------------------------------------------------------------

fifo  uut(.reset(rst),.clock(clk),.rd(rd),.wr(wr),.din(data_in));


/* Clocking device */
initial begin
	clk <= 0;
	rst <=1;
	#(2*tck) rst=0;
	rd <=0;
	wr<=0;
end

always #(tck/2) clk <= ~clk;


initial begin
#4;
data_in="h"; #1 wr=1; #2 wr=0;
data_in="o"; #1 wr=1; #2 wr=0;
data_in="l"; #1 rd=1; wr=1; #2 rd=0; wr=0;
data_in="a"; #1 wr=1; #2 wr=0;
data_in=" "; #1 wr=1; #2 wr=0;
data_in="m"; #1 wr=1; #2 wr=0;
data_in="u"; #1 wr=1; #2 wr=0;
data_in="n"; #1 wr=1; #2 wr=0;
data_in="d"; #1 wr=1; #2 wr=0;
data_in="o"; #1 wr=1; #2 wr=0;
data_in="."; #1 wr=1; #2 wr=0;
data_in="1"; #1 wr=1; #2 wr=0;
data_in="2"; #1 wr=1; #2 wr=0;
data_in="3"; #1 wr=1; #2 wr=0;
data_in="4"; #1 wr=1; #2 wr=0;
data_in="5"; #1 wr=1; #2 wr=0;
data_in="6"; #1 wr=1; #2 wr=0;
data_in="7"; #1 wr=1; #2 wr=0;
data_in="8"; #1 wr=1; #2 wr=0;
data_in="9"; #1 wr=1; #2 wr=0;
data_in="0"; #1 wr=1; #2 wr=0;

#1 rd=1; #2 rd=0;
#1 rd=1; #2 rd=0;
#1 rd=1; #2 rd=0;

data_in="a"; #1 wr=1; rd=0;#2 wr=0;rd=1;
data_in="b"; #1 wr=1; #2 wr=0;
data_in="c"; #1 wr=1; #2 wr=0;
data_in="d"; #1 wr=1; #2 wr=0;

#1 rd=1; #2 rd=0;
#1 rd=1; #2 rd=0;
#1 rd=1; #2 rd=0;
#1 rd=1; #2 rd=0;
#1 rd=1; #2 rd=0;
#1 rd=1; #2 rd=0;
#1 rd=1; #2 rd=0;
#1 rd=1; #2 rd=0;
#1 rd=1; #2 rd=0;
#1 rd=1; #2 rd=0;
#1 rd=1; #2 rd=0;
#1 rd=1; #2 rd=0;
#1 rd=1; #2 rd=0;
#1 rd=1; #2 rd=0;
#1 rd=1; #2 rd=0;
#1 rd=1; #2 rd=0;
#1 rd=1; #2 rd=0;
#1 rd=1; #2 rd=0;


end
initial begin: TEST_CASE
     $dumpfile("fifo_TB.vcd");
     $dumpvars(-1, uut);
     #(200) $finish;
   end

endmodule //

HW/01GRUPO1/02verilog/Liss/FIFO1/simulation/fifo_TB.vcd
$date
	Mon Mar 12 15:36:12 2018
$end
$version
	Icarus Verilog
$end
$timescale
	100ps
$end
$scope module fifo_TB $end
$scope module uut $end
$var wire 1 ! clock $end
$var wire 3 " din [2:0] $end
$var wire 3 # dout [2:0] $end
$var wire 1 $ empty $end
$var wire 1 % rd $end
$var wire 1 & reset $end
$var wire 1 ' wr $end
$var wire 1 ( wr_en $end
$var wire 1 ) full $end
$var reg 1 * empty_next $end
$var reg 1 + empty_reg $end
$var reg 1 , full_next $end
$var reg 1 ) full_reg $end
$var reg 3 - out [2:0] $end
$var reg 4 . rd_next [3:0] $end
$var reg 4 / rd_reg [3:0] $end
$var reg 4 0 rd_succ [3:0] $end
$var reg 4 1 wr_next [3:0] $end
$var reg 4 2 wr_reg [3:0] $end
$var reg 4 3 wr_succ [3:0] $end
$upscope $end
$upscope $end
$enddefinitions $end
#0
$dumpvars
b1 3
b0 2
b0 1
b1 0
b0 /
b0 .
bx -
0,
1+
1*
0)
x(
x'
1&
x%
1$
bx #
bx "
0!
$end
#10
1!
#20
0!
#30
1!
#40
0(
0!
0'
0%
b0 "
0&
#50
b10 3
0$
0+
b1 2
1!
1(
0*
b10 1
1'
#60
0!
#70
1!
b111 "
0(
b1 1
0'
#80
0!
1(
b10 1
1'
#90
b11 1
b11 3
b10 2
1!
#100
0!
b100 "
0(
b10 1
0'
#110
b10 0
b100 3
b1 /
b11 2
b0 #
b0 -
1!
1(
b10 .
b100 1
1'
1%
#120
0!
#130
1!
b1 "
0(
b1 .
b11 1
0'
0%
#140
0!
1(
b100 1
1'
#150
b101 1
b101 3
b100 2
1!
#160
0!
b0 "
0(
b100 1
0'
#170
b110 3
b101 2
1!
1(
b110 1
1'
#180
0!
#190
1!
b101 "
0(
b101 1
0'
#200
0!
1(
b110 1
1'
#210
b111 1
b111 3
b110 2
1!
#220
0!
0(
b110 1
0'
#230
b1000 3
b111 2
1!
1(
b1000 1
1'
#240
0!
#250
1!
b110 "
0(
b111 1
0'
#260
0!
1(
b1000 1
1'
#270
b1001 1
b1001 3
b1000 2
1!
#280
0!
b100 "
0(
b1000 1
0'
#290
b1010 3
b1001 2
1!
1(
b1010 1
1'
#300
0!
#310
1!
b111 "
0(
b1001 1
0'
#320
0!
1(
b1010 1
1'
#330
b1011 1
b1011 3
b1010 2
1!
#340
0!
b110 "
0(
b1010 1
0'
#350
b1100 3
b1011 2
1!
1(
b1100 1
1'
#360
0!
#370
1!
b1 "
0(
b1011 1
0'
#380
0!
1(
b1100 1
1'
#390
b1101 1
b1101 3
b1100 2
1!
#400
0!
b10 "
0(
b1100 1
0'
#410
b1110 3
b1101 2
1!
1(
b1110 1
1'
#420
0!
#430
1!
b11 "
0(
b1101 1
0'
#440
0!
1(
b1110 1
1'
#450
1,
b1111 1
b1111 3
b1110 2
1!
#460
0!
b100 "
0(
0,
b1110 1
0'
#470
b0 3
1)
b1111 2
1!
0(
1,
b1111 1
1'
#480
0!
#490
1!
b101 "
0'
#500
0!
1'
#510
1!
#520
0!
b110 "
0'
#530
1!
1'
#540
0!
#550
1!
b111 "
0'
#560
0!
1'
#570
1!
#580
0!
b0 "
0'
#590
1!
1'
#600
0!
#610
1!
b1 "
0'
#620
0!
1'
#630
1!
#640
0!
b0 "
0'
#650
1!
1'
#660
0!
#670
1!
0'
#680
0!
0,
b10 .
1%
#690
b11 .
b11 0
0)
b10 /
b111 #
b111 -
1!
#700
0!
b10 .
0%
#710
b100 0
b11 /
b100 #
b100 -
1!
b100 .
1%
#720
0!
#730
1!
b11 .
0%
#740
0!
b100 .
1%
#750
b101 .
b101 0
b100 /
b1 #
b1 -
1!
#760
0!
b1 "
b100 .
0%
#770
b1 3
b0 2
1!
1(
b1 1
1'
#780
0!
#790
b110 0
b101 /
b0 #
b0 -
1!
b10 "
0(
b110 .
b0 1
1%
0'
#800
0!
1(
b1 1
b110 .
1'
#810
b111 .
b10 1
b111 0
b10 3
b110 /
b1 2
b101 #
b101 -
1!
#820
0!
b11 "
0(
b111 .
b1 1
0'
#830
b1000 0
b11 3
b111 /
b10 2
1!
1(
b11 1
b1000 .
1'
#840
0!
#850
b1001 0
b1000 /
b110 #
b110 -
1!
b100 "
0(
b1001 .
b10 1
0'
#860
0!
1(
b11 1
b1001 .
1'
#870
b1010 .
b100 1
b1010 0
b100 3
b1001 /
b11 2
b100 #
b100 -
1!
#880
0!
0(
b1010 .
b11 1
0'
#890
b1011 .
b1011 0
b1010 /
b111 #
b111 -
1!
#900
0!
#910
1!
b1010 .
0%
#920
0!
b1011 .
1%
#930
b1100 .
b1100 0
b1011 /
b110 #
b110 -
1!
#940
0!
b1011 .
0%
#950
b1101 0
b1100 /
b1 #
b1 -
1!
b1101 .
1%
#960
0!
#970
1!
b1100 .
0%
#980
0!
b1101 .
1%
#990
b1110 .
b1110 0
b1101 /
b10 #
b10 -
1!
#1000
0!
b1101 .
0%
#1010
b1111 0
b1110 /
b11 #
b11 -
1!
b1111 .
1%
#1020
0!
#1030
1!
b1110 .
0%
#1040
0!
b1111 .
1%
#1050
b0 .
b0 0
b1111 /
b100 #
b100 -
1!
#1060
0!
b1111 .
0%
#1070
b1 0
b0 /
b1 #
b1 -
1!
b1 .
1%
#1080
0!
#1090
1!
b0 .
0%
#1100
0!
b1 .
1%
#1110
b10 .
b10 0
b1 /
b10 #
b10 -
1!
#1120
0!
b1 .
0%
#1130
1*
b11 0
b10 /
b11 #
b11 -
1!
b11 .
1%
#1140
0!
#1150
1!
0*
b10 .
0%
#1160
0!
1*
b11 .
1%
#1170
b100 0
1$
1+
b11 /
b100 #
b100 -
1!
#1180
0!
0%
#1190
b1 #
b1 -
1!
1%
#1200
0!
#1210
1!
0%
#1220
0!
1%
#1230
1!
#1240
0!
0%
#1250
1!
1%
#1260
0!
#1270
1!
0%
#1280
0!
1%
#1290
1!
#1300
0!
0%
#1310
1!
1%
#1320
0!
#1330
1!
0%
#1340
0!
1%
#1350
1!
#1360
0!
0%
#1370
1!
1%
#1380
0!
#1390
1!
0%
#1400
0!
1%
#1410
1!
#1420
0!
0%
